Workbook

Sheet Summary
B2: Global temperature vs CO2, with natural-variability controls
B3: NASA GISTEMP v4 monthly anomalies × Mauna Loa CO2, Mar 1958 - Aug 2026, plus solar, ENSO, volcanic and full-forcing datasets. All numbers below are live links to the analysis tabs.
B5: Headline results
B6: Anthro-ERF regression scaled to F2x, °C per doubling (NOT TCR) | D6: Descriptive slope of T on log2(CO2), °C per doubling (NOT a response estimate) | F6: Detrended annual r (R² 0.40) | H6: Unexplained 2023-2025 residual (°C)
B7: =Forcing!T17 -> 1.6066886 | D7: =Annual!K4 -> 2.7423885 | F7: =Annual!K13 -> 0.63587131 | H7: =Volcanic!N39 -> 0.15129879
B8: ="Slope of annual T on anthropogenic ERF (ENSO controlled, 1959-2025) × F2x = 3.93 W/m². AR(1) 95% "&TEXT(Forcing!T20,"0.00")&" to "&TEXT(Forcing!U20,"0.00")&"; with F2x uncertainty "&TEXT(Forcing!T43,"0.00")&" to "&TEXT(Forcing!U43,"0.00")&"; with IGCC ERF uncertainty also propagated (Monte Carlo, Sensitivity!AC46) 1.43 to 1.78 at 90%. A historical-regression quantity, not the 1%/yr TCR experiment; numerical overlap with AR6 TCR is a comparison, not a validation." -> Slope of annual T on anthropogenic ERF (ENSO controlled, 1959-2025) × F2x = 3.93 W/m². AR(1) 95% 1.48 to 1.74; with F2x uncertainty 1.34 to 1.87; with IGCC ERF uncertainty also propagated (Monte Carlo, Sensitivity!AC46) 1.43 to 1.78 at 90%. A historical-regression quantity, not the 1%/yr TCR experiment; numerical overlap with AR6 TCR is a comparison, not a validation. | D8: ="Annual T on log2(CO2) alone, 67 years, R² 0.93; AR(1) 95% interval "&TEXT(Annual!K20,"0.00")&" to "&TEXT(Annual!L20,"0.00")&". Split sample: "&TEXT(Annual!K21,"0.00")&" (1959-91) vs "&TEXT(Annual!L21,"0.00")&" (1992-2025), a difference of only "&TEXT(Annual!K22,"0.0")&" adjusted SE. CO2 is collinear with total human forcing (r = 0.997), so this is NOT a CO2-only climate response." -> Annual T on log2(CO2) alone, 67 years, R² 0.93; AR(1) 95% interval 2.51 to 2.98. Split sample: 2.57 (1959-91) vs 3.19 (1992-2025), a difference of only 1.3 adjusted SE. CO2 is collinear with total human forcing (r = 0.997), so this is NOT a CO2-only climate response. | F8: Correlation of year-to-year wiggles after removing a linear time trend from both series. Shows the link is not only a shared trend; it does not remove ENSO or identify CO2 separately. | H8: ="Monthly: after CO2, ENSO and sulfate AOD. Annual, after full anthropogenic ERF (incl. aerosol change) + ENSO: "&TEXT(Forcing!T31,"+0.00")&"; with volcanic ERF incl. Hunga Tonga H2O as a regressor: "&TEXT(Forcing!T45,"+0.00")&". Persists under blocked cross-validation. Partly accounted for: see Recent 2023-25 tab (solar cycle 25 about half; ~0.07 °C remains, about one SE)." -> Monthly: after CO2, ENSO and sulfate AOD. Annual, after full anthropogenic ERF (incl. aerosol change) + ENSO: +0.14; with volcanic ERF incl. Hunga Tonga H2O as a regressor: +0.13. Persists under blocked cross-validation. Partly accounted for: see Recent 2023-25 tab (solar cycle 25 about half; ~0.07 °C remains, about one SE).
B10: How the fit improves as each control is added (monthly data)
B11: Model | C11: Months | D11: CO2, °C per doubling | E11: R² | F11: R² of previous model, same months | G11: Residual σ (°C) | H11: Lag-1 autocorr. (monthly) | I11: Added control coefficient | J11: Lag recovered | K11: Tab | M11: Model | N11: R² | O11: Residual σ
B12: CO2 only | C12: =Analysis!I7 -> 822 | D12: =Analysis!I11 -> 2.7335713 | E12: =Analysis!I12 -> 0.86092237 | G12: =ENSO!N7 -> 0.14507445 | H12: =ENSO!N8 -> 0.64377333 | K12: Analysis | M12: CO2 only | N12: =E12 -> 0.86092237 | O12: =G12 -> 0.14507445
B13: + ENSO (ONI, lag 3 mo) | C13: =ENSO!N18 -> 815 | D13: =ENSO!N15 -> 2.7467961 | E13: =ENSO!N17 -> 0.89162717 | F13: =ENSO!N22 -> 0.86058036 | G13: =ENSO!N19 -> 0.12801797 | H13: =ENSO!N20 -> 0.54654178 | I13: =ENSO!N16 -> 0.08703777 | J13: 3 months | K13: ENSO | M13: + ENSO | N13: =E13 -> 0.89162717 | O13: =G13 -> 0.12801797
B14: + volcanic AOD (lag 7 mo) | C14: =Volcanic!N19 -> 814 | D14: =Volcanic!N15 -> 2.7274259 | E14: =Volcanic!N18 -> 0.90076359 | F14: =Volcanic!N22 -> 0.89120225 | G14: =Volcanic!N20 -> 0.12208488 | H14: =Volcanic!N21 -> 0.50280224 | I14: =Volcanic!N17 -> -2.2003523 | J14: 6-8 months | K14: Volcanic | M14: + volcanic | N14: =E14 -> 0.90076359 | O14: =G14 -> 0.12208488
B15: + solar TSI (through 2023) | C15: =COUNT(Volcanic!F9:F791) -> 783 | D15: =Volcanic!N25 -> 2.6436323 | E15: =Volcanic!N29 -> 0.8932405 | F15: =Volcanic!N30 -> 0.88957834 | I15: =Volcanic!N28 -> 0.052957801 | J15: ~11-yr cycle | K15: Solar / Volcanic | M15: kernels | N15: =E16 -> 0.90365216 | O15: =G16 -> 0.11857711
B16: Exponential responses instead of single lags (CO2+ENSO+AOD) | C16: =Kernel!P18 -> 807 | D16: =Kernel!P14 -> 2.704174 | E16: =Kernel!P22 -> 0.90365216 | F16: =Kernel!P21 -> 0.89830013 | G16: =Kernel!P19 -> 0.11857711 | H16: =Kernel!P20 -> 0.47349 | J16: τ: ENSO 6 mo, AOD 12 mo | K16: Kernel
B17: Read each row against the "same months" column, not the row above. The CO2 column is NOT on matched months: the solar row's 2.64 is a window effect (CO2-only on the same 783 months is already 2.640, Volcanic!N31; see Analysis!H18 for end-point sensitivity). Coefficient units: ONI in °C of Niño 3.4 anomaly; AOD unitless (Pinatubo peak ≈ 0.11); TSI in W/m².
B19: What each control found
B20: Solar (TSI) | C20: No trend since 1958 in the TSI record used, and R² ≈ 0.00 on its own, so the Sun cannot be the warming trend in that record (confirmed with NOAA Solar CDR v3 on the Sensitivity tab). But an 11-year cycle consistent with the published ~0.1 °C swing appears in the residuals at ~0.07 °C per W/m² of TSI (~0.40 per W/m² of forcing). Adding TSI moves the CO2 slope from 2.640 to 2.644 on the same months; the apparent drop to 2.64 from 2.73 is the shorter window, not the Sun.
B21: ENSO (ONI) | C21: The dominant short-term noise. Best lag 3 months, ~0.09 °C per unit ONI, both consistent with textbook values (the lag was selected on this record, so this is consistency, not independent recovery). The ONI series used has essentially zero linear trend over the sample (its 30-year base periods are re-centred), so it absorbs none of the CO2 trend here and the CO2 coefficient does not materially move. ONI is not a complete ENSO control (RONI and ERSSTv6 exist; see data note).
B22: Volcanic (AOD) | C22: Best lag 6-8 months; implied peak cooling Pinatubo -0.25, Agung -0.18, El Chichón -0.13 °C. Transient response to a pulse (~0.13 °C per W/m²) is far below the sustained-forcing response (~0.40), which is why summing forcings of different duration and regressing makes the fit worse.
B23: Response kernels | C23: Replacing single lags with one-box exponential responses (τ ≈ 6 months for ENSO, 12 for volcanic AOD) improves the fit on identical months (R² 0.898 → 0.904) and leaves the CO2 coefficient at 2.70. τ was chosen on the full record; under blocked 7-fold cross-validation with τ and coefficients chosen out-of-fold, the same τ values are selected in nearly every fold and the pooled out-of-fold R² is 0.887 (CO2-only 0.838), so the specification is not an in-sample artefact, though the ΔR² is modestly optimistic. Filtering CO2 the same way has no R² optimum: the record cannot separate transient from equilibrium response.
B24: Full forcing (ERF) | C24: Anthropogenic ERF gives 0.40 °C per W/m², 1.6 °C per doubling when scaled by F2x (not TCR), inside the IPCC range. log2(CO2) and anthropogenic ERF are almost perfectly collinear (r = 0.997), so either fits equally well; this does NOT mean CO2 is a constant share of human forcing (its share falls from ~2.3× to ~0.75× of net anthropogenic ERF as aerosol offset shrinks), and the regression does not separate the components. Splitting human forcing into a warming term and an aerosol term gives the same response to each: 0.409 against 0.414 °C per W/m², a difference of -0.005 (Forcing!T21:T22). CORRECTED in v1.6: before that revision this split omitted the other anthropogenic column and reported 0.47 against 0.37, which was an omitted-variable artefact. The two series are nearly orthogonal over this record, so the regression does separate them, but because aerosol ERF is the widest uncertainty in AR6 the data fix the aerosol contribution rather than the response per W/m². See Open Items section B. Giving volcanic ERF its own coefficient gives R² 0.96 and leaves the F2x-scaled (not TCR) value at ~1.59. Aerosol ERF changes ~0.15 W/m² 2019-25 in this dataset, worth ~0.06 °C, so it explains part but not most of the 2023-25 excess.
B26: What this analysis does and does not show
B27: Does: over 1959-2025, log2(CO2) and anthropogenic ERF are interchangeable regressors (r = 0.997). GISTEMP regressed on that proxy plus ONI has in-sample R² ≈ 0.89 monthly and ≈ 0.95 annual; both are dominated by the shared trend, and after linear detrending the annual r is 0.64 (R² 0.40). On matched months, adding ONI, AOD or TSI leaves the CO2 slope within ~0.02 of its CO2-only value. Blocked cross-validation with lag structure and coefficients chosen out-of-fold gives pooled R² 0.887 (Kernel!P62:Q70). Scaling the anthropogenic-ERF slope by F2x gives 1.61 °C per doubling (95% 1.34 to 1.87 with F2x uncertainty; 1.43 to 1.78 at 90% with IGCC ERF uncertainty propagated, Sensitivity!AC46), which is numerically inside the AR6 TCR likely range; that is a comparison, not a validation, since it is not the TCR estimand.
B28: Does not: estimate equilibrium climate sensitivity (a 66-year single-realisation record cannot), and "scaled to F2x" means an observational regression estimate, not the formal 1%-per-year model experiment; establish causation by itself (that rests on radiative physics and fingerprints such as stratospheric cooling); or fully explain the 2023-25 excess warmth: the Recent 2023-25 tab accounts for roughly half of the annual-model residual with solar cycle 25, and the remainder (~0.07 °C) is about one standard error of a 3-year mean. Read that last comparison with the qualifier added in v1.7 at Recent 2023-25!B30:B32: the asymptotic AR(1) formula gives 0.067 for that standard error, the exact AR(1) variance of a mean of three gives 0.058, so the remainder is about 1.2 SE, and the residual BEFORE the solar line is about 2.2 SE. The budget is exploratory and the solar line carries its own unstated uncertainty.
B29: Statistics: all fits are ordinary least squares with autocorrelated residuals (lag-1 ≈ 0.5 monthly, ≈ 0.3 annual; effective n ≈ 40 annual). The monthly effective n of ≈ 290 quoted here before v1.7 came from the AR(1) factor and overstates the independent information: Newey-West out to 96 lags implies a variance inflation near 14, i.e. an effective n nearer 60 monthly (Diagnostics section D item 5). Nothing published rests on the monthly slope. AR(1)-inflated standard errors and 95% intervals are given for the two headline slopes (Annual!K17:L20, Forcing!T19:U20). Lag and τ values were chosen in-sample; Kernel!P51:P60 is only a coefficient holdout with τ fixed. The nested check is Kernel!P62:Q70: a single 1958-95 split cannot identify τ (long τ, degraded holdout), but blocked 7-fold cross-validation selects the same τ values out-of-fold and gives pooled R² 0.887 vs 0.904 in-sample. Newey-West SEs (1-6 lags) on the annual slope, 0.120-0.126, confirm the AR(1) correction.
B30: Data vintages (Sept 2026 review): ERF from the IGCC 2025 file (1750-2025), with its 5-95% percentile files used for uncertainty propagation. Main analysis uses NOAA CPC ONI on ERSSTv5, ClimateIndicator sulfate AOD (GloSSAC v2.23 basis) and NRLTSI2. The successors (ONI on ERSSTv6, GloSSAC v2.24, NOAA Solar CDR v3) were rerun on the Sensitivity tab; no result changes materially. Monthly AOD is sulfate only; Hunga Tonga stratospheric water vapour appears only in the annual volcanic ERF on the Forcing tab and in the Recent 2023-25 budget. HadCRUT5 and Berkeley Earth were run in place of GISTEMP (Sensitivity tab); the headline slopes change by at most 0.05 and the 2023-25 residual by 0.02-0.03 °C.
B31: Sources: NASA GISTEMP v4; NOAA GML Mauna Loa CO2; NRLTSI2 (LASP LISIRD); NOAA CPC ONI; ClimateIndicator/forcing-timeseries (Forster et al.) for volcanic AOD and all ERF series. Download dates and provenance are in the header-cell comments on each tab.
B33: Out-of-sample validation and residual diagnostics (added 2026-10-22)
B34: The two tables above are in-sample. The blocked cross-validation on the Kernel tab and the specification tests on the Diagnostics tab are the out-of-sample and residual checks.
B36: Out-of-sample fit: blocked 7-fold cross-validation, tau and coefficients chosen out-of-fold
B37: Model | C37: In-sample R^2 | D37: Out-of-fold R^2 | E37: Bias (degC) | F37: Source
B38: CO2 only (monthly) | C38: =E12 -> 0.86092237 | D38: =Kernel!P69 -> 0.838 | F38: Kernel!P69
B39: CO2 + ENSO + AOD, exponential responses | C39: =E16 -> 0.90365216 | D39: =Kernel!P66 -> 0.887 | E39: =Kernel!Q66 -> 0.003 | F39: Kernel!P66:Q66
B40: Same, tau fixed at (6, 12) | C40: =E16 -> 0.90365216 | D40: =Kernel!P68 -> 0.889 | E40: =Kernel!Q68 -> 0.003 | F40: Kernel!P68:Q68
B41: Judge the gain from the natural-variability controls on the out-of-fold column, 0.838 to 0.887, rather than on the in-sample 0.861 to 0.904 above. Bias is the mean out-of-fold prediction error in degC. Read the pooled figures with one caveat added in v1.6: pooled out-of-fold R^2 is dominated by the cross-decade trend, which a monotone CO2-only regressor extrapolates across blocks, so the CO2-only benchmark flatters itself. Within each fold the CO2-only R^2 is near zero or negative while the three-factor model cuts the RMSE in every fold; validate_kernels.py now prints both.
B43: Heteroskedasticity and variance clustering (Diagnostics tab)
B44: Breusch-Pagan and White on the monthly three-factor residuals are marginal to significant (p about 0.03 and 0.004) but the auxiliary regressions explain only 1 to 3 per cent of the squared residuals. The large ARCH statistics turn out to be an artefact of the level autocorrelation already documented here: after filtering it out, ARCH-LM at q = 1 falls from about 42 to under 1 (p about 0.4) and Breusch-Pagan is far from significant. On the two annual models almost nothing is detected (Breusch-Pagan p = 0.28 and 0.40), the one marginal statistic being White on the CO2-proxy model at p = 0.035 on 67 points. The corrections are not interchangeable: HC3, robust to heteroskedasticity alone, raises the slope standard errors by 18 per cent (annual CO2 proxy), 4 per cent (annual ERF) and 9 per cent (monthly); the AR(1) inflation addresses serial correlation only; Newey-West covers both. On both annual slopes the AR(1)-inflated standard errors published here are the widest or within a per cent of the widest of the four measures, so no published interval changes. The monthly slope, on which no interval is published, is the one place the AR(1) factor is not the conservative choice.
B45: Detail and live formulas: Diagnostics!AW5:BB51. Standard errors for all three slopes, naive against HC3, Newey-West and AR(1)-inflated: Diagnostics!AX31:BA33. The three questions the reviews left open, RONI as the ENSO control, whether the GHG-aerosol split is identified, and the CERES shortwave candidate for the 2023-25 remainder, are worked through on the Open Items tab.
B47: Workbook version
B48: Version | C48: 1.7.11 | D48: v1.0 = the Sept 2026 state; v1.1 to v1.7.4 were all issued 2026-10-22; v1.7.5 and v1.7.6 on 2026-10-23.
B49: Date of this revision | C49: 2026-10-23
B50: Maintainer | C50: Russ Nida
B51: Revision history: moved to the Change log tab in v1.7.5. The thirteen entries from v1.0 through v1.7.4 are there verbatim, with the version, date and type of each in their own columns, followed by the entries for the moves themselves.

Sheet Analysis
A1: Month/Year | B1: Year (decimal) | C1: Temp (°F) | D1: CO2 (ppm) | E1: Anomaly (°C vs 1951-80) | F1: log2(CO2/preindustrial)
A2: ='F Plus CO2'!A940 -> 3/1958 | B2: =VALUE(RIGHT(A2,4))+(VALUE(LEFT(A2,FIND("/",A2)-1))-0.5)/12 -> 1958.2083 | C2: ='F Plus CO2'!B940 -> 57.344 | D2: ='F Plus CO2'!C940 -> 315.71 | E2: =(C2-32)*5/9-$I$3 -> 0.08 | F2: =LOG(D2/$I$4,2) -> 0.17317313 | H2: Assumptions (edit yellow cells)
A3: ='F Plus CO2'!A941 -> 4/1958 | B3: =VALUE(RIGHT(A3,4))+(VALUE(LEFT(A3,FIND("/",A3)-1))-0.5)/12 -> 1958.2917 | C3: ='F Plus CO2'!B941 -> 57.218 | D3: ='F Plus CO2'!C941 -> 317.45 | E3: =(C3-32)*5/9-$I$3 -> 0.01 | F3: =LOG(D3/$I$4,2) -> 0.18110255 | H3: GISTEMP absolute baseline (°C) | I3: 14
A4: ='F Plus CO2'!A942 -> 5/1958 | B4: =VALUE(RIGHT(A4,4))+(VALUE(LEFT(A4,FIND("/",A4)-1))-0.5)/12 -> 1958.375 | C4: ='F Plus CO2'!B942 -> 57.308 | D4: ='F Plus CO2'!C942 -> 317.51 | E4: =(C4-32)*5/9-$I$3 -> 0.06 | F4: =LOG(D4/$I$4,2) -> 0.1813752 | H4: Preindustrial CO2 (ppm) | I4: 280
A5: ='F Plus CO2'!A943 -> 6/1958 | B5: =VALUE(RIGHT(A5,4))+(VALUE(LEFT(A5,FIND("/",A5)-1))-0.5)/12 -> 1958.4583 | C5: ='F Plus CO2'!B943 -> 57.038 | D5: ='F Plus CO2'!C943 -> 317.27 | E5: =(C5-32)*5/9-$I$3 -> -0.09 | F5: =LOG(D5/$I$4,2) -> 0.18028428
A6: ='F Plus CO2'!A944 -> 7/1958 | B6: =VALUE(RIGHT(A6,4))+(VALUE(LEFT(A6,FIND("/",A6)-1))-0.5)/12 -> 1958.5417 | C6: ='F Plus CO2'!B944 -> 57.29 | D6: ='F Plus CO2'!C944 -> 315.87 | E6: =(C6-32)*5/9-$I$3 -> 0.05 | F6: =LOG(D6/$I$4,2) -> 0.1739041 | H6: Fit statistics (all monthly pairs)
A7: ='F Plus CO2'!A945 -> 8/1958 | B7: =VALUE(RIGHT(A7,4))+(VALUE(LEFT(A7,FIND("/",A7)-1))-0.5)/12 -> 1958.625 | C7: ='F Plus CO2'!B945 -> 57.11 | D7: ='F Plus CO2'!C945 -> 314.93 | E7: =(C7-32)*5/9-$I$3 -> -0.05 | F7: =LOG(D7/$I$4,2) -> 0.16960437 | H7: Months in fit | I7: =COUNT($E$2:$E$823) -> 822
A8: ='F Plus CO2'!A946 -> 9/1958 | B8: =VALUE(RIGHT(A8,4))+(VALUE(LEFT(A8,FIND("/",A8)-1))-0.5)/12 -> 1958.7083 | C8: ='F Plus CO2'!B946 -> 57.146 | D8: ='F Plus CO2'!C946 -> 313.21 | E8: =(C8-32)*5/9-$I$3 -> -0.03 | F8: =LOG(D8/$I$4,2) -> 0.16170345 | H8: Slope, °C per 100 ppm | I8: =SLOPE($E$2:$E$823,$D$2:$D$823)*100 -> 1.0819022
A9: ='F Plus CO2'!A947 -> 10/1958 | B9: =VALUE(RIGHT(A9,4))+(VALUE(LEFT(A9,FIND("/",A9)-1))-0.5)/12 -> 1958.7917 | C9: ='F Plus CO2'!B947 -> 57.272 | D9: ='F Plus CO2'!C947 -> 312.42 | E9: =(C9-32)*5/9-$I$3 -> 0.04 | F9: =LOG(D9/$I$4,2) -> 0.15805999 | H9: Intercept (°C at 0 ppm) | I9: =INTERCEPT($E$2:$E$823,$D$2:$D$823) -> -3.5067569
A10: ='F Plus CO2'!A948 -> 11/1958 | B10: =VALUE(RIGHT(A10,4))+(VALUE(LEFT(A10,FIND("/",A10)-1))-0.5)/12 -> 1958.875 | C10: ='F Plus CO2'!B948 -> 57.236 | D10: ='F Plus CO2'!C948 -> 313.33 | E10: =(C10-32)*5/9-$I$3 -> 0.02 | F10: =LOG(D10/$I$4,2) -> 0.16225608 | H10: R², anomaly vs CO2 | I10: =RSQ($E$2:$E$823,$D$2:$D$823) -> 0.86577375
A11: ='F Plus CO2'!A949 -> 12/1958 | B11: =VALUE(RIGHT(A11,4))+(VALUE(LEFT(A11,FIND("/",A11)-1))-0.5)/12 -> 1958.9583 | C11: ='F Plus CO2'!B949 -> 57.218 | D11: ='F Plus CO2'!C949 -> 314.67 | E11: =(C11-32)*5/9-$I$3 -> 0.01 | F11: =LOG(D11/$I$4,2) -> 0.16841281 | H11: Slope, °C per doubling of CO2 | I11: =SLOPE($E$2:$E$823,$F$2:$F$823) -> 2.7335713
A12: ='F Plus CO2'!A950 -> 1/1959 | B12: =VALUE(RIGHT(A12,4))+(VALUE(LEFT(A12,FIND("/",A12)-1))-0.5)/12 -> 1959.0417 | C12: ='F Plus CO2'!B950 -> 57.344 | D12: ='F Plus CO2'!C950 -> 315.58 | E12: =(C12-32)*5/9-$I$3 -> 0.08 | F12: =LOG(D12/$I$4,2) -> 0.17257895 | H12: R², anomaly vs log2(CO2) | I12: =RSQ($E$2:$E$823,$F$2:$F$823) -> 0.86092237
A13: ='F Plus CO2'!A951 -> 2/1959 | B13: =VALUE(RIGHT(A13,4))+(VALUE(LEFT(A13,FIND("/",A13)-1))-0.5)/12 -> 1959.125 | C13: ='F Plus CO2'!B951 -> 57.326 | D13: ='F Plus CO2'!C951 -> 316.49 | E13: =(C13-32)*5/9-$I$3 -> 0.07 | F13: =LOG(D13/$I$4,2) -> 0.17673309 | H13: Correlation r | I13: =CORREL($E$2:$E$823,$D$2:$D$823) -> 0.93046964
A14: ='F Plus CO2'!A952 -> 3/1959 | B14: =VALUE(RIGHT(A14,4))+(VALUE(LEFT(A14,FIND("/",A14)-1))-0.5)/12 -> 1959.2083 | C14: ='F Plus CO2'!B952 -> 57.524 | D14: ='F Plus CO2'!C952 -> 316.65 | E14: =(C14-32)*5/9-$I$3 -> 0.18 | F14: =LOG(D14/$I$4,2) -> 0.17746225
A15: ='F Plus CO2'!A953 -> 4/1959 | B15: =VALUE(RIGHT(A15,4))+(VALUE(LEFT(A15,FIND("/",A15)-1))-0.5)/12 -> 1959.2917 | C15: ='F Plus CO2'!B953 -> 57.488 | D15: ='F Plus CO2'!C953 -> 317.72 | E15: =(C15-32)*5/9-$I$3 -> 0.16 | F15: =LOG(D15/$I$4,2) -> 0.18232908 | H15: Note: residuals are strongly autocorrelated (monthly ENSO/volcanic noise), so naive standard errors on these slopes would be too small. Slopes and R² are descriptive.
A16: ='F Plus CO2'!A954 -> 5/1959 | B16: =VALUE(RIGHT(A16,4))+(VALUE(LEFT(A16,FIND("/",A16)-1))-0.5)/12 -> 1959.375 | C16: ='F Plus CO2'!B954 -> 57.272 | D16: ='F Plus CO2'!C954 -> 318.29 | E16: =(C16-32)*5/9-$I$3 -> 0.04 | F16: =LOG(D16/$I$4,2) -> 0.184915 | H16: Sources: NASA GISTEMP v4 land+ocean monthly anomalies (tab GLB.Ts+dSST (4), via Temp Dev, C, F); NOAA GML Mauna Loa monthly mean CO2 (tab co2_mm_mlo, via F Plus CO2). Full provenance on the Sources tab and in DATA_SOURCES.md.
A17: ='F Plus CO2'!A955 -> 6/1959 | B17: =VALUE(RIGHT(A17,4))+(VALUE(LEFT(A17,FIND("/",A17)-1))-0.5)/12 -> 1959.4583 | C17: ='F Plus CO2'!B955 -> 57.254 | D17: ='F Plus CO2'!C955 -> 318.15 | E17: =(C17-32)*5/9-$I$3 -> 0.03 | F17: =LOG(D17/$I$4,2) -> 0.18428029
A18: ='F Plus CO2'!A956 -> 7/1959 | B18: =VALUE(RIGHT(A18,4))+(VALUE(LEFT(A18,FIND("/",A18)-1))-0.5)/12 -> 1959.5417 | C18: ='F Plus CO2'!B956 -> 57.254 | D18: ='F Plus CO2'!C956 -> 316.54 | E18: =(C18-32)*5/9-$I$3 -> 0.03 | F18: =LOG(D18/$I$4,2) -> 0.17696099 | H18: End-point sensitivity: monthly CO2-only slope (°C per doubling) by last month included
A19: ='F Plus CO2'!A957 -> 8/1959 | B19: =VALUE(RIGHT(A19,4))+(VALUE(LEFT(A19,FIND("/",A19)-1))-0.5)/12 -> 1959.625 | C19: ='F Plus CO2'!B957 -> 57.182 | D19: ='F Plus CO2'!C957 -> 314.8 | E19: =(C19-32)*5/9-$I$3 -> -0.01 | F19: =LOG(D19/$I$4,2) -> 0.16900871 | H19: through Dec 2022 | I19: =SLOPE($E$2:$E$779,$F$2:$F$779) -> 2.5849313
A20: ='F Plus CO2'!A958 -> 9/1959 | B20: =VALUE(RIGHT(A20,4))+(VALUE(LEFT(A20,FIND("/",A20)-1))-0.5)/12 -> 1959.7083 | C20: ='F Plus CO2'!B958 -> 57.092 | D20: ='F Plus CO2'!C958 -> 313.84 | E20: =(C20-32)*5/9-$I$3 -> -0.06 | F20: =LOG(D20/$I$4,2) -> 0.16460241 | H20: through Dec 2023 | I20: =SLOPE($E$2:$E$791,$F$2:$F$791) -> 2.62928
A21: ='F Plus CO2'!A959 -> 10/1959 | B21: =VALUE(RIGHT(A21,4))+(VALUE(LEFT(A21,FIND("/",A21)-1))-0.5)/12 -> 1959.7917 | C21: ='F Plus CO2'!B959 -> 57.074 | D21: ='F Plus CO2'!C959 -> 313.33 | E21: =(C21-32)*5/9-$I$3 -> -0.07 | F21: =LOG(D21/$I$4,2) -> 0.16225608 | H21: through Dec 2024 | I21: =SLOPE($E$2:$E$803,$F$2:$F$803) -> 2.6884783
A22: ='F Plus CO2'!A960 -> 11/1959 | B22: =VALUE(RIGHT(A22,4))+(VALUE(LEFT(A22,FIND("/",A22)-1))-0.5)/12 -> 1959.875 | C22: ='F Plus CO2'!B960 -> 57.056 | D22: ='F Plus CO2'!C960 -> 314.81 | E22: =(C22-32)*5/9-$I$3 -> -0.08 | F22: =LOG(D22/$I$4,2) -> 0.16905454 | H22: through Dec 2025 | I22: =SLOPE($E$2:$E$815,$F$2:$F$815) -> 2.7158666
A23: ='F Plus CO2'!A961 -> 12/1959 | B23: =VALUE(RIGHT(A23,4))+(VALUE(LEFT(A23,FIND("/",A23)-1))-0.5)/12 -> 1959.9583 | C23: ='F Plus CO2'!B961 -> 57.2 | D23: ='F Plus CO2'!C961 -> 315.58 | E23: =(C23-32)*5/9-$I$3 -> 0 | F23: =LOG(D23/$I$4,2) -> 0.17257895 | H23: through Aug 2026 (all) | I23: =SLOPE($E$2:$E$823,$F$2:$F$823) -> 2.7335713
A24: ='F Plus CO2'!A962 -> 1/1960 | B24: =VALUE(RIGHT(A24,4))+(VALUE(LEFT(A24,FIND("/",A24)-1))-0.5)/12 -> 1960.0417 | C24: ='F Plus CO2'!B962 -> 57.2 | D24: ='F Plus CO2'!C962 -> 316.43 | E24: =(C24-32)*5/9-$I$3 -> 0 | F24: =LOG(D24/$I$4,2) -> 0.17645956 | H24: The last three years lever the slope by ~0.15 °C per doubling. Any coefficient comparison must be made on identical months.
A25: ='F Plus CO2'!A963 -> 2/1960 | B25: =VALUE(RIGHT(A25,4))+(VALUE(LEFT(A25,FIND("/",A25)-1))-0.5)/12 -> 1960.125 | C25: ='F Plus CO2'!B963 -> 57.434 | D25: ='F Plus CO2'!C963 -> 316.98 | E25: =(C25-32)*5/9-$I$3 -> 0.13 | F25: =LOG(D25/$I$4,2) -> 0.17896499
A26: ='F Plus CO2'!A964 -> 3/1960 | B26: =VALUE(RIGHT(A26,4))+(VALUE(LEFT(A26,FIND("/",A26)-1))-0.5)/12 -> 1960.2083 | C26: ='F Plus CO2'!B964 -> 56.57 | D26: ='F Plus CO2'!C964 -> 317.58 | E26: =(C26-32)*5/9-$I$3 -> -0.35 | F26: =LOG(D26/$I$4,2) -> 0.18169323
A27: ='F Plus CO2'!A965 -> 4/1960 | B27: =VALUE(RIGHT(A27,4))+(VALUE(LEFT(A27,FIND("/",A27)-1))-0.5)/12 -> 1960.2917 | C27: ='F Plus CO2'!B965 -> 56.93 | D27: ='F Plus CO2'!C965 -> 319.03 | E27: =(C27-32)*5/9-$I$3 -> -0.15 | F27: =LOG(D27/$I$4,2) -> 0.18826527
A28: ='F Plus CO2'!A966 -> 5/1960 | B28: =VALUE(RIGHT(A28,4))+(VALUE(LEFT(A28,FIND("/",A28)-1))-0.5)/12 -> 1960.375 | C28: ='F Plus CO2'!B966 -> 57.056 | D28: ='F Plus CO2'!C966 -> 320.03 | E28: =(C28-32)*5/9-$I$3 -> -0.08 | F28: =LOG(D28/$I$4,2) -> 0.19278032
A29: ='F Plus CO2'!A967 -> 6/1960 | B29: =VALUE(RIGHT(A29,4))+(VALUE(LEFT(A29,FIND("/",A29)-1))-0.5)/12 -> 1960.4583 | C29: ='F Plus CO2'!B967 -> 57.128 | D29: ='F Plus CO2'!C967 -> 319.58 | E29: =(C29-32)*5/9-$I$3 -> -0.04 | F29: =LOG(D29/$I$4,2) -> 0.1907503
A30: ='F Plus CO2'!A968 -> 7/1960 | B30: =VALUE(RIGHT(A30,4))+(VALUE(LEFT(A30,FIND("/",A30)-1))-0.5)/12 -> 1960.5417 | C30: ='F Plus CO2'!B968 -> 57.128 | D30: ='F Plus CO2'!C968 -> 318.18 | E30: =(C30-32)*5/9-$I$3 -> -0.04 | F30: =LOG(D30/$I$4,2) -> 0.18441633
A31: ='F Plus CO2'!A969 -> 8/1960 | B31: =VALUE(RIGHT(A31,4))+(VALUE(LEFT(A31,FIND("/",A31)-1))-0.5)/12 -> 1960.625 | C31: ='F Plus CO2'!B969 -> 57.236 | D31: ='F Plus CO2'!C969 -> 315.9 | E31: =(C31-32)*5/9-$I$3 -> 0.02 | F31: =LOG(D31/$I$4,2) -> 0.17404111
A32: ='F Plus CO2'!A970 -> 9/1960 | B32: =VALUE(RIGHT(A32,4))+(VALUE(LEFT(A32,FIND("/",A32)-1))-0.5)/12 -> 1960.7083 | C32: ='F Plus CO2'!B970 -> 57.326 | D32: ='F Plus CO2'!C970 -> 314.17 | E32: =(C32-32)*5/9-$I$3 -> 0.07 | F32: =LOG(D32/$I$4,2) -> 0.1661186
A33: ='F Plus CO2'!A971 -> 10/1960 | B33: =VALUE(RIGHT(A33,4))+(VALUE(LEFT(A33,FIND("/",A33)-1))-0.5)/12 -> 1960.7917 | C33: ='F Plus CO2'!B971 -> 57.308 | D33: ='F Plus CO2'!C971 -> 313.83 | E33: =(C33-32)*5/9-$I$3 -> 0.06 | F33: =LOG(D33/$I$4,2) -> 0.16455644
A34: ='F Plus CO2'!A972 -> 11/1960 | B34: =VALUE(RIGHT(A34,4))+(VALUE(LEFT(A34,FIND("/",A34)-1))-0.5)/12 -> 1960.875 | C34: ='F Plus CO2'!B972 -> 57.002 | D34: ='F Plus CO2'!C972 -> 315 | E34: =(C34-32)*5/9-$I$3 -> -0.11 | F34: =LOG(D34/$I$4,2) -> 0.169925
A35: ='F Plus CO2'!A973 -> 12/1960 | B35: =VALUE(RIGHT(A35,4))+(VALUE(LEFT(A35,FIND("/",A35)-1))-0.5)/12 -> 1960.9583 | C35: ='F Plus CO2'!B973 -> 57.542 | D35: ='F Plus CO2'!C973 -> 316.19 | E35: =(C35-32)*5/9-$I$3 -> 0.19 | F35: =LOG(D35/$I$4,2) -> 0.17536491
A36: ='F Plus CO2'!A974 -> 1/1961 | B36: =VALUE(RIGHT(A36,4))+(VALUE(LEFT(A36,FIND("/",A36)-1))-0.5)/12 -> 1961.0417 | C36: ='F Plus CO2'!B974 -> 57.326 | D36: ='F Plus CO2'!C974 -> 316.89 | E36: =(C36-32)*5/9-$I$3 -> 0.07 | F36: =LOG(D36/$I$4,2) -> 0.17855531
... A823: ='F Plus CO2'!A1761 -> 8/2026 | B823: =VALUE(RIGHT(A823,4))+(VALUE(LEFT(A823,FIND("/",A823)-1))-0.5)/12 -> 2026.625 | C823: ='F Plus CO2'!B1761 -> 59.72 | D823: ='F Plus CO2'!C1761 -> 427.55 | E823: =(C823-32)*5/9-$I$3 -> 1.4 | F823: =LOG(D823/$I$4,2) -> 0.61066632

Sheet Annual
A1: Year | B1: Months | C1: Mean CO2 (ppm) | D1: Mean anomaly (°C) | E1: Mean log2(CO2/280) | F1: Anomaly, linear time trend removed | G1: log2 CO2, linear time trend removed | H1: Fit residual (anomaly - log fit)
A2: 1959 | B2: =COUNTIFS(Analysis!$B$2:$B$823,">="&A2,Analysis!$B$2:$B$823,"<"&(A2+1)) -> 12 | C2: =AVERAGEIFS(Analysis!$D$2:$D$823,Analysis!$B$2:$B$823,">="&A2,Analysis!$B$2:$B$823,"<"&(A2+1)) -> 315.98167 | D2: =AVERAGEIFS(Analysis!$E$2:$E$823,Analysis!$B$2:$B$823,">="&A2,Analysis!$B$2:$B$823,"<"&(A2+1)) -> 0.030833333 | E2: =AVERAGEIFS(Analysis!$F$2:$F$823,Analysis!$B$2:$B$823,">="&A2,Analysis!$B$2:$B$823,"<"&(A2+1)) -> 0.1743967 | F2: =D2-($K$8+$K$9*A2) -> 0.22531826 | G2: =E2-($K$10+$K$11*A2) -> 0.031613393 | H2: =D2-($K$5+$K$4*E2) -> 0.14510476 | J2: Annual-mean fit (full calendar years only)
A3: 1960 | B3: =COUNTIFS(Analysis!$B$2:$B$823,">="&A3,Analysis!$B$2:$B$823,"<"&(A3+1)) -> 12 | C3: =AVERAGEIFS(Analysis!$D$2:$D$823,Analysis!$B$2:$B$823,">="&A3,Analysis!$B$2:$B$823,"<"&(A3+1)) -> 316.90833 | D3: =AVERAGEIFS(Analysis!$E$2:$E$823,Analysis!$B$2:$B$823,">="&A3,Analysis!$B$2:$B$823,"<"&(A3+1)) -> -0.025 | E3: =AVERAGEIFS(Analysis!$F$2:$F$823,Analysis!$B$2:$B$823,">="&A3,Analysis!$B$2:$B$823,"<"&(A3+1)) -> 0.17861134 | F3: =D3-($K$8+$K$9*A3) -> 0.15148456 | G3: =E3-($K$10+$K$11*A3) -> 0.029192644 | H3: =D3-($K$5+$K$4*E3) -> 0.077713241 | J3: Years in fit | K3: =COUNT($D$2:$D$68) -> 67
A4: 1961 | B4: =COUNTIFS(Analysis!$B$2:$B$823,">="&A4,Analysis!$B$2:$B$823,"<"&(A4+1)) -> 12 | C4: =AVERAGEIFS(Analysis!$D$2:$D$823,Analysis!$B$2:$B$823,">="&A4,Analysis!$B$2:$B$823,"<"&(A4+1)) -> 317.64333 | D4: =AVERAGEIFS(Analysis!$E$2:$E$823,Analysis!$B$2:$B$823,">="&A4,Analysis!$B$2:$B$823,"<"&(A4+1)) -> 0.056666667 | E4: =AVERAGEIFS(Analysis!$F$2:$F$823,Analysis!$B$2:$B$823,">="&A4,Analysis!$B$2:$B$823,"<"&(A4+1)) -> 0.18196023 | F4: =D4-($K$8+$K$9*A4) -> 0.21515085 | G4: =E4-($K$10+$K$11*A4) -> 0.025906144 | H4: =D4-($K$5+$K$4*E4) -> 0.15019595 | J4: Slope, °C per doubling of CO2 | K4: =SLOPE($D$2:$D$68,$E$2:$E$68) -> 2.7423885
A5: 1962 | B5: =COUNTIFS(Analysis!$B$2:$B$823,">="&A5,Analysis!$B$2:$B$823,"<"&(A5+1)) -> 12 | C5: =AVERAGEIFS(Analysis!$D$2:$D$823,Analysis!$B$2:$B$823,">="&A5,Analysis!$B$2:$B$823,"<"&(A5+1)) -> 318.45333 | D5: =AVERAGEIFS(Analysis!$E$2:$E$823,Analysis!$B$2:$B$823,">="&A5,Analysis!$B$2:$B$823,"<"&(A5+1)) -> 0.030833333 | E5: =AVERAGEIFS(Analysis!$F$2:$F$823,Analysis!$B$2:$B$823,">="&A5,Analysis!$B$2:$B$823,"<"&(A5+1)) -> 0.18563275 | F5: =D5-($K$8+$K$9*A5) -> 0.17131714 | G5: =E5-($K$10+$K$11*A5) -> 0.022943278 | H5: =D5-($K$5+$K$4*E5) -> 0.11429113 | J5: Intercept | K5: =INTERCEPT($D$2:$D$68,$E$2:$E$68) -> -0.59253492
A6: 1963 | B6: =COUNTIFS(Analysis!$B$2:$B$823,">="&A6,Analysis!$B$2:$B$823,"<"&(A6+1)) -> 12 | C6: =AVERAGEIFS(Analysis!$D$2:$D$823,Analysis!$B$2:$B$823,">="&A6,Analysis!$B$2:$B$823,"<"&(A6+1)) -> 318.9925 | D6: =AVERAGEIFS(Analysis!$E$2:$E$823,Analysis!$B$2:$B$823,">="&A6,Analysis!$B$2:$B$823,"<"&(A6+1)) -> 0.054166667 | E6: =AVERAGEIFS(Analysis!$F$2:$F$823,Analysis!$B$2:$B$823,">="&A6,Analysis!$B$2:$B$823,"<"&(A6+1)) -> 0.18806838 | F6: =D6-($K$8+$K$9*A6) -> 0.17665011 | G6: =E6-($K$10+$K$11*A6) -> 0.018743511 | H6: =D6-($K$5+$K$4*E6) -> 0.13094503 | J6: R², annual anomaly vs log2(CO2) | K6: =RSQ($D$2:$D$68,$E$2:$E$68) -> 0.93091854
A7: 1964 | B7: =COUNTIFS(Analysis!$B$2:$B$823,">="&A7,Analysis!$B$2:$B$823,"<"&(A7+1)) -> 12 | C7: =AVERAGEIFS(Analysis!$D$2:$D$823,Analysis!$B$2:$B$823,">="&A7,Analysis!$B$2:$B$823,"<"&(A7+1)) -> 319.62 | D7: =AVERAGEIFS(Analysis!$E$2:$E$823,Analysis!$B$2:$B$823,">="&A7,Analysis!$B$2:$B$823,"<"&(A7+1)) -> -0.19916667 | E7: =AVERAGEIFS(Analysis!$F$2:$F$823,Analysis!$B$2:$B$823,">="&A7,Analysis!$B$2:$B$823,"<"&(A7+1)) -> 0.19090695 | F7: =D7-($K$8+$K$9*A7) -> -0.094683601 | G7: =E7-($K$10+$K$11*A7) -> 0.014946691 | H7: =D7-($K$5+$K$4*E7) -> -0.13017276 | J7: Lag-1 autocorrelation of fit residuals | K7: =CORREL($H$2:$H$67,$H$3:$H$68) -> 0.25356714
A8: 1965 | B8: =COUNTIFS(Analysis!$B$2:$B$823,">="&A8,Analysis!$B$2:$B$823,"<"&(A8+1)) -> 12 | C8: =AVERAGEIFS(Analysis!$D$2:$D$823,Analysis!$B$2:$B$823,">="&A8,Analysis!$B$2:$B$823,"<"&(A8+1)) -> 320.03667 | D8: =AVERAGEIFS(Analysis!$E$2:$E$823,Analysis!$B$2:$B$823,">="&A8,Analysis!$B$2:$B$823,"<"&(A8+1)) -> -0.10666667 | E8: =AVERAGEIFS(Analysis!$F$2:$F$823,Analysis!$B$2:$B$823,">="&A8,Analysis!$B$2:$B$823,"<"&(A8+1)) -> 0.19279249 | F8: =D8-($K$8+$K$9*A8) -> -0.020183973 | G8: =E8-($K$10+$K$11*A8) -> 0.010196842 | H8: =D8-($K$5+$K$4*E8) -> -0.042843646 | J8: Anomaly time trend: intercept | K8: =INTERCEPT($D$2:$D$68,$A$2:$A$68) -> -35.457215
A9: 1966 | B9: =COUNTIFS(Analysis!$B$2:$B$823,">="&A9,Analysis!$B$2:$B$823,"<"&(A9+1)) -> 12 | C9: =AVERAGEIFS(Analysis!$D$2:$D$823,Analysis!$B$2:$B$823,">="&A9,Analysis!$B$2:$B$823,"<"&(A9+1)) -> 321.3675 | D9: =AVERAGEIFS(Analysis!$E$2:$E$823,Analysis!$B$2:$B$823,">="&A9,Analysis!$B$2:$B$823,"<"&(A9+1)) -> -0.0575 | E9: =AVERAGEIFS(Analysis!$F$2:$F$823,Analysis!$B$2:$B$823,">="&A9,Analysis!$B$2:$B$823,"<"&(A9+1)) -> 0.19877222 | F9: =D9-($K$8+$K$9*A9) -> 0.010982321 | G9: =E9-($K$10+$K$11*A9) -> 0.0095411815 | H9: =D9-($K$5+$K$4*E9) -> -0.010075723 | J9: Anomaly time trend: slope (°C/yr) | K9: =SLOPE($D$2:$D$68,$A$2:$A$68) -> 0.018000372
A10: 1967 | B10: =COUNTIFS(Analysis!$B$2:$B$823,">="&A10,Analysis!$B$2:$B$823,"<"&(A10+1)) -> 12 | C10: =AVERAGEIFS(Analysis!$D$2:$D$823,Analysis!$B$2:$B$823,">="&A10,Analysis!$B$2:$B$823,"<"&(A10+1)) -> 322.17917 | D10: =AVERAGEIFS(Analysis!$E$2:$E$823,Analysis!$B$2:$B$823,">="&A10,Analysis!$B$2:$B$823,"<"&(A10+1)) -> -0.024166667 | E10: =AVERAGEIFS(Analysis!$F$2:$F$823,Analysis!$B$2:$B$823,">="&A10,Analysis!$B$2:$B$823,"<"&(A10+1)) -> 0.20241456 | F10: =D10-($K$8+$K$9*A10) -> 0.026315282 | G10: =E10-($K$10+$K$11*A10) -> 0.0065481314 | H10: =D10-($K$5+$K$4*E10) -> 0.013268899 | J10: log2 CO2 time trend: intercept | K10: =INTERCEPT($E$2:$E$68,$A$2:$A$68) -> -12.855946
A11: 1968 | B11: =COUNTIFS(Analysis!$B$2:$B$823,">="&A11,Analysis!$B$2:$B$823,"<"&(A11+1)) -> 12 | C11: =AVERAGEIFS(Analysis!$D$2:$D$823,Analysis!$B$2:$B$823,">="&A11,Analysis!$B$2:$B$823,"<"&(A11+1)) -> 323.05 | D11: =AVERAGEIFS(Analysis!$E$2:$E$823,Analysis!$B$2:$B$823,">="&A11,Analysis!$B$2:$B$823,"<"&(A11+1)) -> -0.0825 | E11: =AVERAGEIFS(Analysis!$F$2:$F$823,Analysis!$B$2:$B$823,">="&A11,Analysis!$B$2:$B$823,"<"&(A11+1)) -> 0.20630941 | F11: =D11-($K$8+$K$9*A11) -> -0.050018424 | G11: =E11-($K$10+$K$11*A11) -> 0.0038075972 | H11: =D11-($K$5+$K$4*E11) -> -0.055745643 | J11: log2 CO2 time trend: slope (/yr) | K11: =SLOPE($E$2:$E$68,$A$2:$A$68) -> 0.0066353903
A12: 1969 | B12: =COUNTIFS(Analysis!$B$2:$B$823,">="&A12,Analysis!$B$2:$B$823,"<"&(A12+1)) -> 12 | C12: =AVERAGEIFS(Analysis!$D$2:$D$823,Analysis!$B$2:$B$823,">="&A12,Analysis!$B$2:$B$823,"<"&(A12+1)) -> 324.62083 | D12: =AVERAGEIFS(Analysis!$E$2:$E$823,Analysis!$B$2:$B$823,">="&A12,Analysis!$B$2:$B$823,"<"&(A12+1)) -> 0.0525 | E12: =AVERAGEIFS(Analysis!$F$2:$F$823,Analysis!$B$2:$B$823,">="&A12,Analysis!$B$2:$B$823,"<"&(A12+1)) -> 0.2133079 | F12: =D12-($K$8+$K$9*A12) -> 0.066981204 | G12: =E12-($K$10+$K$11*A12) -> 0.0041706899 | H12: =D12-($K$5+$K$4*E12) -> 0.060061798
A13: 1970 | B13: =COUNTIFS(Analysis!$B$2:$B$823,">="&A13,Analysis!$B$2:$B$823,"<"&(A13+1)) -> 12 | C13: =AVERAGEIFS(Analysis!$D$2:$D$823,Analysis!$B$2:$B$823,">="&A13,Analysis!$B$2:$B$823,"<"&(A13+1)) -> 325.68167 | D13: =AVERAGEIFS(Analysis!$E$2:$E$823,Analysis!$B$2:$B$823,">="&A13,Analysis!$B$2:$B$823,"<"&(A13+1)) -> 0.0275 | E13: =AVERAGEIFS(Analysis!$F$2:$F$823,Analysis!$B$2:$B$823,">="&A13,Analysis!$B$2:$B$823,"<"&(A13+1)) -> 0.21801538 | F13: =D13-($K$8+$K$9*A13) -> 0.023980831 | G13: =E13-($K$10+$K$11*A13) -> 0.002242785 | H13: =D13-($K$5+$K$4*E13) -> 0.022152044 | J13: DETRENDED TEST: r between residual series | K13: =CORREL($F$2:$F$68,$G$2:$G$68) -> 0.63587131
A14: 1971 | B14: =COUNTIFS(Analysis!$B$2:$B$823,">="&A14,Analysis!$B$2:$B$823,"<"&(A14+1)) -> 12 | C14: =AVERAGEIFS(Analysis!$D$2:$D$823,Analysis!$B$2:$B$823,">="&A14,Analysis!$B$2:$B$823,"<"&(A14+1)) -> 326.32 | D14: =AVERAGEIFS(Analysis!$E$2:$E$823,Analysis!$B$2:$B$823,">="&A14,Analysis!$B$2:$B$823,"<"&(A14+1)) -> -0.079166667 | E14: =AVERAGEIFS(Analysis!$F$2:$F$823,Analysis!$B$2:$B$823,">="&A14,Analysis!$B$2:$B$823,"<"&(A14+1)) -> 0.22084049 | F14: =D14-($K$8+$K$9*A14) -> -0.10068621 | G14: =E14-($K$10+$K$11*A14) -> -0.0015674995 | H14: =D14-($K$5+$K$4*E14) -> -0.09226216
A15: 1972 | B15: =COUNTIFS(Analysis!$B$2:$B$823,">="&A15,Analysis!$B$2:$B$823,"<"&(A15+1)) -> 12 | C15: =AVERAGEIFS(Analysis!$D$2:$D$823,Analysis!$B$2:$B$823,">="&A15,Analysis!$B$2:$B$823,"<"&(A15+1)) -> 327.45667 | D15: =AVERAGEIFS(Analysis!$E$2:$E$823,Analysis!$B$2:$B$823,">="&A15,Analysis!$B$2:$B$823,"<"&(A15+1)) -> 0.0091666667 | E15: =AVERAGEIFS(Analysis!$F$2:$F$823,Analysis!$B$2:$B$823,">="&A15,Analysis!$B$2:$B$823,"<"&(A15+1)) -> 0.22586053 | F15: =D15-($K$8+$K$9*A15) -> -0.030353247 | G15: =E15-($K$10+$K$11*A15) -> -0.0031828518 | H15: =D15-($K$5+$K$4*E15) -> -0.017695721 | J15: Detrended R² | K15: =RSQ($F$2:$F$68,$G$2:$G$68) -> 0.40433233
A16: 1973 | B16: =COUNTIFS(Analysis!$B$2:$B$823,">="&A16,Analysis!$B$2:$B$823,"<"&(A16+1)) -> 12 | C16: =AVERAGEIFS(Analysis!$D$2:$D$823,Analysis!$B$2:$B$823,">="&A16,Analysis!$B$2:$B$823,"<"&(A16+1)) -> 329.68167 | D16: =AVERAGEIFS(Analysis!$E$2:$E$823,Analysis!$B$2:$B$823,">="&A16,Analysis!$B$2:$B$823,"<"&(A16+1)) -> 0.16083333 | E16: =AVERAGEIFS(Analysis!$F$2:$F$823,Analysis!$B$2:$B$823,">="&A16,Analysis!$B$2:$B$823,"<"&(A16+1)) -> 0.23562788 | F16: =D16-($K$8+$K$9*A16) -> 0.10331305 | G16: =E16-($K$10+$K$11*A16) -> -5.0888931e-05 | H16: =D16-($K$5+$K$4*E16) -> 0.10718507
A17: 1974 | B17: =COUNTIFS(Analysis!$B$2:$B$823,">="&A17,Analysis!$B$2:$B$823,"<"&(A17+1)) -> 12 | C17: =AVERAGEIFS(Analysis!$D$2:$D$823,Analysis!$B$2:$B$823,">="&A17,Analysis!$B$2:$B$823,"<"&(A17+1)) -> 330.19333 | D17: =AVERAGEIFS(Analysis!$E$2:$E$823,Analysis!$B$2:$B$823,">="&A17,Analysis!$B$2:$B$823,"<"&(A17+1)) -> -0.071666667 | E17: =AVERAGEIFS(Analysis!$F$2:$F$823,Analysis!$B$2:$B$823,">="&A17,Analysis!$B$2:$B$823,"<"&(A17+1)) -> 0.23785982 | F17: =D17-($K$8+$K$9*A17) -> -0.14718733 | G17: =E17-($K$10+$K$11*A17) -> -0.004454341 | H17: =D17-($K$5+$K$4*E17) -> -0.13143577 | J17: Naive OLS standard error of slope | K17: =INDEX(LINEST($D$2:$D$68,$E$2:$E$68,TRUE(),TRUE()),2,1) -> 0.092661048
A18: 1975 | B18: =COUNTIFS(Analysis!$B$2:$B$823,">="&A18,Analysis!$B$2:$B$823,"<"&(A18+1)) -> 12 | C18: =AVERAGEIFS(Analysis!$D$2:$D$823,Analysis!$B$2:$B$823,">="&A18,Analysis!$B$2:$B$823,"<"&(A18+1)) -> 331.1275 | D18: =AVERAGEIFS(Analysis!$E$2:$E$823,Analysis!$B$2:$B$823,">="&A18,Analysis!$B$2:$B$823,"<"&(A18+1)) -> -0.013333333 | E18: =AVERAGEIFS(Analysis!$F$2:$F$823,Analysis!$B$2:$B$823,">="&A18,Analysis!$B$2:$B$823,"<"&(A18+1)) -> 0.24193918 | F18: =D18-($K$8+$K$9*A18) -> -0.10685436 | G18: =E18-($K$10+$K$11*A18) -> -0.007010368 | H18: =D18-($K$5+$K$4*E18) -> -0.084289639 | J18: AR(1) inflation factor √((1+ρ)/(1-ρ)) | K18: =SQRT((1+K7)/(1-K7)) -> 1.2959207
A19: 1976 | B19: =COUNTIFS(Analysis!$B$2:$B$823,">="&A19,Analysis!$B$2:$B$823,"<"&(A19+1)) -> 12 | C19: =AVERAGEIFS(Analysis!$D$2:$D$823,Analysis!$B$2:$B$823,">="&A19,Analysis!$B$2:$B$823,"<"&(A19+1)) -> 332.02583 | D19: =AVERAGEIFS(Analysis!$E$2:$E$823,Analysis!$B$2:$B$823,">="&A19,Analysis!$B$2:$B$823,"<"&(A19+1)) -> -0.0975 | E19: =AVERAGEIFS(Analysis!$F$2:$F$823,Analysis!$B$2:$B$823,">="&A19,Analysis!$B$2:$B$823,"<"&(A19+1)) -> 0.24584257 | F19: =D19-($K$8+$K$9*A19) -> -0.2090214 | G19: =E19-($K$10+$K$11*A19) -> -0.0097423662 | H19: =D19-($K$5+$K$4*E19) -> -0.17916092 | J19: Adjusted standard error | K19: =K17*K18 -> 0.12008137
A20: 1977 | B20: =COUNTIFS(Analysis!$B$2:$B$823,">="&A20,Analysis!$B$2:$B$823,"<"&(A20+1)) -> 12 | C20: =AVERAGEIFS(Analysis!$D$2:$D$823,Analysis!$B$2:$B$823,">="&A20,Analysis!$B$2:$B$823,"<"&(A20+1)) -> 333.84417 | D20: =AVERAGEIFS(Analysis!$E$2:$E$823,Analysis!$B$2:$B$823,">="&A20,Analysis!$B$2:$B$823,"<"&(A20+1)) -> 0.17833333 | E20: =AVERAGEIFS(Analysis!$F$2:$F$823,Analysis!$B$2:$B$823,">="&A20,Analysis!$B$2:$B$823,"<"&(A20+1)) -> 0.25372587 | F20: =D20-($K$8+$K$9*A20) -> 0.048811557 | G20: =E20-($K$10+$K$11*A20) -> -0.0084944611 | H20: =D20-($K$5+$K$4*E20) -> 0.075053352 | J20: 95% interval, low / high (°C per doubling) | K20: =K4-1.96*K19 -> 2.507029 | L20: =K4+1.96*K19 -> 2.977748
A21: 1978 | B21: =COUNTIFS(Analysis!$B$2:$B$823,">="&A21,Analysis!$B$2:$B$823,"<"&(A21+1)) -> 12 | C21: =AVERAGEIFS(Analysis!$D$2:$D$823,Analysis!$B$2:$B$823,">="&A21,Analysis!$B$2:$B$823,"<"&(A21+1)) -> 335.415 | D21: =AVERAGEIFS(Analysis!$E$2:$E$823,Analysis!$B$2:$B$823,">="&A21,Analysis!$B$2:$B$823,"<"&(A21+1)) -> 0.066666667 | E21: =AVERAGEIFS(Analysis!$F$2:$F$823,Analysis!$B$2:$B$823,">="&A21,Analysis!$B$2:$B$823,"<"&(A21+1)) -> 0.26049698 | F21: =D21-($K$8+$K$9*A21) -> -0.080855482 | G21: =E21-($K$10+$K$11*A21) -> -0.0083587422 | H21: =D21-($K$5+$K$4*E21) -> -0.055182327 | J21: Split sample: slope 1959-1991 / 1992-2025 | K21: =SLOPE($D$2:$D$34,$E$2:$E$34) -> 2.573599 | L21: =SLOPE($D$35:$D$68,$E$35:$E$68) -> 3.1905042
A22: 1979 | B22: =COUNTIFS(Analysis!$B$2:$B$823,">="&A22,Analysis!$B$2:$B$823,"<"&(A22+1)) -> 12 | C22: =AVERAGEIFS(Analysis!$D$2:$D$823,Analysis!$B$2:$B$823,">="&A22,Analysis!$B$2:$B$823,"<"&(A22+1)) -> 336.835 | D22: =AVERAGEIFS(Analysis!$E$2:$E$823,Analysis!$B$2:$B$823,">="&A22,Analysis!$B$2:$B$823,"<"&(A22+1)) -> 0.16416667 | E22: =AVERAGEIFS(Analysis!$F$2:$F$823,Analysis!$B$2:$B$823,">="&A22,Analysis!$B$2:$B$823,"<"&(A22+1)) -> 0.26659554 | F22: =D22-($K$8+$K$9*A22) -> -0.0013558544 | G22: =E22-($K$10+$K$11*A22) -> -0.008895571 | H22: =D22-($K$5+$K$4*E22) -> 0.025593049 | J22: Split difference ÷ combined AR(1)-adjusted SE (t-like) | K22: =(L21-K21)/SQRT((INDEX(LINEST($D$2:$D$34,$E$2:$E$34,TRUE(),TRUE()),2,1)*K18)^2+(INDEX(LINEST($D$35:$D$68,$E$35:$E$68,TRUE(),TRUE()),2,1)*K18)^2) -> 1.257008
A23: 1980 | B23: =COUNTIFS(Analysis!$B$2:$B$823,">="&A23,Analysis!$B$2:$B$823,"<"&(A23+1)) -> 12 | C23: =AVERAGEIFS(Analysis!$D$2:$D$823,Analysis!$B$2:$B$823,">="&A23,Analysis!$B$2:$B$823,"<"&(A23+1)) -> 338.7625 | D23: =AVERAGEIFS(Analysis!$E$2:$E$823,Analysis!$B$2:$B$823,">="&A23,Analysis!$B$2:$B$823,"<"&(A23+1)) -> 0.25583333 | E23: =AVERAGEIFS(Analysis!$F$2:$F$823,Analysis!$B$2:$B$823,">="&A23,Analysis!$B$2:$B$823,"<"&(A23+1)) -> 0.27482719 | F23: =D23-($K$8+$K$9*A23) -> 0.07231044 | G23: =E23-($K$10+$K$11*A23) -> -0.0072993114 | H23: =D23-($K$5+$K$4*E23) -> 0.094685333 | J23: Summary of central results
A24: 1981 | B24: =COUNTIFS(Analysis!$B$2:$B$823,">="&A24,Analysis!$B$2:$B$823,"<"&(A24+1)) -> 12 | C24: =AVERAGEIFS(Analysis!$D$2:$D$823,Analysis!$B$2:$B$823,">="&A24,Analysis!$B$2:$B$823,"<"&(A24+1)) -> 340.12 | D24: =AVERAGEIFS(Analysis!$E$2:$E$823,Analysis!$B$2:$B$823,">="&A24,Analysis!$B$2:$B$823,"<"&(A24+1)) -> 0.32333333 | E24: =AVERAGEIFS(Analysis!$F$2:$F$823,Analysis!$B$2:$B$823,">="&A24,Analysis!$B$2:$B$823,"<"&(A24+1)) -> 0.28059167 | F24: =D24-($K$8+$K$9*A24) -> 0.12181007 | G24: =E24-($K$10+$K$11*A24) -> -0.008170222 | H24: =D24-($K$5+$K$4*E24) -> 0.14637689 | J24: Monthly fit: °C per CO2 doubling | K24: Annual fit: °C per CO2 doubling | L24: Detrended annual r
A25: 1982 | B25: =COUNTIFS(Analysis!$B$2:$B$823,">="&A25,Analysis!$B$2:$B$823,"<"&(A25+1)) -> 12 | C25: =AVERAGEIFS(Analysis!$D$2:$D$823,Analysis!$B$2:$B$823,">="&A25,Analysis!$B$2:$B$823,"<"&(A25+1)) -> 341.47833 | D25: =AVERAGEIFS(Analysis!$E$2:$E$823,Analysis!$B$2:$B$823,">="&A25,Analysis!$B$2:$B$823,"<"&(A25+1)) -> 0.13916667 | E25: =AVERAGEIFS(Analysis!$F$2:$F$823,Analysis!$B$2:$B$823,">="&A25,Analysis!$B$2:$B$823,"<"&(A25+1)) -> 0.28634093 | F25: =D25-($K$8+$K$9*A25) -> -0.080356972 | G25: =E25-($K$10+$K$11*A25) -> -0.0090563455 | H25: =D25-($K$5+$K$4*E25) -> -0.053556499 | J25: =Analysis!I11 -> 2.7335713 | K25: =K4 -> 2.7423885 | L25: =K13 -> 0.63587131
A26: 1983 | B26: =COUNTIFS(Analysis!$B$2:$B$823,">="&A26,Analysis!$B$2:$B$823,"<"&(A26+1)) -> 12 | C26: =AVERAGEIFS(Analysis!$D$2:$D$823,Analysis!$B$2:$B$823,">="&A26,Analysis!$B$2:$B$823,"<"&(A26+1)) -> 343.1525 | D26: =AVERAGEIFS(Analysis!$E$2:$E$823,Analysis!$B$2:$B$823,">="&A26,Analysis!$B$2:$B$823,"<"&(A26+1)) -> 0.315 | E26: =AVERAGEIFS(Analysis!$F$2:$F$823,Analysis!$B$2:$B$823,">="&A26,Analysis!$B$2:$B$823,"<"&(A26+1)) -> 0.293402 | F26: =D26-($K$8+$K$9*A26) -> 0.077475989 | G26: =E26-($K$10+$K$11*A26) -> -0.0086306664 | H26: =D26-($K$5+$K$4*E26) -> 0.10291264 | J26: 822 months, 1958-2026 | K26: 67 full years, 1959-2025 | L26: linear time trend removed from both series
A27: 1984 | B27: =COUNTIFS(Analysis!$B$2:$B$823,">="&A27,Analysis!$B$2:$B$823,"<"&(A27+1)) -> 12 | C27: =AVERAGEIFS(Analysis!$D$2:$D$823,Analysis!$B$2:$B$823,">="&A27,Analysis!$B$2:$B$823,"<"&(A27+1)) -> 344.86667 | D27: =AVERAGEIFS(Analysis!$E$2:$E$823,Analysis!$B$2:$B$823,">="&A27,Analysis!$B$2:$B$823,"<"&(A27+1)) -> 0.155 | E27: =AVERAGEIFS(Analysis!$F$2:$F$823,Analysis!$B$2:$B$823,">="&A27,Analysis!$B$2:$B$823,"<"&(A27+1)) -> 0.30058891 | F27: =D27-($K$8+$K$9*A27) -> -0.10052438 | G27: =E27-($K$10+$K$11*A27) -> -0.0080791536 | H27: =D27-($K$5+$K$4*E27) -> -0.076796642 | J27: Caution: these are descriptive observational regressions over 1958-2026, not estimates of equilibrium climate sensitivity.
A28: 1985 | B28: =COUNTIFS(Analysis!$B$2:$B$823,">="&A28,Analysis!$B$2:$B$823,"<"&(A28+1)) -> 12 | C28: =AVERAGEIFS(Analysis!$D$2:$D$823,Analysis!$B$2:$B$823,">="&A28,Analysis!$B$2:$B$823,"<"&(A28+1)) -> 346.35167 | D28: =AVERAGEIFS(Analysis!$E$2:$E$823,Analysis!$B$2:$B$823,">="&A28,Analysis!$B$2:$B$823,"<"&(A28+1)) -> 0.11833333 | E28: =AVERAGEIFS(Analysis!$F$2:$F$823,Analysis!$B$2:$B$823,">="&A28,Analysis!$B$2:$B$823,"<"&(A28+1)) -> 0.3067888 | F28: =D28-($K$8+$K$9*A28) -> -0.15519142 | G28: =E28-($K$10+$K$11*A28) -> -0.0085146485 | H28: =D28-($K$5+$K$4*E28) -> -0.13046583 | J28: See the Solar, ENSO, Volcanic and Forcing tabs for the natural-variability controls and the full-forcing comparison.
A29: 1986 | B29: =COUNTIFS(Analysis!$B$2:$B$823,">="&A29,Analysis!$B$2:$B$823,"<"&(A29+1)) -> 12 | C29: =AVERAGEIFS(Analysis!$D$2:$D$823,Analysis!$B$2:$B$823,">="&A29,Analysis!$B$2:$B$823,"<"&(A29+1)) -> 347.6075 | D29: =AVERAGEIFS(Analysis!$E$2:$E$823,Analysis!$B$2:$B$823,">="&A29,Analysis!$B$2:$B$823,"<"&(A29+1)) -> 0.18 | E29: =AVERAGEIFS(Analysis!$F$2:$F$823,Analysis!$B$2:$B$823,">="&A29,Analysis!$B$2:$B$823,"<"&(A29+1)) -> 0.31201398 | F29: =D29-($K$8+$K$9*A29) -> -0.11152513 | G29: =E29-($K$10+$K$11*A29) -> -0.009924862 | H29: =D29-($K$5+$K$4*E29) -> -0.083128628
A30: 1987 | B30: =COUNTIFS(Analysis!$B$2:$B$823,">="&A30,Analysis!$B$2:$B$823,"<"&(A30+1)) -> 12 | C30: =AVERAGEIFS(Analysis!$D$2:$D$823,Analysis!$B$2:$B$823,">="&A30,Analysis!$B$2:$B$823,"<"&(A30+1)) -> 349.31167 | D30: =AVERAGEIFS(Analysis!$E$2:$E$823,Analysis!$B$2:$B$823,">="&A30,Analysis!$B$2:$B$823,"<"&(A30+1)) -> 0.32166667 | E30: =AVERAGEIFS(Analysis!$F$2:$F$823,Analysis!$B$2:$B$823,">="&A30,Analysis!$B$2:$B$823,"<"&(A30+1)) -> 0.31907046 | F30: =D30-($K$8+$K$9*A30) -> 0.012141166 | G30: =E30-($K$10+$K$11*A30) -> -0.0095037704 | H30: =D30-($K$5+$K$4*E30) -> 0.039186424 | J30: How to read this sheet
A31: 1988 | B31: =COUNTIFS(Analysis!$B$2:$B$823,">="&A31,Analysis!$B$2:$B$823,"<"&(A31+1)) -> 12 | C31: =AVERAGEIFS(Analysis!$D$2:$D$823,Analysis!$B$2:$B$823,">="&A31,Analysis!$B$2:$B$823,"<"&(A31+1)) -> 351.69 | D31: =AVERAGEIFS(Analysis!$E$2:$E$823,Analysis!$B$2:$B$823,">="&A31,Analysis!$B$2:$B$823,"<"&(A31+1)) -> 0.39 | E31: =AVERAGEIFS(Analysis!$F$2:$F$823,Analysis!$B$2:$B$823,">="&A31,Analysis!$B$2:$B$823,"<"&(A31+1)) -> 0.32886052 | F31: =D31-($K$8+$K$9*A31) -> 0.062474127 | G31: =E31-($K$10+$K$11*A31) -> -0.006349102 | H31: =D31-($K$5+$K$4*E31) -> 0.080671613 | J31: 1. Annual means remove most of the month-to-month autocorrelation (lag-1 falls from ~0.64 monthly to ~0.25), so the 67 years are closer to independent observations than the 822 months.
A32: 1989 | B32: =COUNTIFS(Analysis!$B$2:$B$823,">="&A32,Analysis!$B$2:$B$823,"<"&(A32+1)) -> 12 | C32: =AVERAGEIFS(Analysis!$D$2:$D$823,Analysis!$B$2:$B$823,">="&A32,Analysis!$B$2:$B$823,"<"&(A32+1)) -> 353.205 | D32: =AVERAGEIFS(Analysis!$E$2:$E$823,Analysis!$B$2:$B$823,">="&A32,Analysis!$B$2:$B$823,"<"&(A32+1)) -> 0.27416667 | E32: =AVERAGEIFS(Analysis!$F$2:$F$823,Analysis!$B$2:$B$823,">="&A32,Analysis!$B$2:$B$823,"<"&(A32+1)) -> 0.33505818 | F32: =D32-($K$8+$K$9*A32) -> -0.071359579 | G32: =E32-($K$10+$K$11*A32) -> -0.0067868342 | H32: =D32-($K$5+$K$4*E32) -> -0.052158107 | J32: 2. The detrended test answers "are these just two things rising with time?": a straight-line time trend is removed from BOTH series and the leftover wiggles are correlated. A high r here cannot be produced by a shared trend.
A33: 1990 | B33: =COUNTIFS(Analysis!$B$2:$B$823,">="&A33,Analysis!$B$2:$B$823,"<"&(A33+1)) -> 12 | C33: =AVERAGEIFS(Analysis!$D$2:$D$823,Analysis!$B$2:$B$823,">="&A33,Analysis!$B$2:$B$823,"<"&(A33+1)) -> 354.4525 | D33: =AVERAGEIFS(Analysis!$E$2:$E$823,Analysis!$B$2:$B$823,">="&A33,Analysis!$B$2:$B$823,"<"&(A33+1)) -> 0.44916667 | E33: =AVERAGEIFS(Analysis!$F$2:$F$823,Analysis!$B$2:$B$823,">="&A33,Analysis!$B$2:$B$823,"<"&(A33+1)) -> 0.34014661 | F33: =D33-($K$8+$K$9*A33) -> 0.085640048 | G33: =E33-($K$10+$K$11*A33) -> -0.0083337973 | H33: =D33-($K$5+$K$4*E33) -> 0.10888745 | J33: 3. Tests deliberately omitted: regressing anomaly on CO2 plus time (CO2 and time correlate at ~0.99 here, so the coefficients are unstable and uninformative), and 5- or 10-year differences (CO2 moves only ~0.03-0.07 doublings per step, so ENSO noise swamps the signal and R² collapses regardless of the true relationship).
A34: 1991 | B34: =COUNTIFS(Analysis!$B$2:$B$823,">="&A34,Analysis!$B$2:$B$823,"<"&(A34+1)) -> 12 | C34: =AVERAGEIFS(Analysis!$D$2:$D$823,Analysis!$B$2:$B$823,">="&A34,Analysis!$B$2:$B$823,"<"&(A34+1)) -> 355.70417 | D34: =AVERAGEIFS(Analysis!$E$2:$E$823,Analysis!$B$2:$B$823,">="&A34,Analysis!$B$2:$B$823,"<"&(A34+1)) -> 0.4075 | E34: =AVERAGEIFS(Analysis!$F$2:$F$823,Analysis!$B$2:$B$823,">="&A34,Analysis!$B$2:$B$823,"<"&(A34+1)) -> 0.34522236 | F34: =D34-($K$8+$K$9*A34) -> 0.025973009 | G34: =E34-($K$10+$K$11*A34) -> -0.0098934366 | H34: =D34-($K$5+$K$4*E34) -> 0.053301102 | J34: 4. Uncertainty: the naive OLS standard error is inflated by the AR(1) factor (Grok/GPT review, Sept 2026); the resulting 95% interval (~2.5 to 3.0 °C per doubling) reflects time-series error only, not forcing or dataset uncertainty. Newey-West standard errors with 1-6 lags give 0.120-0.126, so the AR(1) heuristic is adequate here. The split-sample slopes (1959-1991 vs 1992-2025) differ (~2.6 vs ~3.2) but only by ~1.3 combined adjusted SEs (K22), so the difference is suggestive, not established. The direction is what the forcing data predict: net anthropogenic forcing grew faster than CO2 alone once aerosol offset stopped growing (Forcing tab, T42:U42), which is a reason to prefer the anthropogenic-ERF regression over the CO2 proxy for any response estimate.
A35: 1992 | B35: =COUNTIFS(Analysis!$B$2:$B$823,">="&A35,Analysis!$B$2:$B$823,"<"&(A35+1)) -> 12 | C35: =AVERAGEIFS(Analysis!$D$2:$D$823,Analysis!$B$2:$B$823,">="&A35,Analysis!$B$2:$B$823,"<"&(A35+1)) -> 356.545 | D35: =AVERAGEIFS(Analysis!$E$2:$E$823,Analysis!$B$2:$B$823,">="&A35,Analysis!$B$2:$B$823,"<"&(A35+1)) -> 0.22416667 | E35: =AVERAGEIFS(Analysis!$F$2:$F$823,Analysis!$B$2:$B$823,">="&A35,Analysis!$B$2:$B$823,"<"&(A35+1)) -> 0.34862967 | F35: =D35-($K$8+$K$9*A35) -> -0.1753607 | G35: =E35-($K$10+$K$11*A35) -> -0.013121512 | H35: =D35-($K$5+$K$4*E35) -> -0.13937641 | J35: 5. None of these fits is a climate sensitivity estimate. They describe the observed 1958-2026 co-variation; other forcings (methane, aerosols, solar, volcanic) and ocean lag are not separated out.
A36: 1993 | B36: =COUNTIFS(Analysis!$B$2:$B$823,">="&A36,Analysis!$B$2:$B$823,"<"&(A36+1)) -> 12 | C36: =AVERAGEIFS(Analysis!$D$2:$D$823,Analysis!$B$2:$B$823,">="&A36,Analysis!$B$2:$B$823,"<"&(A36+1)) -> 357.215 | D36: =AVERAGEIFS(Analysis!$E$2:$E$823,Analysis!$B$2:$B$823,">="&A36,Analysis!$B$2:$B$823,"<"&(A36+1)) -> 0.23333333 | E36: =AVERAGEIFS(Analysis!$F$2:$F$823,Analysis!$B$2:$B$823,">="&A36,Analysis!$B$2:$B$823,"<"&(A36+1)) -> 0.3513444 | F36: =D36-($K$8+$K$9*A36) -> -0.1841944 | G36: =E36-($K$10+$K$11*A36) -> -0.017042172 | H36: =D36-($K$5+$K$4*E36) -> -0.13765459
A37: 1994 | B37: =COUNTIFS(Analysis!$B$2:$B$823,">="&A37,Analysis!$B$2:$B$823,"<"&(A37+1)) -> 12 | C37: =AVERAGEIFS(Analysis!$D$2:$D$823,Analysis!$B$2:$B$823,">="&A37,Analysis!$B$2:$B$823,"<"&(A37+1)) -> 358.95917 | D37: =AVERAGEIFS(Analysis!$E$2:$E$823,Analysis!$B$2:$B$823,">="&A37,Analysis!$B$2:$B$823,"<"&(A37+1)) -> 0.31583333 | E37: =AVERAGEIFS(Analysis!$F$2:$F$823,Analysis!$B$2:$B$823,">="&A37,Analysis!$B$2:$B$823,"<"&(A37+1)) -> 0.35837405 | F37: =D37-($K$8+$K$9*A37) -> -0.11969477 | G37: =E37-($K$10+$K$11*A37) -> -0.016647912 | H37: =D37-($K$5+$K$4*E37) -> -0.074432624
A38: 1995 | B38: =COUNTIFS(Analysis!$B$2:$B$823,">="&A38,Analysis!$B$2:$B$823,"<"&(A38+1)) -> 12 | C38: =AVERAGEIFS(Analysis!$D$2:$D$823,Analysis!$B$2:$B$823,">="&A38,Analysis!$B$2:$B$823,"<"&(A38+1)) -> 360.96833 | D38: =AVERAGEIFS(Analysis!$E$2:$E$823,Analysis!$B$2:$B$823,">="&A38,Analysis!$B$2:$B$823,"<"&(A38+1)) -> 0.4475 | E38: =AVERAGEIFS(Analysis!$F$2:$F$823,Analysis!$B$2:$B$823,">="&A38,Analysis!$B$2:$B$823,"<"&(A38+1)) -> 0.36642609 | F38: =D38-($K$8+$K$9*A38) -> -0.0060284806 | G38: =E38-($K$10+$K$11*A38) -> -0.015231268 | H38: =D38-($K$5+$K$4*E38) -> 0.035152237
A39: 1996 | B39: =COUNTIFS(Analysis!$B$2:$B$823,">="&A39,Analysis!$B$2:$B$823,"<"&(A39+1)) -> 12 | C39: =AVERAGEIFS(Analysis!$D$2:$D$823,Analysis!$B$2:$B$823,">="&A39,Analysis!$B$2:$B$823,"<"&(A39+1)) -> 362.74333 | D39: =AVERAGEIFS(Analysis!$E$2:$E$823,Analysis!$B$2:$B$823,">="&A39,Analysis!$B$2:$B$823,"<"&(A39+1)) -> 0.33416667 | E39: =AVERAGEIFS(Analysis!$F$2:$F$823,Analysis!$B$2:$B$823,">="&A39,Analysis!$B$2:$B$823,"<"&(A39+1)) -> 0.37350294 | F39: =D39-($K$8+$K$9*A39) -> -0.13736219 | G39: =E39-($K$10+$K$11*A39) -> -0.014789809 | H39: =D39-($K$5+$K$4*E39) -> -0.097588567
A40: 1997 | B40: =COUNTIFS(Analysis!$B$2:$B$823,">="&A40,Analysis!$B$2:$B$823,"<"&(A40+1)) -> 12 | C40: =AVERAGEIFS(Analysis!$D$2:$D$823,Analysis!$B$2:$B$823,">="&A40,Analysis!$B$2:$B$823,"<"&(A40+1)) -> 363.87667 | D40: =AVERAGEIFS(Analysis!$E$2:$E$823,Analysis!$B$2:$B$823,">="&A40,Analysis!$B$2:$B$823,"<"&(A40+1)) -> 0.4675 | E40: =AVERAGEIFS(Analysis!$F$2:$F$823,Analysis!$B$2:$B$823,">="&A40,Analysis!$B$2:$B$823,"<"&(A40+1)) -> 0.37800252 | F40: =D40-($K$8+$K$9*A40) -> -0.022029226 | G40: =E40-($K$10+$K$11*A40) -> -0.016925611 | H40: =D40-($K$5+$K$4*E40) -> 0.023405149
A41: 1998 | B41: =COUNTIFS(Analysis!$B$2:$B$823,">="&A41,Analysis!$B$2:$B$823,"<"&(A41+1)) -> 12 | C41: =AVERAGEIFS(Analysis!$D$2:$D$823,Analysis!$B$2:$B$823,">="&A41,Analysis!$B$2:$B$823,"<"&(A41+1)) -> 366.84 | D41: =AVERAGEIFS(Analysis!$E$2:$E$823,Analysis!$B$2:$B$823,">="&A41,Analysis!$B$2:$B$823,"<"&(A41+1)) -> 0.60916667 | E41: =AVERAGEIFS(Analysis!$F$2:$F$823,Analysis!$B$2:$B$823,">="&A41,Analysis!$B$2:$B$823,"<"&(A41+1)) -> 0.38970838 | F41: =D41-($K$8+$K$9*A41) -> 0.10163707 | G41: =E41-($K$10+$K$11*A41) -> -0.011855143 | H41: =D41-($K$5+$K$4*E41) -> 0.1329698
A42: 1999 | B42: =COUNTIFS(Analysis!$B$2:$B$823,">="&A42,Analysis!$B$2:$B$823,"<"&(A42+1)) -> 12 | C42: =AVERAGEIFS(Analysis!$D$2:$D$823,Analysis!$B$2:$B$823,">="&A42,Analysis!$B$2:$B$823,"<"&(A42+1)) -> 368.54 | D42: =AVERAGEIFS(Analysis!$E$2:$E$823,Analysis!$B$2:$B$823,">="&A42,Analysis!$B$2:$B$823,"<"&(A42+1)) -> 0.3825 | E42: =AVERAGEIFS(Analysis!$F$2:$F$823,Analysis!$B$2:$B$823,">="&A42,Analysis!$B$2:$B$823,"<"&(A42+1)) -> 0.39637329 | F42: =D42-($K$8+$K$9*A42) -> -0.14302997 | G42: =E42-($K$10+$K$11*A42) -> -0.011825628 | H42: =D42-($K$5+$K$4*E42) -> -0.11197462
A43: 2000 | B43: =COUNTIFS(Analysis!$B$2:$B$823,">="&A43,Analysis!$B$2:$B$823,"<"&(A43+1)) -> 12 | C43: =AVERAGEIFS(Analysis!$D$2:$D$823,Analysis!$B$2:$B$823,">="&A43,Analysis!$B$2:$B$823,"<"&(A43+1)) -> 369.7075 | D43: =AVERAGEIFS(Analysis!$E$2:$E$823,Analysis!$B$2:$B$823,">="&A43,Analysis!$B$2:$B$823,"<"&(A43+1)) -> 0.39333333 | E43: =AVERAGEIFS(Analysis!$F$2:$F$823,Analysis!$B$2:$B$823,">="&A43,Analysis!$B$2:$B$823,"<"&(A43+1)) -> 0.40094355 | F43: =D43-($K$8+$K$9*A43) -> -0.15019701 | G43: =E43-($K$10+$K$11*A43) -> -0.01389075 | H43: =D43-($K$5+$K$4*E43) -> -0.11367474
A44: 2001 | B44: =COUNTIFS(Analysis!$B$2:$B$823,">="&A44,Analysis!$B$2:$B$823,"<"&(A44+1)) -> 12 | C44: =AVERAGEIFS(Analysis!$D$2:$D$823,Analysis!$B$2:$B$823,">="&A44,Analysis!$B$2:$B$823,"<"&(A44+1)) -> 371.31917 | D44: =AVERAGEIFS(Analysis!$E$2:$E$823,Analysis!$B$2:$B$823,">="&A44,Analysis!$B$2:$B$823,"<"&(A44+1)) -> 0.53333333 | E44: =AVERAGEIFS(Analysis!$F$2:$F$823,Analysis!$B$2:$B$823,">="&A44,Analysis!$B$2:$B$823,"<"&(A44+1)) -> 0.40721575 | F44: =D44-($K$8+$K$9*A44) -> -0.028197382 | G44: =E44-($K$10+$K$11*A44) -> -0.014253945 | H44: =D44-($K$5+$K$4*E44) -> 0.0091244626
A45: 2002 | B45: =COUNTIFS(Analysis!$B$2:$B$823,">="&A45,Analysis!$B$2:$B$823,"<"&(A45+1)) -> 12 | C45: =AVERAGEIFS(Analysis!$D$2:$D$823,Analysis!$B$2:$B$823,">="&A45,Analysis!$B$2:$B$823,"<"&(A45+1)) -> 373.4525 | D45: =AVERAGEIFS(Analysis!$E$2:$E$823,Analysis!$B$2:$B$823,">="&A45,Analysis!$B$2:$B$823,"<"&(A45+1)) -> 0.6275 | E45: =AVERAGEIFS(Analysis!$F$2:$F$823,Analysis!$B$2:$B$823,">="&A45,Analysis!$B$2:$B$823,"<"&(A45+1)) -> 0.41548364 | F45: =D45-($K$8+$K$9*A45) -> 0.047968912 | G45: =E45-($K$10+$K$11*A45) -> -0.012621442 | H45: =D45-($K$5+$K$4*E45) -> 0.080617354
A46: 2003 | B46: =COUNTIFS(Analysis!$B$2:$B$823,">="&A46,Analysis!$B$2:$B$823,"<"&(A46+1)) -> 12 | C46: =AVERAGEIFS(Analysis!$D$2:$D$823,Analysis!$B$2:$B$823,">="&A46,Analysis!$B$2:$B$823,"<"&(A46+1)) -> 375.98333 | D46: =AVERAGEIFS(Analysis!$E$2:$E$823,Analysis!$B$2:$B$823,">="&A46,Analysis!$B$2:$B$823,"<"&(A46+1)) -> 0.61666667 | E46: =AVERAGEIFS(Analysis!$F$2:$F$823,Analysis!$B$2:$B$823,">="&A46,Analysis!$B$2:$B$823,"<"&(A46+1)) -> 0.42522604 | F46: =D46-($K$8+$K$9*A46) -> 0.019135206 | G46: =E46-($K$10+$K$11*A46) -> -0.0095144408 | H46: =D46-($K$5+$K$4*E46) -> 0.043066599
A47: 2004 | B47: =COUNTIFS(Analysis!$B$2:$B$823,">="&A47,Analysis!$B$2:$B$823,"<"&(A47+1)) -> 12 | C47: =AVERAGEIFS(Analysis!$D$2:$D$823,Analysis!$B$2:$B$823,">="&A47,Analysis!$B$2:$B$823,"<"&(A47+1)) -> 377.69833 | D47: =AVERAGEIFS(Analysis!$E$2:$E$823,Analysis!$B$2:$B$823,">="&A47,Analysis!$B$2:$B$823,"<"&(A47+1)) -> 0.53416667 | E47: =AVERAGEIFS(Analysis!$F$2:$F$823,Analysis!$B$2:$B$823,">="&A47,Analysis!$B$2:$B$823,"<"&(A47+1)) -> 0.43178695 | F47: =D47-($K$8+$K$9*A47) -> -0.081365166 | G47: =E47-($K$10+$K$11*A47) -> -0.009588917 | H47: =D47-($K$5+$K$4*E47) -> -0.057425976
... A68: 2025 | B68: =COUNTIFS(Analysis!$B$2:$B$823,">="&A68,Analysis!$B$2:$B$823,"<"&(A68+1)) -> 12 | C68: =AVERAGEIFS(Analysis!$D$2:$D$823,Analysis!$B$2:$B$823,">="&A68,Analysis!$B$2:$B$823,"<"&(A68+1)) -> 427.34917 | D68: =AVERAGEIFS(Analysis!$E$2:$E$823,Analysis!$B$2:$B$823,">="&A68,Analysis!$B$2:$B$823,"<"&(A68+1)) -> 1.1933333 | E68: =AVERAGEIFS(Analysis!$F$2:$F$823,Analysis!$B$2:$B$823,">="&A68,Analysis!$B$2:$B$823,"<"&(A68+1)) -> 0.60997494 | F68: =D68-($K$8+$K$9*A68) -> 0.19979368 | G68: =E68-($K$10+$K$11*A68) -> 0.029255881 | H68: =D68-($K$5+$K$4*E68) -> 0.11307999

Sheet Solar
A1: Month/Year | B1: Anomaly (°C) | C1: log2(CO2/280) | D1: TSI (W/m²), NRLTSI2 | F1: Year | G1: Mean anomaly (°C) | H1: Mean log2(CO2/280) | I1: Mean TSI (W/m²) | J1: CO2-fit residual (from Annual!H) | K1: Multiple-regression fitted anomaly
A2: =Analysis!A2 -> 3/1958 | B2: =Analysis!E2 -> 0.08 | C2: =Analysis!F2 -> 0.17317313 | D2: 1361.03 | F2: 1959 | G2: =AVERAGEIFS(Analysis!$E$2:$E$823,Analysis!$B$2:$B$823,">="&F2,Analysis!$B$2:$B$823,"<"&(F2+1)) -> 0.030833333 | H2: =AVERAGEIFS(Analysis!$F$2:$F$823,Analysis!$B$2:$B$823,">="&F2,Analysis!$B$2:$B$823,"<"&(F2+1)) -> 0.1743967 | I2: =AVERAGEIFS($D$2:$D$791,Analysis!$B$2:$B$791,">="&F2,Analysis!$B$2:$B$791,"<"&(F2+1)) -> 1361.565 | J2: =Annual!H2 -> 0.14510476 | K2: =$O$16+$O$17*H2+$O$18*I2 -> -0.072108867 | N2: Assumptions
A3: =Analysis!A3 -> 4/1958 | B3: =Analysis!E3 -> 0.01 | C3: =Analysis!F3 -> 0.18110255 | D3: 1361.85 | F3: 1960 | G3: =AVERAGEIFS(Analysis!$E$2:$E$823,Analysis!$B$2:$B$823,">="&F3,Analysis!$B$2:$B$823,"<"&(F3+1)) -> -0.025 | H3: =AVERAGEIFS(Analysis!$F$2:$F$823,Analysis!$B$2:$B$823,">="&F3,Analysis!$B$2:$B$823,"<"&(F3+1)) -> 0.17861134 | I3: =AVERAGEIFS($D$2:$D$791,Analysis!$B$2:$B$791,">="&F3,Analysis!$B$2:$B$791,"<"&(F3+1)) -> 1361.4283 | J3: =Annual!H3 -> 0.077713241 | K3: =$O$16+$O$17*H3+$O$18*I3 -> -0.070102138 | N3: Planetary albedo (fraction reflected) | O3: 0.3
A4: =Analysis!A4 -> 5/1958 | B4: =Analysis!E4 -> 0.06 | C4: =Analysis!F4 -> 0.1813752 | D4: 1362.07 | F4: 1961 | G4: =AVERAGEIFS(Analysis!$E$2:$E$823,Analysis!$B$2:$B$823,">="&F4,Analysis!$B$2:$B$823,"<"&(F4+1)) -> 0.056666667 | H4: =AVERAGEIFS(Analysis!$F$2:$F$823,Analysis!$B$2:$B$823,">="&F4,Analysis!$B$2:$B$823,"<"&(F4+1)) -> 0.18196023 | I4: =AVERAGEIFS($D$2:$D$791,Analysis!$B$2:$B$791,">="&F4,Analysis!$B$2:$B$791,"<"&(F4+1)) -> 1360.995 | J4: =Annual!H4 -> 0.15019595 | K4: =$O$16+$O$17*H4+$O$18*I4 -> -0.090402125 | N4: CO2 forcing coefficient (W/m² per ln) | O4: 5.35
A5: =Analysis!A5 -> 6/1958 | B5: =Analysis!E5 -> -0.09 | C5: =Analysis!F5 -> 0.18028428 | D5: 1362.08 | F5: 1962 | G5: =AVERAGEIFS(Analysis!$E$2:$E$823,Analysis!$B$2:$B$823,">="&F5,Analysis!$B$2:$B$823,"<"&(F5+1)) -> 0.030833333 | H5: =AVERAGEIFS(Analysis!$F$2:$F$823,Analysis!$B$2:$B$823,">="&F5,Analysis!$B$2:$B$823,"<"&(F5+1)) -> 0.18563275 | I5: =AVERAGEIFS($D$2:$D$791,Analysis!$B$2:$B$791,">="&F5,Analysis!$B$2:$B$791,"<"&(F5+1)) -> 1360.7975 | J5: =Annual!H5 -> 0.11429113 | K5: =$O$16+$O$17*H5+$O$18*I5 -> -0.093940204
A6: =Analysis!A6 -> 7/1958 | B6: =Analysis!E6 -> 0.05 | C6: =Analysis!F6 -> 0.1739041 | D6: 1361.68 | F6: 1963 | G6: =AVERAGEIFS(Analysis!$E$2:$E$823,Analysis!$B$2:$B$823,">="&F6,Analysis!$B$2:$B$823,"<"&(F6+1)) -> 0.054166667 | H6: =AVERAGEIFS(Analysis!$F$2:$F$823,Analysis!$B$2:$B$823,">="&F6,Analysis!$B$2:$B$823,"<"&(F6+1)) -> 0.18806838 | I6: =AVERAGEIFS($D$2:$D$791,Analysis!$B$2:$B$791,">="&F6,Analysis!$B$2:$B$791,"<"&(F6+1)) -> 1360.7333 | J6: =Annual!H6 -> 0.13094503 | K6: =$O$16+$O$17*H6+$O$18*I6 -> -0.091781846 | N6: Does the Sun explain it? (annual means, 1959-2023)
A7: =Analysis!A7 -> 8/1958 | B7: =Analysis!E7 -> -0.05 | C7: =Analysis!F7 -> 0.16960437 | D7: 1361.92 | F7: 1964 | G7: =AVERAGEIFS(Analysis!$E$2:$E$823,Analysis!$B$2:$B$823,">="&F7,Analysis!$B$2:$B$823,"<"&(F7+1)) -> -0.19916667 | H7: =AVERAGEIFS(Analysis!$F$2:$F$823,Analysis!$B$2:$B$823,">="&F7,Analysis!$B$2:$B$823,"<"&(F7+1)) -> 0.19090695 | I7: =AVERAGEIFS($D$2:$D$791,Analysis!$B$2:$B$791,">="&F7,Analysis!$B$2:$B$791,"<"&(F7+1)) -> 1360.7283 | J7: =Annual!H7 -> -0.13017276 | K7: =$O$16+$O$17*H7+$O$18*I7 -> -0.084561575 | N7: Years in fit | O7: =COUNT($G$2:$G$66) -> 65
A8: =Analysis!A8 -> 9/1958 | B8: =Analysis!E8 -> -0.03 | C8: =Analysis!F8 -> 0.16170345 | D8: 1362.04 | F8: 1965 | G8: =AVERAGEIFS(Analysis!$E$2:$E$823,Analysis!$B$2:$B$823,">="&F8,Analysis!$B$2:$B$823,"<"&(F8+1)) -> -0.10666667 | H8: =AVERAGEIFS(Analysis!$F$2:$F$823,Analysis!$B$2:$B$823,">="&F8,Analysis!$B$2:$B$823,"<"&(F8+1)) -> 0.19279249 | I8: =AVERAGEIFS($D$2:$D$791,Analysis!$B$2:$B$791,">="&F8,Analysis!$B$2:$B$791,"<"&(F8+1)) -> 1360.7725 | J8: =Annual!H8 -> -0.042843646 | K8: =$O$16+$O$17*H8+$O$18*I8 -> -0.076563742 | N8: TSI: mean (W/m²) | O8: =AVERAGE($I$2:$I$66) -> 1361.0745
A9: =Analysis!A9 -> 10/1958 | B9: =Analysis!E9 -> 0.04 | C9: =Analysis!F9 -> 0.15805999 | D9: 1361.99 | F9: 1966 | G9: =AVERAGEIFS(Analysis!$E$2:$E$823,Analysis!$B$2:$B$823,">="&F9,Analysis!$B$2:$B$823,"<"&(F9+1)) -> -0.0575 | H9: =AVERAGEIFS(Analysis!$F$2:$F$823,Analysis!$B$2:$B$823,">="&F9,Analysis!$B$2:$B$823,"<"&(F9+1)) -> 0.19877222 | I9: =AVERAGEIFS($D$2:$D$791,Analysis!$B$2:$B$791,">="&F9,Analysis!$B$2:$B$791,"<"&(F9+1)) -> 1361.0008 | J9: =Annual!H9 -> -0.010075723 | K9: =$O$16+$O$17*H9+$O$18*I9 -> -0.045248767 | N9: TSI: max minus min (W/m²) | O9: =MAX($I$2:$I$66)-MIN($I$2:$I$66) -> 1.3983333
A10: =Analysis!A10 -> 11/1958 | B10: =Analysis!E10 -> 0.02 | C10: =Analysis!F10 -> 0.16225608 | D10: 1362.07 | F10: 1967 | G10: =AVERAGEIFS(Analysis!$E$2:$E$823,Analysis!$B$2:$B$823,">="&F10,Analysis!$B$2:$B$823,"<"&(F10+1)) -> -0.024166667 | H10: =AVERAGEIFS(Analysis!$F$2:$F$823,Analysis!$B$2:$B$823,">="&F10,Analysis!$B$2:$B$823,"<"&(F10+1)) -> 0.20241456 | I10: =AVERAGEIFS($D$2:$D$791,Analysis!$B$2:$B$791,">="&F10,Analysis!$B$2:$B$791,"<"&(F10+1)) -> 1361.225 | J10: =Annual!H10 -> 0.013268899 | K10: =$O$16+$O$17*H10+$O$18*I10 -> -0.020437758 | N10: TSI linear trend, W/m² per decade | O10: =SLOPE($I$2:$I$66,$F$2:$F$66)*10 -> -0.0069777098
A11: =Analysis!A11 -> 12/1958 | B11: =Analysis!E11 -> 0.01 | C11: =Analysis!F11 -> 0.16841281 | D11: 1361.54 | F11: 1968 | G11: =AVERAGEIFS(Analysis!$E$2:$E$823,Analysis!$B$2:$B$823,">="&F11,Analysis!$B$2:$B$823,"<"&(F11+1)) -> -0.0825 | H11: =AVERAGEIFS(Analysis!$F$2:$F$823,Analysis!$B$2:$B$823,">="&F11,Analysis!$B$2:$B$823,"<"&(F11+1)) -> 0.20630941 | I11: =AVERAGEIFS($D$2:$D$791,Analysis!$B$2:$B$791,">="&F11,Analysis!$B$2:$B$791,"<"&(F11+1)) -> 1361.3042 | J11: =Annual!H11 -> -0.055745643 | K11: =$O$16+$O$17*H11+$O$18*I11 -> -0.0047305884 | N11: R², anomaly vs TSI alone | O11: =RSQ($G$2:$G$66,$I$2:$I$66) -> 0.0015483771
A12: =Analysis!A12 -> 1/1959 | B12: =Analysis!E12 -> 0.08 | C12: =Analysis!F12 -> 0.17257895 | D12: 1361.36 | F12: 1969 | G12: =AVERAGEIFS(Analysis!$E$2:$E$823,Analysis!$B$2:$B$823,">="&F12,Analysis!$B$2:$B$823,"<"&(F12+1)) -> 0.0525 | H12: =AVERAGEIFS(Analysis!$F$2:$F$823,Analysis!$B$2:$B$823,">="&F12,Analysis!$B$2:$B$823,"<"&(F12+1)) -> 0.2133079 | I12: =AVERAGEIFS($D$2:$D$791,Analysis!$B$2:$B$791,">="&F12,Analysis!$B$2:$B$791,"<"&(F12+1)) -> 1361.3767 | J12: =Annual!H12 -> 0.060061798 | K12: =$O$16+$O$17*H12+$O$18*I12 -> 0.018790167 | N12: r, CO2-fit residual vs TSI | O12: =CORREL($J$2:$J$66,$I$2:$I$66) -> 0.26682413
A13: =Analysis!A13 -> 2/1959 | B13: =Analysis!E13 -> 0.07 | C13: =Analysis!F13 -> 0.17673309 | D13: 1361.98 | F13: 1970 | G13: =AVERAGEIFS(Analysis!$E$2:$E$823,Analysis!$B$2:$B$823,">="&F13,Analysis!$B$2:$B$823,"<"&(F13+1)) -> 0.0275 | H13: =AVERAGEIFS(Analysis!$F$2:$F$823,Analysis!$B$2:$B$823,">="&F13,Analysis!$B$2:$B$823,"<"&(F13+1)) -> 0.21801538 | I13: =AVERAGEIFS($D$2:$D$791,Analysis!$B$2:$B$791,">="&F13,Analysis!$B$2:$B$791,"<"&(F13+1)) -> 1361.3742 | J13: =Annual!H13 -> 0.022152044 | K13: =$O$16+$O$17*H13+$O$18*I13 -> 0.031154773 | N13: R², anomaly vs log2(CO2) alone | O13: =RSQ($G$2:$G$66,$H$2:$H$66) -> 0.9275573
A14: =Analysis!A14 -> 3/1959 | B14: =Analysis!E14 -> 0.18 | C14: =Analysis!F14 -> 0.17746225 | D14: 1361.39 | F14: 1971 | G14: =AVERAGEIFS(Analysis!$E$2:$E$823,Analysis!$B$2:$B$823,">="&F14,Analysis!$B$2:$B$823,"<"&(F14+1)) -> -0.079166667 | H14: =AVERAGEIFS(Analysis!$F$2:$F$823,Analysis!$B$2:$B$823,">="&F14,Analysis!$B$2:$B$823,"<"&(F14+1)) -> 0.22084049 | I14: =AVERAGEIFS($D$2:$D$791,Analysis!$B$2:$B$791,">="&F14,Analysis!$B$2:$B$791,"<"&(F14+1)) -> 1361.04 | J14: =Annual!H14 -> -0.09226216 | K14: =$O$16+$O$17*H14+$O$18*I14 -> 0.016146246
A15: =Analysis!A15 -> 4/1959 | B15: =Analysis!E15 -> 0.16 | C15: =Analysis!F15 -> 0.18232908 | D15: 1361.71 | F15: 1972 | G15: =AVERAGEIFS(Analysis!$E$2:$E$823,Analysis!$B$2:$B$823,">="&F15,Analysis!$B$2:$B$823,"<"&(F15+1)) -> 0.0091666667 | H15: =AVERAGEIFS(Analysis!$F$2:$F$823,Analysis!$B$2:$B$823,">="&F15,Analysis!$B$2:$B$823,"<"&(F15+1)) -> 0.22586053 | I15: =AVERAGEIFS($D$2:$D$791,Analysis!$B$2:$B$791,">="&F15,Analysis!$B$2:$B$791,"<"&(F15+1)) -> 1361.1008 | J15: =Annual!H15 -> -0.017695721 | K15: =$O$16+$O$17*H15+$O$18*I15 -> 0.033613025 | N15: Multiple regression: anomaly = a + b·log2(CO2) + c·TSI
A16: =Analysis!A16 -> 5/1959 | B16: =Analysis!E16 -> 0.04 | C16: =Analysis!F16 -> 0.184915 | D16: 1361.74 | F16: 1973 | G16: =AVERAGEIFS(Analysis!$E$2:$E$823,Analysis!$B$2:$B$823,">="&F16,Analysis!$B$2:$B$823,"<"&(F16+1)) -> 0.16083333 | H16: =AVERAGEIFS(Analysis!$F$2:$F$823,Analysis!$B$2:$B$823,">="&F16,Analysis!$B$2:$B$823,"<"&(F16+1)) -> 0.23562788 | I16: =AVERAGEIFS($D$2:$D$791,Analysis!$B$2:$B$791,">="&F16,Analysis!$B$2:$B$791,"<"&(F16+1)) -> 1360.865 | J16: =Annual!H16 -> 0.10718507 | K16: =$O$16+$O$17*H16+$O$18*I16 -> 0.043717258 | N16: a (intercept) | O16: =INDEX(LINEST($G$2:$G$66,$H$2:$H$66:$I$2:$I$66),1,3) -> -92.335343
A17: =Analysis!A17 -> 6/1959 | B17: =Analysis!E17 -> 0.03 | C17: =Analysis!F17 -> 0.18428029 | D17: 1361.6 | F17: 1974 | G17: =AVERAGEIFS(Analysis!$E$2:$E$823,Analysis!$B$2:$B$823,">="&F17,Analysis!$B$2:$B$823,"<"&(F17+1)) -> -0.071666667 | H17: =AVERAGEIFS(Analysis!$F$2:$F$823,Analysis!$B$2:$B$823,">="&F17,Analysis!$B$2:$B$823,"<"&(F17+1)) -> 0.23785982 | I17: =AVERAGEIFS($D$2:$D$791,Analysis!$B$2:$B$791,">="&F17,Analysis!$B$2:$B$791,"<"&(F17+1)) -> 1360.7717 | J17: =Annual!H17 -> -0.13143577 | K17: =$O$16+$O$17*H17+$O$18*I17 -> 0.043366862 | N17: b: °C per CO2 doubling | O17: =INDEX(LINEST($G$2:$G$66,$H$2:$H$66:$I$2:$I$66),1,2) -> 2.6623896
A18: =Analysis!A18 -> 7/1959 | B18: =Analysis!E18 -> 0.03 | C18: =Analysis!F18 -> 0.17696099 | D18: 1361.81 | F18: 1975 | G18: =AVERAGEIFS(Analysis!$E$2:$E$823,Analysis!$B$2:$B$823,">="&F18,Analysis!$B$2:$B$823,"<"&(F18+1)) -> -0.013333333 | H18: =AVERAGEIFS(Analysis!$F$2:$F$823,Analysis!$B$2:$B$823,">="&F18,Analysis!$B$2:$B$823,"<"&(F18+1)) -> 0.24193918 | I18: =AVERAGEIFS($D$2:$D$791,Analysis!$B$2:$B$791,">="&F18,Analysis!$B$2:$B$791,"<"&(F18+1)) -> 1360.715 | J18: =Annual!H18 -> -0.084289639 | K18: =$O$16+$O$17*H18+$O$18*I18 -> 0.050407158 | N18: c: °C per W/m² of TSI | O18: =INDEX(LINEST($G$2:$G$66,$H$2:$H$66:$I$2:$I$66),1,1) -> 0.067421623
A19: =Analysis!A19 -> 8/1959 | B19: =Analysis!E19 -> -0.01 | C19: =Analysis!F19 -> 0.16900871 | D19: 1361.19 | F19: 1976 | G19: =AVERAGEIFS(Analysis!$E$2:$E$823,Analysis!$B$2:$B$823,">="&F19,Analysis!$B$2:$B$823,"<"&(F19+1)) -> -0.0975 | H19: =AVERAGEIFS(Analysis!$F$2:$F$823,Analysis!$B$2:$B$823,">="&F19,Analysis!$B$2:$B$823,"<"&(F19+1)) -> 0.24584257 | I19: =AVERAGEIFS($D$2:$D$791,Analysis!$B$2:$B$791,">="&F19,Analysis!$B$2:$B$791,"<"&(F19+1)) -> 1360.6942 | J19: =Annual!H19 -> -0.17916092 | K19: =$O$16+$O$17*H19+$O$18*I19 -> 0.059394892 | N19: R² | O19: =INDEX(LINEST($G$2:$G$66,$H$2:$H$66:$I$2:$I$66,TRUE(),TRUE()),3,1) -> 0.93264127
A20: =Analysis!A20 -> 9/1959 | B20: =Analysis!E20 -> -0.06 | C20: =Analysis!F20 -> 0.16460241 | D20: 1361.64 | F20: 1977 | G20: =AVERAGEIFS(Analysis!$E$2:$E$823,Analysis!$B$2:$B$823,">="&F20,Analysis!$B$2:$B$823,"<"&(F20+1)) -> 0.17833333 | H20: =AVERAGEIFS(Analysis!$F$2:$F$823,Analysis!$B$2:$B$823,">="&F20,Analysis!$B$2:$B$823,"<"&(F20+1)) -> 0.25372587 | I20: =AVERAGEIFS($D$2:$D$791,Analysis!$B$2:$B$791,">="&F20,Analysis!$B$2:$B$791,"<"&(F20+1)) -> 1360.8892 | J20: =Annual!H20 -> 0.075053352 | K20: =$O$16+$O$17*H20+$O$18*I20 -> 0.093530512 | N20: implied °C per W/m² of solar FORCING | O20: =O18/((1-O3)/4) -> 0.38526642
A21: =Analysis!A21 -> 10/1959 | B21: =Analysis!E21 -> -0.07 | C21: =Analysis!F21 -> 0.16225608 | D21: 1361.6 | F21: 1978 | G21: =AVERAGEIFS(Analysis!$E$2:$E$823,Analysis!$B$2:$B$823,">="&F21,Analysis!$B$2:$B$823,"<"&(F21+1)) -> 0.066666667 | H21: =AVERAGEIFS(Analysis!$F$2:$F$823,Analysis!$B$2:$B$823,">="&F21,Analysis!$B$2:$B$823,"<"&(F21+1)) -> 0.26049698 | I21: =AVERAGEIFS($D$2:$D$791,Analysis!$B$2:$B$791,">="&F21,Analysis!$B$2:$B$791,"<"&(F21+1)) -> 1361.2133 | J21: =Annual!H21 -> -0.055182327 | K21: =$O$16+$O$17*H21+$O$18*I21 -> 0.13341369
A22: =Analysis!A22 -> 11/1959 | B22: =Analysis!E22 -> -0.08 | C22: =Analysis!F22 -> 0.16905454 | D22: 1361.37 | F22: 1979 | G22: =AVERAGEIFS(Analysis!$E$2:$E$823,Analysis!$B$2:$B$823,">="&F22,Analysis!$B$2:$B$823,"<"&(F22+1)) -> 0.16416667 | H22: =AVERAGEIFS(Analysis!$F$2:$F$823,Analysis!$B$2:$B$823,">="&F22,Analysis!$B$2:$B$823,"<"&(F22+1)) -> 0.26659554 | I22: =AVERAGEIFS($D$2:$D$791,Analysis!$B$2:$B$791,">="&F22,Analysis!$B$2:$B$791,"<"&(F22+1)) -> 1361.6 | J22: =Annual!H22 -> 0.025593049 | K22: =$O$16+$O$17*H22+$O$18*I22 -> 0.17572013 | N22: Forcing comparison over the record
A23: =Analysis!A23 -> 12/1959 | B23: =Analysis!E23 -> 0 | C23: =Analysis!F23 -> 0.17257895 | D23: 1361.39 | F23: 1980 | G23: =AVERAGEIFS(Analysis!$E$2:$E$823,Analysis!$B$2:$B$823,">="&F23,Analysis!$B$2:$B$823,"<"&(F23+1)) -> 0.25583333 | H23: =AVERAGEIFS(Analysis!$F$2:$F$823,Analysis!$B$2:$B$823,">="&F23,Analysis!$B$2:$B$823,"<"&(F23+1)) -> 0.27482719 | I23: =AVERAGEIFS($D$2:$D$791,Analysis!$B$2:$B$791,">="&F23,Analysis!$B$2:$B$791,"<"&(F23+1)) -> 1361.6375 | J23: =Annual!H23 -> 0.094685333 | K23: =$O$16+$O$17*H23+$O$18*I23 -> 0.2001643 | N23: Solar-cycle forcing amplitude (W/m²) | O23: =O9*(1-O3)/4 -> 0.24470833
A24: =Analysis!A24 -> 1/1960 | B24: =Analysis!E24 -> 0 | C24: =Analysis!F24 -> 0.17645956 | D24: 1361.48 | F24: 1981 | G24: =AVERAGEIFS(Analysis!$E$2:$E$823,Analysis!$B$2:$B$823,">="&F24,Analysis!$B$2:$B$823,"<"&(F24+1)) -> 0.32333333 | H24: =AVERAGEIFS(Analysis!$F$2:$F$823,Analysis!$B$2:$B$823,">="&F24,Analysis!$B$2:$B$823,"<"&(F24+1)) -> 0.28059167 | I24: =AVERAGEIFS($D$2:$D$791,Analysis!$B$2:$B$791,">="&F24,Analysis!$B$2:$B$791,"<"&(F24+1)) -> 1361.685 | J24: =Annual!H24 -> 0.14637689 | K24: =$O$16+$O$17*H24+$O$18*I24 -> 0.21871411 | N24: CO2 forcing change, Mar 1958 to Dec 2023 (W/m²) | O24: =O4*LN(Analysis!D791/Analysis!D2) -> 1.5506945
A25: =Analysis!A25 -> 2/1960 | B25: =Analysis!E25 -> 0.13 | C25: =Analysis!F25 -> 0.17896499 | D25: 1361.54 | F25: 1982 | G25: =AVERAGEIFS(Analysis!$E$2:$E$823,Analysis!$B$2:$B$823,">="&F25,Analysis!$B$2:$B$823,"<"&(F25+1)) -> 0.13916667 | H25: =AVERAGEIFS(Analysis!$F$2:$F$823,Analysis!$B$2:$B$823,">="&F25,Analysis!$B$2:$B$823,"<"&(F25+1)) -> 0.28634093 | I25: =AVERAGEIFS($D$2:$D$791,Analysis!$B$2:$B$791,">="&F25,Analysis!$B$2:$B$791,"<"&(F25+1)) -> 1361.2258 | J25: =Annual!H25 -> -0.053556499 | K25: =$O$16+$O$17*H25+$O$18*I25 -> 0.20306314 | N25: Ratio CO2 / solar cycle | O25: =O24/O23 -> 6.3369091
A26: =Analysis!A26 -> 3/1960 | B26: =Analysis!E26 -> -0.35 | C26: =Analysis!F26 -> 0.18169323 | D26: 1361.63 | F26: 1983 | G26: =AVERAGEIFS(Analysis!$E$2:$E$823,Analysis!$B$2:$B$823,">="&F26,Analysis!$B$2:$B$823,"<"&(F26+1)) -> 0.315 | H26: =AVERAGEIFS(Analysis!$F$2:$F$823,Analysis!$B$2:$B$823,">="&F26,Analysis!$B$2:$B$823,"<"&(F26+1)) -> 0.293402 | I26: =AVERAGEIFS($D$2:$D$791,Analysis!$B$2:$B$791,">="&F26,Analysis!$B$2:$B$791,"<"&(F26+1)) -> 1361.2142 | J26: =Annual!H26 -> 0.10291264 | K26: =$O$16+$O$17*H26+$O$18*I26 -> 0.22107587 | N26: Expected solar-cycle temperature swing (°C) | O26: =O23*O20 -> 0.094277903
A27: =Analysis!A27 -> 4/1960 | B27: =Analysis!E27 -> -0.15 | C27: =Analysis!F27 -> 0.18826527 | D27: 1361.28 | F27: 1984 | G27: =AVERAGEIFS(Analysis!$E$2:$E$823,Analysis!$B$2:$B$823,">="&F27,Analysis!$B$2:$B$823,"<"&(F27+1)) -> 0.155 | H27: =AVERAGEIFS(Analysis!$F$2:$F$823,Analysis!$B$2:$B$823,">="&F27,Analysis!$B$2:$B$823,"<"&(F27+1)) -> 0.30058891 | I27: =AVERAGEIFS($D$2:$D$791,Analysis!$B$2:$B$791,">="&F27,Analysis!$B$2:$B$791,"<"&(F27+1)) -> 1360.7892 | J27: =Annual!H27 -> -0.076796642 | K27: =$O$16+$O$17*H27+$O$18*I27 -> 0.21155602
A28: =Analysis!A28 -> 5/1960 | B28: =Analysis!E28 -> -0.08 | C28: =Analysis!F28 -> 0.19278032 | D28: 1361.33 | F28: 1985 | G28: =AVERAGEIFS(Analysis!$E$2:$E$823,Analysis!$B$2:$B$823,">="&F28,Analysis!$B$2:$B$823,"<"&(F28+1)) -> 0.11833333 | H28: =AVERAGEIFS(Analysis!$F$2:$F$823,Analysis!$B$2:$B$823,">="&F28,Analysis!$B$2:$B$823,"<"&(F28+1)) -> 0.3067888 | I28: =AVERAGEIFS($D$2:$D$791,Analysis!$B$2:$B$791,">="&F28,Analysis!$B$2:$B$791,"<"&(F28+1)) -> 1360.6325 | J28: =Annual!H28 -> -0.13046583 | K28: =$O$16+$O$17*H28+$O$18*I28 -> 0.21749983 | N28: How to read this sheet
A29: =Analysis!A29 -> 6/1960 | B29: =Analysis!E29 -> -0.04 | C29: =Analysis!F29 -> 0.1907503 | D29: 1361.56 | F29: 1986 | G29: =AVERAGEIFS(Analysis!$E$2:$E$823,Analysis!$B$2:$B$823,">="&F29,Analysis!$B$2:$B$823,"<"&(F29+1)) -> 0.18 | H29: =AVERAGEIFS(Analysis!$F$2:$F$823,Analysis!$B$2:$B$823,">="&F29,Analysis!$B$2:$B$823,"<"&(F29+1)) -> 0.31201398 | I29: =AVERAGEIFS($D$2:$D$791,Analysis!$B$2:$B$791,">="&F29,Analysis!$B$2:$B$791,"<"&(F29+1)) -> 1360.6417 | J29: =Annual!H29 -> -0.083128628 | K29: =$O$16+$O$17*H29+$O$18*I29 -> 0.23202932 | N29: 1. TSI alone: essentially zero explanatory power (R² ~0.00) and no trend over 1959-2023. The Sun cannot account for the warming trend in this record.
A30: =Analysis!A30 -> 7/1960 | B30: =Analysis!E30 -> -0.04 | C30: =Analysis!F30 -> 0.18441633 | D30: 1361.34 | F30: 1987 | G30: =AVERAGEIFS(Analysis!$E$2:$E$823,Analysis!$B$2:$B$823,">="&F30,Analysis!$B$2:$B$823,"<"&(F30+1)) -> 0.32166667 | H30: =AVERAGEIFS(Analysis!$F$2:$F$823,Analysis!$B$2:$B$823,">="&F30,Analysis!$B$2:$B$823,"<"&(F30+1)) -> 0.31907046 | I30: =AVERAGEIFS($D$2:$D$791,Analysis!$B$2:$B$791,">="&F30,Analysis!$B$2:$B$791,"<"&(F30+1)) -> 1360.7825 | J30: =Annual!H30 -> 0.039186424 | K30: =$O$16+$O$17*H30+$O$18*I30 -> 0.26031164 | N30: 2. But the Sun is not zero: the ~11-year cycle shows up as a small positive correlation with the leftovers of the CO2 fit, and in the multiple regression as ~0.07 °C per W/m² of TSI, i.e. a ~0.1 °C peak-to-trough cycle. That matches the published estimate, and finding it is a good sign the data and method are sound.
A31: =Analysis!A31 -> 8/1960 | B31: =Analysis!E31 -> 0.02 | C31: =Analysis!F31 -> 0.17404111 | D31: 1361.38 | F31: 1988 | G31: =AVERAGEIFS(Analysis!$E$2:$E$823,Analysis!$B$2:$B$823,">="&F31,Analysis!$B$2:$B$823,"<"&(F31+1)) -> 0.39 | H31: =AVERAGEIFS(Analysis!$F$2:$F$823,Analysis!$B$2:$B$823,">="&F31,Analysis!$B$2:$B$823,"<"&(F31+1)) -> 0.32886052 | I31: =AVERAGEIFS($D$2:$D$791,Analysis!$B$2:$B$791,">="&F31,Analysis!$B$2:$B$791,"<"&(F31+1)) -> 1361.1225 | J31: =Annual!H31 -> 0.080671613 | K31: =$O$16+$O$17*H31+$O$18*I31 -> 0.30929994 | N31: 3. Adding TSI barely moves the CO2 coefficient. The apparent 2.74 to ~2.66 shift is the shorter window the TSI series forces (ending 2023), not the Sun: on the same months the CO2-only slope is already 2.640 (Volcanic!N31), and Sensitivity!AB22:AC22 gives 2.662 against 2.715 on the two windows. TSI and log2(CO2) are nearly orthogonal.
A32: =Analysis!A32 -> 9/1960 | B32: =Analysis!E32 -> 0.07 | C32: =Analysis!F32 -> 0.1661186 | D32: 1361.59 | F32: 1989 | G32: =AVERAGEIFS(Analysis!$E$2:$E$823,Analysis!$B$2:$B$823,">="&F32,Analysis!$B$2:$B$823,"<"&(F32+1)) -> 0.27416667 | H32: =AVERAGEIFS(Analysis!$F$2:$F$823,Analysis!$B$2:$B$823,">="&F32,Analysis!$B$2:$B$823,"<"&(F32+1)) -> 0.33505818 | I32: =AVERAGEIFS($D$2:$D$791,Analysis!$B$2:$B$791,">="&F32,Analysis!$B$2:$B$791,"<"&(F32+1)) -> 1361.64 | J32: =Annual!H32 -> -0.052158107 | K32: =$O$16+$O$17*H32+$O$18*I32 -> 0.36069121 | N32: 4. Forcing arithmetic: the whole solar cycle is worth ~0.25 W/m²; CO2 forcing grew ~1.5 W/m² across the record, about six times the cycle amplitude, and it is a one-way trend rather than an oscillation.
A33: =Analysis!A33 -> 10/1960 | B33: =Analysis!E33 -> 0.06 | C33: =Analysis!F33 -> 0.16455644 | D33: 1361.44 | F33: 1990 | G33: =AVERAGEIFS(Analysis!$E$2:$E$823,Analysis!$B$2:$B$823,">="&F33,Analysis!$B$2:$B$823,"<"&(F33+1)) -> 0.44916667 | H33: =AVERAGEIFS(Analysis!$F$2:$F$823,Analysis!$B$2:$B$823,">="&F33,Analysis!$B$2:$B$823,"<"&(F33+1)) -> 0.34014661 | I33: =AVERAGEIFS($D$2:$D$791,Analysis!$B$2:$B$791,">="&F33,Analysis!$B$2:$B$791,"<"&(F33+1)) -> 1361.5533 | J33: =Annual!H33 -> 0.10888745 | K33: =$O$16+$O$17*H33+$O$18*I33 -> 0.36839538 | N33: 5. Same caveats as elsewhere: descriptive regressions on a 65-year record, not a sensitivity estimate. Aerosols, other greenhouse gases, volcanoes and ENSO are still not in the model.
A34: =Analysis!A34 -> 11/1960 | B34: =Analysis!E34 -> -0.11 | C34: =Analysis!F34 -> 0.169925 | D34: 1361.23 | F34: 1991 | G34: =AVERAGEIFS(Analysis!$E$2:$E$823,Analysis!$B$2:$B$823,">="&F34,Analysis!$B$2:$B$823,"<"&(F34+1)) -> 0.4075 | H34: =AVERAGEIFS(Analysis!$F$2:$F$823,Analysis!$B$2:$B$823,">="&F34,Analysis!$B$2:$B$823,"<"&(F34+1)) -> 0.34522236 | I34: =AVERAGEIFS($D$2:$D$791,Analysis!$B$2:$B$791,">="&F34,Analysis!$B$2:$B$791,"<"&(F34+1)) -> 1361.5208 | J34: =Annual!H34 -> 0.053301102 | K34: =$O$16+$O$17*H34+$O$18*I34 -> 0.3797178
A35: =Analysis!A35 -> 12/1960 | B35: =Analysis!E35 -> 0.19 | C35: =Analysis!F35 -> 0.17536491 | D35: 1361.34 | F35: 1992 | G35: =AVERAGEIFS(Analysis!$E$2:$E$823,Analysis!$B$2:$B$823,">="&F35,Analysis!$B$2:$B$823,"<"&(F35+1)) -> 0.22416667 | H35: =AVERAGEIFS(Analysis!$F$2:$F$823,Analysis!$B$2:$B$823,">="&F35,Analysis!$B$2:$B$823,"<"&(F35+1)) -> 0.34862967 | I35: =AVERAGEIFS($D$2:$D$791,Analysis!$B$2:$B$791,">="&F35,Analysis!$B$2:$B$791,"<"&(F35+1)) -> 1361.3092 | J35: =Annual!H35 -> -0.13937641 | K35: =$O$16+$O$17*H35+$O$18*I35 -> 0.37451849
A36: =Analysis!A36 -> 1/1961 | B36: =Analysis!E36 -> 0.07 | C36: =Analysis!F36 -> 0.17855531 | D36: 1361.24 | F36: 1993 | G36: =AVERAGEIFS(Analysis!$E$2:$E$823,Analysis!$B$2:$B$823,">="&F36,Analysis!$B$2:$B$823,"<"&(F36+1)) -> 0.23333333 | H36: =AVERAGEIFS(Analysis!$F$2:$F$823,Analysis!$B$2:$B$823,">="&F36,Analysis!$B$2:$B$823,"<"&(F36+1)) -> 0.3513444 | I36: =AVERAGEIFS($D$2:$D$791,Analysis!$B$2:$B$791,">="&F36,Analysis!$B$2:$B$791,"<"&(F36+1)) -> 1360.9408 | J36: =Annual!H36 -> -0.13765459 | K36: =$O$16+$O$17*H36+$O$18*I36 -> 0.35691253
A37: =Analysis!A37 -> 2/1961 | B37: =Analysis!E37 -> 0.19 | C37: =Analysis!F37 -> 0.18223826 | D37: 1361.13 | F37: 1994 | G37: =AVERAGEIFS(Analysis!$E$2:$E$823,Analysis!$B$2:$B$823,">="&F37,Analysis!$B$2:$B$823,"<"&(F37+1)) -> 0.31583333 | H37: =AVERAGEIFS(Analysis!$F$2:$F$823,Analysis!$B$2:$B$823,">="&F37,Analysis!$B$2:$B$823,"<"&(F37+1)) -> 0.35837405 | I37: =AVERAGEIFS($D$2:$D$791,Analysis!$B$2:$B$791,">="&F37,Analysis!$B$2:$B$791,"<"&(F37+1)) -> 1360.7442 | J37: =Annual!H37 -> -0.074432624 | K37: =$O$16+$O$17*H37+$O$18*I37 -> 0.36236861
A38: =Analysis!A38 -> 3/1961 | B38: =Analysis!E38 -> 0.09 | C38: =Analysis!F38 -> 0.18604772 | D38: 1361.04 | F38: 1995 | G38: =AVERAGEIFS(Analysis!$E$2:$E$823,Analysis!$B$2:$B$823,">="&F38,Analysis!$B$2:$B$823,"<"&(F38+1)) -> 0.4475 | H38: =AVERAGEIFS(Analysis!$F$2:$F$823,Analysis!$B$2:$B$823,">="&F38,Analysis!$B$2:$B$823,"<"&(F38+1)) -> 0.36642609 | I38: =AVERAGEIFS($D$2:$D$791,Analysis!$B$2:$B$791,">="&F38,Analysis!$B$2:$B$791,"<"&(F38+1)) -> 1360.7325 | J38: =Annual!H38 -> 0.035152237 | K38: =$O$16+$O$17*H38+$O$18*I38 -> 0.38301968
A39: =Analysis!A39 -> 4/1961 | B39: =Analysis!E39 -> 0.13 | C39: =Analysis!F39 -> 0.19029879 | D39: 1360.93 | F39: 1996 | G39: =AVERAGEIFS(Analysis!$E$2:$E$823,Analysis!$B$2:$B$823,">="&F39,Analysis!$B$2:$B$823,"<"&(F39+1)) -> 0.33416667 | H39: =AVERAGEIFS(Analysis!$F$2:$F$823,Analysis!$B$2:$B$823,">="&F39,Analysis!$B$2:$B$823,"<"&(F39+1)) -> 0.37350294 | I39: =AVERAGEIFS($D$2:$D$791,Analysis!$B$2:$B$791,">="&F39,Analysis!$B$2:$B$791,"<"&(F39+1)) -> 1360.6758 | J39: =Annual!H39 -> -0.097588567 | K39: =$O$16+$O$17*H39+$O$18*I39 -> 0.39804045
A40: =Analysis!A40 -> 5/1961 | B40: =Analysis!E40 -> 0.12 | C40: =Analysis!F40 -> 0.1952576 | D40: 1361.01 | F40: 1997 | G40: =AVERAGEIFS(Analysis!$E$2:$E$823,Analysis!$B$2:$B$823,">="&F40,Analysis!$B$2:$B$823,"<"&(F40+1)) -> 0.4675 | H40: =AVERAGEIFS(Analysis!$F$2:$F$823,Analysis!$B$2:$B$823,">="&F40,Analysis!$B$2:$B$823,"<"&(F40+1)) -> 0.37800252 | I40: =AVERAGEIFS($D$2:$D$791,Analysis!$B$2:$B$791,">="&F40,Analysis!$B$2:$B$791,"<"&(F40+1)) -> 1360.8067 | J40: =Annual!H40 -> 0.023405149 | K40: =$O$16+$O$17*H40+$O$18*I40 -> 0.4188411
A41: =Analysis!A41 -> 6/1961 | B41: =Analysis!E41 -> 0.11 | C41: =Analysis!F41 -> 0.19160777 | D41: 1360.82 | F41: 1998 | G41: =AVERAGEIFS(Analysis!$E$2:$E$823,Analysis!$B$2:$B$823,">="&F41,Analysis!$B$2:$B$823,"<"&(F41+1)) -> 0.60916667 | H41: =AVERAGEIFS(Analysis!$F$2:$F$823,Analysis!$B$2:$B$823,">="&F41,Analysis!$B$2:$B$823,"<"&(F41+1)) -> 0.38970838 | I41: =AVERAGEIFS($D$2:$D$791,Analysis!$B$2:$B$791,">="&F41,Analysis!$B$2:$B$791,"<"&(F41+1)) -> 1361.1742 | J41: =Annual!H41 -> 0.1329698 | K41: =$O$16+$O$17*H41+$O$18*I41 -> 0.4747841
A42: =Analysis!A42 -> 7/1961 | B42: =Analysis!E42 -> 0.01 | C42: =Analysis!F42 -> 0.1861383 | D42: 1360.94 | F42: 1999 | G42: =AVERAGEIFS(Analysis!$E$2:$E$823,Analysis!$B$2:$B$823,">="&F42,Analysis!$B$2:$B$823,"<"&(F42+1)) -> 0.3825 | H42: =AVERAGEIFS(Analysis!$F$2:$F$823,Analysis!$B$2:$B$823,">="&F42,Analysis!$B$2:$B$823,"<"&(F42+1)) -> 0.39637329 | I42: =AVERAGEIFS($D$2:$D$791,Analysis!$B$2:$B$791,">="&F42,Analysis!$B$2:$B$791,"<"&(F42+1)) -> 1361.4808 | J42: =Annual!H42 -> -0.11197462 | K42: =$O$16+$O$17*H42+$O$18*I42 -> 0.51320464
A43: =Analysis!A43 -> 8/1961 | B43: =Analysis!E43 -> 0.01 | C43: =Analysis!F43 -> 0.17809997 | D43: 1361.23 | F43: 2000 | G43: =AVERAGEIFS(Analysis!$E$2:$E$823,Analysis!$B$2:$B$823,">="&F43,Analysis!$B$2:$B$823,"<"&(F43+1)) -> 0.39333333 | H43: =AVERAGEIFS(Analysis!$F$2:$F$823,Analysis!$B$2:$B$823,">="&F43,Analysis!$B$2:$B$823,"<"&(F43+1)) -> 0.40094355 | I43: =AVERAGEIFS($D$2:$D$791,Analysis!$B$2:$B$791,">="&F43,Analysis!$B$2:$B$791,"<"&(F43+1)) -> 1361.6592 | J43: =Annual!H43 -> -0.11367474 | K43: =$O$16+$O$17*H43+$O$18*I43 -> 0.537396
A44: =Analysis!A44 -> 9/1961 | B44: =Analysis!E44 -> 0.08 | C44: =Analysis!F44 -> 0.1698792 | D44: 1360.78 | F44: 2001 | G44: =AVERAGEIFS(Analysis!$E$2:$E$823,Analysis!$B$2:$B$823,">="&F44,Analysis!$B$2:$B$823,"<"&(F44+1)) -> 0.53333333 | H44: =AVERAGEIFS(Analysis!$F$2:$F$823,Analysis!$B$2:$B$823,">="&F44,Analysis!$B$2:$B$823,"<"&(F44+1)) -> 0.40721575 | I44: =AVERAGEIFS($D$2:$D$791,Analysis!$B$2:$B$791,">="&F44,Analysis!$B$2:$B$791,"<"&(F44+1)) -> 1361.5692 | J44: =Annual!H44 -> 0.0091244626 | K44: =$O$16+$O$17*H44+$O$18*I44 -> 0.54802708
A45: =Analysis!A45 -> 10/1961 | B45: =Analysis!E45 -> 0 | C45: =Analysis!F45 -> 0.1713441 | D45: 1361.02 | F45: 2002 | G45: =AVERAGEIFS(Analysis!$E$2:$E$823,Analysis!$B$2:$B$823,">="&F45,Analysis!$B$2:$B$823,"<"&(F45+1)) -> 0.6275 | H45: =AVERAGEIFS(Analysis!$F$2:$F$823,Analysis!$B$2:$B$823,">="&F45,Analysis!$B$2:$B$823,"<"&(F45+1)) -> 0.41548364 | I45: =AVERAGEIFS($D$2:$D$791,Analysis!$B$2:$B$791,">="&F45,Analysis!$B$2:$B$791,"<"&(F45+1)) -> 1361.6367 | J45: =Annual!H45 -> 0.080617354 | K45: =$O$16+$O$17*H45+$O$18*I45 -> 0.57459039
... A66: =Analysis!A66 -> 7/1963 | B66: =Analysis!E66 -> 0.06 | C66: =Analysis!F66 -> 0.19147241 | D66: 1360.76 | F66: 2023 | G66: =AVERAGEIFS(Analysis!$E$2:$E$823,Analysis!$B$2:$B$823,">="&F66,Analysis!$B$2:$B$823,"<"&(F66+1)) -> 1.1725 | H66: =AVERAGEIFS(Analysis!$F$2:$F$823,Analysis!$B$2:$B$823,">="&F66,Analysis!$B$2:$B$823,"<"&(F66+1)) -> 0.58865436 | I66: =AVERAGEIFS($D$2:$D$791,Analysis!$B$2:$B$791,">="&F66,Analysis!$B$2:$B$791,"<"&(F66+1)) -> 1362.0025 | J66: =Annual!H66 -> 0.15071599 | K66: =$O$16+$O$17*H66+$O$18*I66 -> 1.0603034
A67: =Analysis!A67 -> 8/1963 | B67: =Analysis!E67 -> 0.22 | C67: =Analysis!F67 -> 0.1825561 | D67: 1360.72
A68: =Analysis!A68 -> 9/1963 | B68: =Analysis!E68 -> 0.17 | C68: =Analysis!F68 -> 0.17545617 | D68: 1360.57
A69: =Analysis!A69 -> 10/1963 | B69: =Analysis!E69 -> 0.15 | C69: =Analysis!F69 -> 0.17445208 | D69: 1360.7
A70: =Analysis!A70 -> 11/1963 | B70: =Analysis!E70 -> 0.15 | C70: =Analysis!F70 -> 0.17937455 | D70: 1360.84
A71: =Analysis!A71 -> 12/1963 | B71: =Analysis!E71 -> -0.03 | C71: =Analysis!F71 -> 0.18518694 | D71: 1360.78
A72: =Analysis!A72 -> 1/1964 | B72: =Analysis!E72 -> -0.09 | C72: =Analysis!F72 -> 0.19070515 | D72: 1360.71
A73: =Analysis!A73 -> 2/1964 | B73: =Analysis!E73 -> -0.1 | C73: =Analysis!F73 -> 0.1928254 | D73: 1360.74
A74: =Analysis!A74 -> 3/1964 | B74: =Analysis!E74 -> -0.21 | C74: =Analysis!F74 -> 0.19602244 | D74: 1360.71
A75: =Analysis!A75 -> 4/1964 | B75: =Analysis!E75 -> -0.32 | C75: =Analysis!F75 -> 0.20091682 | D75: 1360.78
A76: =Analysis!A76 -> 5/1964 | B76: =Analysis!E76 -> -0.25 | C76: =Analysis!F76 -> 0.20275353 | D76: 1360.71
A77: =Analysis!A77 -> 6/1964 | B77: =Analysis!E77 -> -0.04 | C77: =Analysis!F77 -> 0.20114093 | D77: 1360.73
A78: =Analysis!A78 -> 7/1964 | B78: =Analysis!E78 -> -0.04 | C78: =Analysis!F78 -> 0.19462742 | D78: 1360.7
... A791: =Analysis!A791 -> 12/2023 | B791: =Analysis!E791 -> 1.36 | C791: =Analysis!F791 -> 0.59133747 | D791: 1361.97

Sheet ENSO
A1: Month/Year | B1: Anomaly (°C) | C1: log2(CO2/280) | D1: ONI lagged 3 mo | E1: TSI (W/m²) | F1: ONI (same month) | G1: Residual after CO2-only fit | H1: Fitted: CO2 + ENSO | I1: Residual after CO2 + ENSO | J1: ENSO-adjusted anomaly
A2: =Analysis!A2 -> 3/1958 | B2: =Analysis!E2 -> 0.08 | C2: =Analysis!F2 -> 0.17317313 | E2: =Solar!D2 -> 1361.03 | G2: =B2-($N$4+$N$5*C2) -> 0.19317526 | H2: =IF(D2="","",$N$14+$N$15*C2+$N$16*D2) | I2: =IF(D2="","",B2-H2) | J2: =IF(D2="","",B2-$N$16*D2) | M2: Monthly regressions
A3: =Analysis!A3 -> 4/1958 | B3: =Analysis!E3 -> 0.01 | C3: =Analysis!F3 -> 0.18110255 | E3: =Solar!D3 -> 1361.85 | G3: =B3-($N$4+$N$5*C3) -> 0.10149962 | H3: =IF(D3="","",$N$14+$N$15*C3+$N$16*D3) | I3: =IF(D3="","",B3-H3) | J3: =IF(D3="","",B3-$N$16*D3) | M3: CO2-only fit (all 822 months)
A4: =Analysis!A4 -> 5/1958 | B4: =Analysis!E4 -> 0.06 | C4: =Analysis!F4 -> 0.1813752 | E4: =Solar!D4 -> 1362.07 | G4: =B4-($N$4+$N$5*C4) -> 0.15075431 | H4: =IF(D4="","",$N$14+$N$15*C4+$N$16*D4) | I4: =IF(D4="","",B4-H4) | J4: =IF(D4="","",B4-$N$16*D4) | M4: intercept | N4: =INTERCEPT($B$2:$B$823,$C$2:$C$823) -> -0.58655637
A5: =Analysis!A5 -> 6/1958 | B5: =Analysis!E5 -> -0.09 | C5: =Analysis!F5 -> 0.18028428 | D5: =IF(F2="","",F2) | E5: =Solar!D5 -> 1362.08 | G5: =B5-($N$4+$N$5*C5) -> 0.0037364132 | H5: =IF(D5="","",$N$14+$N$15*C5+$N$16*D5) | I5: =IF(D5="","",B5-H5) | J5: =IF(D5="","",B5-$N$16*D5) | M5: slope, °C per doubling | N5: =SLOPE($B$2:$B$823,$C$2:$C$823) -> 2.7335713
A6: =Analysis!A6 -> 7/1958 | B6: =Analysis!E6 -> 0.05 | C6: =Analysis!F6 -> 0.1739041 | D6: =IF(F3="","",F3) | E6: =Solar!D6 -> 1361.68 | F6: 0.43 | G6: =B6-($N$4+$N$5*C6) -> 0.16117711 | H6: =IF(D6="","",$N$14+$N$15*C6+$N$16*D6) | I6: =IF(D6="","",B6-H6) | J6: =IF(D6="","",B6-$N$16*D6) | M6: R² | N6: =RSQ($B$2:$B$823,$C$2:$C$823) -> 0.86092237
A7: =Analysis!A7 -> 8/1958 | B7: =Analysis!E7 -> -0.05 | C7: =Analysis!F7 -> 0.16960437 | D7: =IF(F4="","",F4) | E7: =Solar!D7 -> 1361.92 | F7: 0.32 | G7: =B7-($N$4+$N$5*C7) -> 0.072930729 | H7: =IF(D7="","",$N$14+$N$15*C7+$N$16*D7) | I7: =IF(D7="","",B7-H7) | J7: =IF(D7="","",B7-$N$16*D7) | M7: residual std dev (°C) | N7: =STDEV($G$2:$G$823) -> 0.14507445
A8: =Analysis!A8 -> 9/1958 | B8: =Analysis!E8 -> -0.03 | C8: =Analysis!F8 -> 0.16170345 | D8: =IF(F5="","",F5) | E8: =Solar!D8 -> 1362.04 | F8: 0.28 | G8: =B8-($N$4+$N$5*C8) -> 0.11452845 | H8: =IF(D8="","",$N$14+$N$15*C8+$N$16*D8) | I8: =IF(D8="","",B8-H8) | J8: =IF(D8="","",B8-$N$16*D8) | M8: lag-1 autocorrelation of residuals (monthly) | N8: =CORREL($G$2:$G$822,$G$3:$G$823) -> 0.64377333
A9: =Analysis!A9 -> 10/1958 | B9: =Analysis!E9 -> 0.04 | C9: =Analysis!F9 -> 0.15805999 | D9: =IF(F6="","",F6) -> 0.43 | E9: =Solar!D9 -> 1361.99 | F9: 0.3 | G9: =B9-($N$4+$N$5*C9) -> 0.19448812 | H9: =IF(D9="","",$N$14+$N$15*C9+$N$16*D9) -> -0.12271685 | I9: =IF(D9="","",B9-H9) -> 0.16271685 | J9: =IF(D9="","",B9-$N$16*D9) -> 0.0025737589 | M9: Lag test: r between CO2-only residual and ONI lagged k months | P9: lag k (months) | Q9: r
A10: =Analysis!A10 -> 11/1958 | B10: =Analysis!E10 -> 0.02 | C10: =Analysis!F10 -> 0.16225608 | D10: =IF(F7="","",F7) -> 0.32 | E10: =Solar!D10 -> 1362.07 | F10: 0.36 | G10: =B10-($N$4+$N$5*C10) -> 0.16301779 | H10: =IF(D10="","",$N$14+$N$15*C10+$N$16*D10) -> -0.12076519 | I10: =IF(D10="","",B10-H10) -> 0.14076519 | J10: =IF(D10="","",B10-$N$16*D10) -> -0.0078520864 | P10: 0 | Q10: =CORREL($G$12:$G$823,OFFSET($F$12:$F$823,-P10,0)) -> 0.40219379
A11: =Analysis!A11 -> 12/1958 | B11: =Analysis!E11 -> 0.01 | C11: =Analysis!F11 -> 0.16841281 | D11: =IF(F8="","",F8) -> 0.28 | E11: =Solar!D11 -> 1361.54 | F11: 0.56 | G11: =B11-($N$4+$N$5*C11) -> 0.13618792 | H11: =IF(D11="","",$N$14+$N$15*C11+$N$16*D11) -> -0.10733541 | I11: =IF(D11="","",B11-H11) -> 0.11733541 | J11: =IF(D11="","",B11-$N$16*D11) -> -0.014370576 | P11: 1 | Q11: =CORREL($G$12:$G$823,OFFSET($F$12:$F$823,-P11,0)) -> 0.44939671
A12: =Analysis!A12 -> 1/1959 | B12: =Analysis!E12 -> 0.08 | C12: =Analysis!F12 -> 0.17257895 | D12: =IF(F9="","",F9) -> 0.3 | E12: =Solar!D12 -> 1361.36 | F12: 0.6 | G12: =B12-($N$4+$N$5*C12) -> 0.19479949 | H12: =IF(D12="","",$N$14+$N$15*C12+$N$16*D12) -> -0.094151127 | I12: =IF(D12="","",B12-H12) -> 0.17415113 | J12: =IF(D12="","",B12-$N$16*D12) -> 0.053888669 | P12: 2 | Q12: =CORREL($G$12:$G$823,OFFSET($F$12:$F$823,-P12,0)) -> 0.4697352
A13: =Analysis!A13 -> 2/1959 | B13: =Analysis!E13 -> 0.07 | C13: =Analysis!F13 -> 0.17673309 | D13: =IF(F10="","",F10) -> 0.36 | E13: =Solar!D13 -> 1361.98 | F13: 0.64 | G13: =B13-($N$4+$N$5*C13) -> 0.17344386 | H13: =IF(D13="","",$N$14+$N$15*C13+$N$16*D13) -> -0.077518287 | I13: =IF(D13="","",B13-H13) -> 0.14751829 | J13: =IF(D13="","",B13-$N$16*D13) -> 0.038666403 | M13: Two-factor: anomaly = a + b·log2(CO2) + c·ONI(lag 3) | P13: 3 | Q13: =CORREL($G$12:$G$823,OFFSET($F$12:$F$823,-P13,0)) -> 0.47136425
A14: =Analysis!A14 -> 3/1959 | B14: =Analysis!E14 -> 0.18 | C14: =Analysis!F14 -> 0.17746225 | D14: =IF(F11="","",F11) -> 0.56 | E14: =Solar!D14 -> 1361.39 | F14: 0.48 | G14: =B14-($N$4+$N$5*C14) -> 0.28145064 | H14: =IF(D14="","",$N$14+$N$15*C14+$N$16*D14) -> -0.058107871 | I14: =IF(D14="","",B14-H14) -> 0.23810787 | J14: =IF(D14="","",B14-$N$16*D14) -> 0.13125885 | M14: a | N14: =INDEX(LINEST($B$9:$B$823,$C$9:$C$823:$D$9:$D$823),1,3) -> -0.59430165 | P14: 4 | Q14: =CORREL($G$12:$G$823,OFFSET($F$12:$F$823,-P14,0)) -> 0.45237679
A15: =Analysis!A15 -> 4/1959 | B15: =Analysis!E15 -> 0.16 | C15: =Analysis!F15 -> 0.18232908 | D15: =IF(F12="","",F12) -> 0.6 | E15: =Solar!D15 -> 1361.71 | F15: 0.39 | G15: =B15-($N$4+$N$5*C15) -> 0.24814681 | H15: =IF(D15="","",$N$14+$N$15*C15+$N$16*D15) -> -0.041258173 | I15: =IF(D15="","",B15-H15) -> 0.20125817 | J15: =IF(D15="","",B15-$N$16*D15) -> 0.10777734 | M15: b: °C per CO2 doubling | N15: =INDEX(LINEST($B$9:$B$823,$C$9:$C$823:$D$9:$D$823),1,2) -> 2.7467961 | P15: 5 | Q15: =CORREL($G$12:$G$823,OFFSET($F$12:$F$823,-P15,0)) -> 0.4214056
A16: =Analysis!A16 -> 5/1959 | B16: =Analysis!E16 -> 0.04 | C16: =Analysis!F16 -> 0.184915 | D16: =IF(F13="","",F13) -> 0.64 | E16: =Solar!D16 -> 1361.74 | F16: 0.24 | G16: =B16-($N$4+$N$5*C16) -> 0.12107801 | H16: =IF(D16="","",$N$14+$N$15*C16+$N$16*D16) -> -0.030673659 | I16: =IF(D16="","",B16-H16) -> 0.070673659 | J16: =IF(D16="","",B16-$N$16*D16) -> -0.015704173 | M16: c: °C per unit ONI | N16: =INDEX(LINEST($B$9:$B$823,$C$9:$C$823:$D$9:$D$823),1,1) -> 0.08703777 | P16: 6 | Q16: =CORREL($G$12:$G$823,OFFSET($F$12:$F$823,-P16,0)) -> 0.38564353
A17: =Analysis!A17 -> 6/1959 | B17: =Analysis!E17 -> 0.03 | C17: =Analysis!F17 -> 0.18428029 | D17: =IF(F14="","",F14) -> 0.48 | E17: =Solar!D17 -> 1361.6 | F17: 0.02 | G17: =B17-($N$4+$N$5*C17) -> 0.11281303 | H17: =IF(D17="","",$N$14+$N$15*C17+$N$16*D17) -> -0.04634312 | I17: =IF(D17="","",B17-H17) -> 0.07634312 | J17: =IF(D17="","",B17-$N$16*D17) -> -0.01177813 | M17: R² | N17: =INDEX(LINEST($B$9:$B$823,$C$9:$C$823:$D$9:$D$823,TRUE(),TRUE()),3,1) -> 0.89162717
A18: =Analysis!A18 -> 7/1959 | B18: =Analysis!E18 -> 0.03 | C18: =Analysis!F18 -> 0.17696099 | D18: =IF(F15="","",F15) -> 0.39 | E18: =Solar!D18 -> 1361.81 | F18: -0.19 | G18: =B18-($N$4+$N$5*C18) -> 0.13282087 | H18: =IF(D18="","",$N$14+$N$15*C18+$N$16*D18) -> -0.074281151 | I18: =IF(D18="","",B18-H18) -> 0.10428115 | J18: =IF(D18="","",B18-$N$16*D18) -> -0.0039447303 | M18: months in fit | N18: =COUNT($D$9:$D$823) -> 815
A19: =Analysis!A19 -> 8/1959 | B19: =Analysis!E19 -> -0.01 | C19: =Analysis!F19 -> 0.16900871 | D19: =IF(F16="","",F16) -> 0.24 | E19: =Solar!D19 -> 1361.19 | F19: -0.23 | G19: =B19-($N$4+$N$5*C19) -> 0.11455899 | H19: =IF(D19="","",$N$14+$N$15*C19+$N$16*D19) -> -0.1091801 | I19: =IF(D19="","",B19-H19) -> 0.099180104 | J19: =IF(D19="","",B19-$N$16*D19) -> -0.030889065 | M19: residual std dev (°C) | N19: =STDEV($I$9:$I$823) -> 0.12801797
A20: =Analysis!A20 -> 9/1959 | B20: =Analysis!E20 -> -0.06 | C20: =Analysis!F20 -> 0.16460241 | D20: =IF(F17="","",F17) -> 0.02 | E20: =Solar!D20 -> 1361.64 | F20: -0.04 | G20: =B20-($N$4+$N$5*C20) -> 0.076603926 | H20: =IF(D20="","",$N$14+$N$15*C20+$N$16*D20) -> -0.14043162 | I20: =IF(D20="","",B20-H20) -> 0.080431622 | J20: =IF(D20="","",B20-$N$16*D20) -> -0.061740755 | M20: lag-1 autocorrelation of residuals | N20: =CORREL($I$9:$I$822,$I$10:$I$823) -> 0.54654178
A21: =Analysis!A21 -> 10/1959 | B21: =Analysis!E21 -> -0.07 | C21: =Analysis!F21 -> 0.16225608 | D21: =IF(F18="","",F18) -> -0.19 | E21: =Solar!D21 -> 1361.6 | F21: 0.11 | G21: =B21-($N$4+$N$5*C21) -> 0.073017793 | H21: =IF(D21="","",$N$14+$N$15*C21+$N$16*D21) -> -0.16515445 | I21: =IF(D21="","",B21-H21) -> 0.095154451 | J21: =IF(D21="","",B21-$N$16*D21) -> -0.053462824 | M21: R², ENSO-adjusted anomaly vs log2(CO2) | N21: =RSQ($J$9:$J$823,$C$9:$C$823) -> 0.88833339
A22: =Analysis!A22 -> 11/1959 | B22: =Analysis!E22 -> -0.08 | C22: =Analysis!F22 -> 0.16905454 | D22: =IF(F19="","",F19) -> -0.23 | E22: =Solar!D22 -> 1361.37 | F22: 0.23 | G22: =B22-($N$4+$N$5*C22) -> 0.044433715 | H22: =IF(D22="","",$N$14+$N$15*C22+$N$16*D22) -> -0.14996198 | I22: =IF(D22="","",B22-H22) -> 0.069961975 | J22: =IF(D22="","",B22-$N$16*D22) -> -0.059981313 | M22: R² of CO2-only fit on the same months | N22: =RSQ($B$9:$B$823,$C$9:$C$823) -> 0.86058036
A23: =Analysis!A23 -> 12/1959 | B23: =Analysis!E23 -> 0 | C23: =Analysis!F23 -> 0.17257895 | D23: =IF(F20="","",F20) -> -0.04 | E23: =Solar!D23 -> 1361.39 | F23: 0.14 | G23: =B23-($N$4+$N$5*C23) -> 0.11479949 | H23: =IF(D23="","",$N$14+$N$15*C23+$N$16*D23) -> -0.12374397 | I23: =IF(D23="","",B23-H23) -> 0.12374397 | J23: =IF(D23="","",B23-$N$16*D23) -> 0.0034815108 | M23: Three-factor: + d·TSI (months through Dec 2023 only)
A24: =Analysis!A24 -> 1/1960 | B24: =Analysis!E24 -> 0 | C24: =Analysis!F24 -> 0.17645956 | D24: =IF(F21="","",F21) -> 0.11 | E24: =Solar!D24 -> 1361.48 | F24: 0.02 | G24: =B24-($N$4+$N$5*C24) -> 0.10419158 | H24: =IF(D24="","",$N$14+$N$15*C24+$N$16*D24) -> -0.10002906 | I24: =IF(D24="","",B24-H24) -> 0.10002906 | J24: =IF(D24="","",B24-$N$16*D24) -> -0.0095741547 | M24: b: °C per CO2 doubling | N24: =INDEX(LINEST($B$9:$B$791,$C$9:$C$791:$E$9:$E$791),1,3) -> 2.6631276
A25: =Analysis!A25 -> 2/1960 | B25: =Analysis!E25 -> 0.13 | C25: =Analysis!F25 -> 0.17896499 | D25: =IF(F22="","",F22) -> 0.23 | E25: =Solar!D25 -> 1361.54 | F25: 0.03 | G25: =B25-($N$4+$N$5*C25) -> 0.2273428 | H25: =IF(D25="","",$N$14+$N$15*C25+$N$16*D25) -> -0.082702624 | I25: =IF(D25="","",B25-H25) -> 0.21270262 | J25: =IF(D25="","",B25-$N$16*D25) -> 0.10998131 | M25: c: °C per unit ONI | N25: =INDEX(LINEST($B$9:$B$791,$C$9:$C$791:$E$9:$E$791),1,2) -> 0.084315145
A26: =Analysis!A26 -> 3/1960 | B26: =Analysis!E26 -> -0.35 | C26: =Analysis!F26 -> 0.18169323 | D26: =IF(F23="","",F23) -> 0.14 | E26: =Solar!D26 -> 1361.63 | F26: 0.06 | G26: =B26-($N$4+$N$5*C26) -> -0.26011505 | H26: =IF(D26="","",$N$14+$N$15*C26+$N$16*D26) -> -0.083042093 | I26: =IF(D26="","",B26-H26) -> -0.26695791 | J26: =IF(D26="","",B26-$N$16*D26) -> -0.36218529 | M26: d: °C per W/m² TSI | N26: =INDEX(LINEST($B$9:$B$791,$C$9:$C$791:$E$9:$E$791),1,1) -> 0.060734269
A27: =Analysis!A27 -> 4/1960 | B27: =Analysis!E27 -> -0.15 | C27: =Analysis!F27 -> 0.18826527 | D27: =IF(F24="","",F24) -> 0.02 | E27: =Solar!D27 -> 1361.28 | F27: 0.17 | G27: =B27-($N$4+$N$5*C27) -> -0.078080173 | H27: =IF(D27="","",$N$14+$N$15*C27+$N$16*D27) -> -0.075434587 | I27: =IF(D27="","",B27-H27) -> -0.074565413 | J27: =IF(D27="","",B27-$N$16*D27) -> -0.15174076 | M27: R² | N27: =INDEX(LINEST($B$9:$B$791,$C$9:$C$791:$E$9:$E$791,TRUE(),TRUE()),3,1) -> 0.8820907
A28: =Analysis!A28 -> 5/1960 | B28: =Analysis!E28 -> -0.08 | C28: =Analysis!F28 -> 0.19278032 | D28: =IF(F25="","",F25) -> 0.03 | E28: =Solar!D28 -> 1361.33 | F28: 0.04 | G28: =B28-($N$4+$N$5*C28) -> -0.020422404 | H28: =IF(D28="","",$N$14+$N$15*C28+$N$16*D28) -> -0.062162267 | I28: =IF(D28="","",B28-H28) -> -0.017837733 | J28: =IF(D28="","",B28-$N$16*D28) -> -0.082611133 | M28: R² of two-factor on the same months | N28: =INDEX(LINEST($B$9:$B$791,$C$9:$C$791:$D$9:$D$791,TRUE(),TRUE()),3,1) -> 0.8772397
A29: =Analysis!A29 -> 6/1960 | B29: =Analysis!E29 -> -0.04 | C29: =Analysis!F29 -> 0.1907503 | D29: =IF(F26="","",F26) -> 0.06 | E29: =Solar!D29 -> 1361.56 | F29: 0 | G29: =B29-($N$4+$N$5*C29) -> 0.02512682 | H29: =IF(D29="","",$N$14+$N$15*C29+$N$16*D29) -> -0.065127206 | I29: =IF(D29="","",B29-H29) -> 0.025127206 | J29: =IF(D29="","",B29-$N$16*D29) -> -0.045222266
A30: =Analysis!A30 -> 7/1960 | B30: =Analysis!E30 -> -0.04 | C30: =Analysis!F30 -> 0.18441633 | D30: =IF(F27="","",F27) -> 0.17 | E30: =Solar!D30 -> 1361.34 | F30: 0.01 | G30: =B30-($N$4+$N$5*C30) -> 0.042441179 | H30: =IF(D30="","",$N$14+$N$15*C30+$N$16*D30) -> -0.072951175 | I30: =IF(D30="","",B30-H30) -> 0.032951175 | J30: =IF(D30="","",B30-$N$16*D30) -> -0.054796421 | M30: Recent residual check
A31: =Analysis!A31 -> 8/1960 | B31: =Analysis!E31 -> 0.02 | C31: =Analysis!F31 -> 0.17404111 | D31: =IF(F28="","",F28) -> 0.04 | E31: =Solar!D31 -> 1361.38 | F31: 0.15 | G31: =B31-($N$4+$N$5*C31) -> 0.13080258 | H31: =IF(D31="","",$N$14+$N$15*C31+$N$16*D31) -> -0.11276469 | I31: =IF(D31="","",B31-H31) -> 0.13276469 | J31: =IF(D31="","",B31-$N$16*D31) -> 0.016518489 | M31: mean residual after CO2+ENSO, 2023-2025 (°C) | N31: =AVERAGEIFS($I$2:$I$823,Analysis!$B$2:$B$823,">=2023",Analysis!$B$2:$B$823,"<2026") -> 0.13825717
A32: =Analysis!A32 -> 9/1960 | B32: =Analysis!E32 -> 0.07 | C32: =Analysis!F32 -> 0.1661186 | D32: =IF(F29="","",F29) -> 0 | E32: =Solar!D32 -> 1361.59 | F32: 0.19 | G32: =B32-($N$4+$N$5*C32) -> 0.20245933 | H32: =IF(D32="","",$N$14+$N$15*C32+$N$16*D32) -> -0.13800773 | I32: =IF(D32="","",B32-H32) -> 0.20800773 | J32: =IF(D32="","",B32-$N$16*D32) -> 0.07 | M32: mean residual, 1959-2022 (°C) | N32: =AVERAGEIFS($I$2:$I$823,Analysis!$B$2:$B$823,">=1959",Analysis!$B$2:$B$823,"<2023") -> -0.008359683
A33: =Analysis!A33 -> 10/1960 | B33: =Analysis!E33 -> 0.06 | C33: =Analysis!F33 -> 0.16455644 | D33: =IF(F30="","",F30) -> 0.01 | E33: =Solar!D33 -> 1361.44 | F33: 0.08 | G33: =B33-($N$4+$N$5*C33) -> 0.19672959 | H33: =IF(D33="","",$N$14+$N$15*C33+$N$16*D33) -> -0.14142827 | I33: =IF(D33="","",B33-H33) -> 0.20142827 | J33: =IF(D33="","",B33-$N$16*D33) -> 0.059129622
A34: =Analysis!A34 -> 11/1960 | B34: =Analysis!E34 -> -0.11 | C34: =Analysis!F34 -> 0.169925 | D34: =IF(F31="","",F31) -> 0.15 | E34: =Solar!D34 -> 1361.23 | F34: -0.07 | G34: =B34-($N$4+$N$5*C34) -> 0.012054251 | H34: =IF(D34="","",$N$14+$N$15*C34+$N$16*D34) -> -0.11449665 | I34: =IF(D34="","",B34-H34) -> 0.0044966477 | J34: =IF(D34="","",B34-$N$16*D34) -> -0.12305567 | M34: How to read this sheet
A35: =Analysis!A35 -> 12/1960 | B35: =Analysis!E35 -> 0.19 | C35: =Analysis!F35 -> 0.17536491 | D35: =IF(F32="","",F32) -> 0.19 | E35: =Solar!D35 -> 1361.34 | F35: -0.07 | G35: =B35-($N$4+$N$5*C35) -> 0.29718386 | H35: =IF(D35="","",$N$14+$N$15*C35+$N$16*D35) -> -0.096072807 | I35: =IF(D35="","",B35-H35) -> 0.28607281 | J35: =IF(D35="","",B35-$N$16*D35) -> 0.17346282 | M35: 1. ENSO is the dominant short-term noise. Adding lagged ONI raises monthly R² from 0.86 to 0.89 and cuts residual scatter by ~12%; the coefficient (~0.09 °C per unit ONI) matches the published ~0.1 °C per °C of Niño 3.4.
A36: =Analysis!A36 -> 1/1961 | B36: =Analysis!E36 -> 0.07 | C36: =Analysis!F36 -> 0.17855531 | D36: =IF(F33="","",F33) -> 0.08 | E36: =Solar!D36 -> 1361.24 | F36: 0 | G36: =B36-($N$4+$N$5*C36) -> 0.1684627 | H36: =IF(D36="","",$N$14+$N$15*C36+$N$16*D36) -> -0.096883603 | I36: =IF(D36="","",B36-H36) -> 0.1668836 | J36: =IF(D36="","",B36-$N$16*D36) -> 0.063036978 | M36: 2. The lag test peaks at 3 months, the known delay for tropical Pacific heat to spread into the global mean. Obtaining that value from the data is consistent with the known physics, though it does not by itself validate the model.
A37: =Analysis!A37 -> 2/1961 | B37: =Analysis!E37 -> 0.19 | C37: =Analysis!F37 -> 0.18223826 | D37: =IF(F34="","",F34) -> -0.07 | E37: =Solar!D37 -> 1361.13 | F37: 0.03 | G37: =B37-($N$4+$N$5*C37) -> 0.27839507 | H37: =IF(D37="","",$N$14+$N$15*C37+$N$16*D37) -> -0.099822938 | I37: =IF(D37="","",B37-H37) -> 0.28982294 | J37: =IF(D37="","",B37-$N$16*D37) -> 0.19609264 | M37: 3. The CO2 coefficient barely moves (2.73 to 2.75 °C per doubling). ONI is detrended by construction (centred 30-year base periods), so it is close to orthogonal to the CO2 trend and absorbs almost none of it. Note that this is a property of the index convention, not a finding: an ENSO index built without re-centred bases, such as RONI, does carry a trend and does take some of the signal (Open Items section A).
A38: =Analysis!A38 -> 3/1961 | B38: =Analysis!E38 -> 0.09 | C38: =Analysis!F38 -> 0.18604772 | D38: =IF(F35="","",F35) -> -0.07 | E38: =Solar!D38 -> 1361.04 | F38: 0.01 | G38: =B38-($N$4+$N$5*C38) -> 0.16798165 | H38: =IF(D38="","",$N$14+$N$15*C38+$N$16*D38) -> -0.089359136 | I38: =IF(D38="","",B38-H38) -> 0.17935914 | J38: =IF(D38="","",B38-$N$16*D38) -> 0.096092644 | M38: 4. What is still unexplained: the largest negative residuals are Jul-Sep 1992 and Apr 1964 (Pinatubo and Agung eruptions), so volcanic aerosols are the next control. The 2023-2025 residual is positive (~+0.14 °C): the recent warmth exceeds what CO2 + El Niño predict, which is an open question in the literature (aerosol reductions from shipping-fuel rules, solar cycle 25 maximum, and possibly cloud feedback are candidates).
A39: =Analysis!A39 -> 4/1961 | B39: =Analysis!E39 -> 0.13 | C39: =Analysis!F39 -> 0.19029879 | D39: =IF(F36="","",F36) -> 0 | E39: =Solar!D39 -> 1360.93 | F39: 0.05 | G39: =B39-($N$4+$N$5*C39) -> 0.19636104 | H39: =IF(D39="","",$N$14+$N$15*C39+$N$16*D39) -> -0.071589665 | I39: =IF(D39="","",B39-H39) -> 0.20158966 | J39: =IF(D39="","",B39-$N$16*D39) -> 0.13 | M39: 5. Residuals remain autocorrelated (lag-1 ~0.55), so these are still descriptive fits, not estimates of equilibrium climate sensitivity.
A40: =Analysis!A40 -> 5/1961 | B40: =Analysis!E40 -> 0.12 | C40: =Analysis!F40 -> 0.1952576 | D40: =IF(F37="","",F37) -> 0.03 | E40: =Solar!D40 -> 1361.01 | F40: 0.22 | G40: =B40-($N$4+$N$5*C40) -> 0.1728058 | H40: =IF(D40="","",$N$14+$N$15*C40+$N$16*D40) -> -0.055357708 | I40: =IF(D40="","",B40-H40) -> 0.17535771 | J40: =IF(D40="","",B40-$N$16*D40) -> 0.11738887
A41: =Analysis!A41 -> 6/1961 | B41: =Analysis!E41 -> 0.11 | C41: =Analysis!F41 -> 0.19160777 | D41: =IF(F38="","",F38) -> 0.01 | E41: =Solar!D41 -> 1360.82 | F41: 0.22 | G41: =B41-($N$4+$N$5*C41) -> 0.17278286 | H41: =IF(D41="","",$N$14+$N$15*C41+$N$16*D41) -> -0.067123796 | I41: =IF(D41="","",B41-H41) -> 0.1771238 | J41: =IF(D41="","",B41-$N$16*D41) -> 0.10912962
A42: =Analysis!A42 -> 7/1961 | B42: =Analysis!E42 -> 0.01 | C42: =Analysis!F42 -> 0.1861383 | D42: =IF(F39="","",F39) -> 0.05 | E42: =Solar!D42 -> 1360.94 | F42: 0.08 | G42: =B42-($N$4+$N$5*C42) -> 0.087734046 | H42: =IF(D42="","",$N$14+$N$15*C42+$N$16*D42) -> -0.078665801 | I42: =IF(D42="","",B42-H42) -> 0.088665801 | J42: =IF(D42="","",B42-$N$16*D42) -> 0.0056481115
A43: =Analysis!A43 -> 8/1961 | B43: =Analysis!E43 -> 0.01 | C43: =Analysis!F43 -> 0.17809997 | D43: =IF(F40="","",F40) -> 0.22 | E43: =Solar!D43 -> 1361.23 | F43: -0.2 | G43: =B43-($N$4+$N$5*C43) -> 0.1097074 | H43: =IF(D43="","",$N$14+$N$15*C43+$N$16*D43) -> -0.085949037 | I43: =IF(D43="","",B43-H43) -> 0.095949037 | J43: =IF(D43="","",B43-$N$16*D43) -> -0.0091483094
A44: =Analysis!A44 -> 9/1961 | B44: =Analysis!E44 -> 0.08 | C44: =Analysis!F44 -> 0.1698792 | D44: =IF(F41="","",F41) -> 0.22 | E44: =Solar!D44 -> 1360.78 | F44: -0.32 | G44: =B44-($N$4+$N$5*C44) -> 0.20217945 | H44: =IF(D44="","",$N$14+$N$15*C44+$N$16*D44) -> -0.10852981 | I44: =IF(D44="","",B44-H44) -> 0.18852981 | J44: =IF(D44="","",B44-$N$16*D44) -> 0.060851691
A45: =Analysis!A45 -> 10/1961 | B45: =Analysis!E45 -> 0 | C45: =Analysis!F45 -> 0.1713441 | D45: =IF(F42="","",F42) -> 0.08 | E45: =Solar!D45 -> 1361.02 | F45: -0.22 | G45: =B45-($N$4+$N$5*C45) -> 0.11817505 | H45: =IF(D45="","",$N$14+$N$15*C45+$N$16*D45) -> -0.11669132 | I45: =IF(D45="","",B45-H45) -> 0.11669132 | J45: =IF(D45="","",B45-$N$16*D45) -> -0.0069630216
A46: =Analysis!A46 -> 11/1961 | B46: =Analysis!E46 -> 0.03 | C46: =Analysis!F46 -> 0.17495421 | D46: =IF(F43="","",F43) -> -0.2 | E46: =Solar!D46 -> 1360.89 | F46: -0.11 | G46: =B46-($N$4+$N$5*C46) -> 0.13830656 | H46: =IF(D46="","",$N$14+$N$15*C46+$N$16*D46) -> -0.13114566 | I46: =IF(D46="","",B46-H46) -> 0.16114566 | J46: =IF(D46="","",B46-$N$16*D46) -> 0.047407554
A47: =Analysis!A47 -> 12/1961 | B47: =Analysis!E47 -> -0.16 | C47: =Analysis!F47 -> 0.17910152 | D47: =IF(F44="","",F44) -> -0.32 | E47: =Solar!D47 -> 1360.91 | F47: -0.05 | G47: =B47-($N$4+$N$5*C47) -> -0.063030426 | H47: =IF(D47="","",$N$14+$N$15*C47+$N$16*D47) -> -0.13019836 | I47: =IF(D47="","",B47-H47) -> -0.029801635 | J47: =IF(D47="","",B47-$N$16*D47) -> -0.13214791
A48: =Analysis!A48 -> 1/1962 | B48: =Analysis!E48 -> 0.05 | C48: =Analysis!F48 -> 0.18332771 | D48: =IF(F45="","",F45) -> -0.22 | E48: =Solar!D48 -> 1360.76 | F48: -0.16 | G48: =B48-($N$4+$N$5*C48) -> 0.135417 | H48: =IF(D48="","",$N$14+$N$15*C48+$N$16*D48) -> -0.10988613 | I48: =IF(D48="","",B48-H48) -> 0.15988613 | J48: =IF(D48="","",B48-$N$16*D48) -> 0.069148309
A49: =Analysis!A49 -> 2/1962 | B49: =Analysis!E49 -> 0.15 | C49: =Analysis!F49 -> 0.18609301 | D49: =IF(F46="","",F46) -> -0.11 | E49: =Solar!D49 -> 1360.67 | F49: -0.17 | G49: =B49-($N$4+$N$5*C49) -> 0.22785785 | H49: =IF(D49="","",$N$14+$N$15*C49+$N$16*D49) -> -0.092716244 | I49: =IF(D49="","",B49-H49) -> 0.24271624 | J49: =IF(D49="","",B49-$N$16*D49) -> 0.15957415
A50: =Analysis!A50 -> 3/1962 | B50: =Analysis!E50 -> 0.1 | C50: =Analysis!F50 -> 0.19120166 | D50: =IF(F47="","",F47) -> -0.05 | E50: =Solar!D50 -> 1360.96 | F50: -0.15 | G50: =B50-($N$4+$N$5*C50) -> 0.16389298 | H50: =IF(D50="","",$N$14+$N$15*C50+$N$16*D50) -> -0.073461555 | I50: =IF(D50="","",B50-H50) -> 0.17346156 | J50: =IF(D50="","",B50-$N$16*D50) -> 0.10435189
A51: =Analysis!A51 -> 4/1962 | B51: =Analysis!E51 -> 0.05 | C51: =Analysis!F51 -> 0.19521259 | D51: =IF(F48="","",F48) -> -0.16 | E51: =Solar!D51 -> 1360.85 | F51: -0.2 | G51: =B51-($N$4+$N$5*C51) -> 0.10292882 | H51: =IF(D51="","",$N$14+$N$15*C51+$N$16*D51) -> -0.072018499 | I51: =IF(D51="","",B51-H51) -> 0.1220185 | J51: =IF(D51="","",B51-$N$16*D51) -> 0.063926043
... A791: =Analysis!A791 -> 12/2023 | B791: =Analysis!E791 -> 1.36 | C791: =Analysis!F791 -> 0.59133747 | D791: =IF(F788="","",F788) -> 1.5 | E791: =Solar!D791 -> 1361.97 | F791: 1.99 | G791: =B791-($N$4+$N$5*C791) -> 0.33009319 | H791: =IF(D791="","",$N$14+$N$15*C791+$N$16*D791) -> 1.1605385 | I791: =IF(D791="","",B791-H791) -> 0.19946151 | J791: =IF(D791="","",B791-$N$16*D791) -> 1.2294433
A792: =Analysis!A792 -> 1/2024 | B792: =Analysis!E792 -> 1.25 | C792: =Analysis!F792 -> 0.59454855 | D792: =IF(F789="","",F789) -> 1.74 | F792: 1.84 | G792: =B792-($N$4+$N$5*C792) -> 0.21131549 | H792: =IF(D792="","",$N$14+$N$15*C792+$N$16*D792) -> 1.1902477 | I792: =IF(D792="","",B792-H792) -> 0.059752269 | J792: =IF(D792="","",B792-$N$16*D792) -> 1.0985543
A793: =Analysis!A793 -> 2/2024 | B793: =Analysis!E793 -> 1.44 | C793: =Analysis!F793 -> 0.60050765 | D793: =IF(F790="","",F790) -> 1.9 | F793: 1.53 | G793: =B793-($N$4+$N$5*C793) -> 0.38502587 | H793: =IF(D793="","",$N$14+$N$15*C793+$N$16*D793) -> 1.2205422 | I793: =IF(D793="","",B793-H793) -> 0.2194578 | J793: =IF(D793="","",B793-$N$16*D793) -> 1.2746282
A794: =Analysis!A794 -> 3/2024 | B794: =Analysis!E794 -> 1.4 | C794: =Analysis!F794 -> 0.60332538 | D794: =IF(F791="","",F791) -> 1.99 | F794: 1.18 | G794: =B794-($N$4+$N$5*C794) -> 0.3373234 | H794: =IF(D794="","",$N$14+$N$15*C794+$N$16*D794) -> 1.2361153 | I794: =IF(D794="","",B794-H794) -> 0.16388467 | J794: =IF(D794="","",B794-$N$16*D794) -> 1.2267948
A795: =Analysis!A795 -> 4/2024 | B795: =Analysis!E795 -> 1.32 | C795: =Analysis!F795 -> 0.60715274 | D795: =IF(F792="","",F792) -> 1.84 | F795: 0.77 | G795: =B795-($N$4+$N$5*C795) -> 0.24686103 | H795: =IF(D795="","",$N$14+$N$15*C795+$N$16*D795) -> 1.2335727 | I795: =IF(D795="","",B795-H795) -> 0.08642735 | J795: =IF(D795="","",B795-$N$16*D795) -> 1.1598505
A796: =Analysis!A796 -> 5/2024 | B796: =Analysis!E796 -> 1.16 | C796: =Analysis!F796 -> 0.60847134 | D796: =IF(F793="","",F793) -> 1.53 | F796: 0.43 | G796: =B796-($N$4+$N$5*C796) -> 0.083256558 | H796: =IF(D796="","",$N$14+$N$15*C796+$N$16*D796) -> 1.2102129 | I796: =IF(D796="","",B796-H796) -> -0.050212853 | J796: =IF(D796="","",B796-$N$16*D796) -> 1.0268322
A797: =Analysis!A797 -> 6/2024 | B797: =Analysis!E797 -> 1.23 | C797: =Analysis!F797 -> 0.60850513 | D797: =IF(F794="","",F794) -> 1.18 | F797: 0.18 | G797: =B797-($N$4+$N$5*C797) -> 0.15316418 | H797: =IF(D797="","",$N$14+$N$15*C797+$N$16*D797) -> 1.1798425 | I797: =IF(D797="","",B797-H797) -> 0.05015754 | J797: =IF(D797="","",B797-$N$16*D797) -> 1.1272954
A798: =Analysis!A798 -> 7/2024 | B798: =Analysis!E798 -> 1.2 | C798: =Analysis!F798 -> 0.60390182 | D798: =IF(F795="","",F795) -> 0.77 | F798: 0.06 | G798: =B798-($N$4+$N$5*C798) -> 0.13574764 | H798: =IF(D798="","",$N$14+$N$15*C798+$N$16*D798) -> 1.1315126 | I798: =IF(D798="","",B798-H798) -> 0.068487368 | J798: =IF(D798="","",B798-$N$16*D798) -> 1.1329809
A799: =Analysis!A799 -> 8/2024 | B799: =Analysis!E799 -> 1.3 | C799: =Analysis!F799 -> 0.59519673 | D799: =IF(F796="","",F796) -> 0.43 | F799: -0.04 | G799: =B799-($N$4+$N$5*C799) -> 0.25954364 | H799: =IF(D799="","",$N$14+$N$15*C799+$N$16*D799) -> 1.0780087 | I799: =IF(D799="","",B799-H799) -> 0.22199133 | J799: =IF(D799="","",B799-$N$16*D799) -> 1.2625738
A800: =Analysis!A800 -> 9/2024 | B800: =Analysis!E800 -> 1.21 | C800: =Analysis!F800 -> 0.59191873 | D800: =IF(F797="","",F797) -> 0.18 | F800: -0.12 | G800: =B800-($N$4+$N$5*C800) -> 0.17850429 | H800: =IF(D800="","",$N$14+$N$15*C800+$N$16*D800) -> 1.0472452 | I800: =IF(D800="","",B800-H800) -> 0.16275477 | J800: =IF(D800="","",B800-$N$16*D800) -> 1.1943332
A801: =Analysis!A801 -> 10/2024 | B801: =Analysis!E801 -> 1.35 | C801: =Analysis!F801 -> 0.5931147 | D801: =IF(F798="","",F798) -> 0.06 | F801: -0.19 | G801: =B801-($N$4+$N$5*C801) -> 0.31523503 | H801: =IF(D801="","",$N$14+$N$15*C801+$N$16*D801) -> 1.0400858 | I801: =IF(D801="","",B801-H801) -> 0.30991422 | J801: =IF(D801="","",B801-$N$16*D801) -> 1.3447777
A802: =Analysis!A802 -> 11/2024 | B802: =Analysis!E802 -> 1.3 | C802: =Analysis!F802 -> 0.59812696 | D802: =IF(F799="","",F799) -> -0.04 | F802: -0.29 | G802: =B802-($N$4+$N$5*C802) -> 0.25153365 | H802: =IF(D802="","",$N$14+$N$15*C802+$N$16*D802) -> 1.0451497 | I802: =IF(D802="","",B802-H802) -> 0.25485034 | J802: =IF(D802="","",B802-$N$16*D802) -> 1.3034815
A803: =Analysis!A803 -> 12/2024 | B803: =Analysis!E803 -> 1.27 | C803: =Analysis!F803 -> 0.60339321 | D803: =IF(F800="","",F800) -> -0.12 | F803: -0.43 | G803: =B803-($N$4+$N$5*C803) -> 0.20713799 | H803: =IF(D803="","",$N$14+$N$15*C803+$N$16*D803) -> 1.0526519 | I803: =IF(D803="","",B803-H803) -> 0.21734805 | J803: =IF(D803="","",B803-$N$16*D803) -> 1.2804445
... A822: =Analysis!A822 -> 7/2026 | B822: =Analysis!E822 -> 1.25 | C822: =Analysis!F822 -> 0.61598793 | D822: =IF(F819="","",F819) -> 0.46 | F822: 1.8 | G822: =B822-($N$4+$N$5*C822) -> 0.1527094 | H822: =IF(D822="","",$N$14+$N$15*C822+$N$16*D822) -> 1.137729 | I822: =IF(D822="","",B822-H822) -> 0.11227099 | J822: =IF(D822="","",B822-$N$16*D822) -> 1.2099626
A823: =Analysis!A823 -> 8/2026 | B823: =Analysis!E823 -> 1.4 | C823: =Analysis!F823 -> 0.61066632 | D823: =IF(F820="","",F820) -> 0.95 | G823: =B823-($N$4+$N$5*C823) -> 0.31725641 | H823: =IF(D823="","",$N$14+$N$15*C823+$N$16*D823) -> 1.1657601 | I823: =IF(D823="","",B823-H823) -> 0.23423988 | J823: =IF(D823="","",B823-$N$16*D823) -> 1.3173141

Sheet Volcanic
A1: Month/Year | B1: Anomaly (°C) | C1: log2(CO2/280) | D1: ONI lagged 3 mo | E1: Strat. AOD lagged 7 mo | F1: TSI (W/m²) | G1: Strat. AOD (same month) | H1: Volcanic ERF (W/m²) | I1: Fitted: CO2+ENSO+AOD | J1: Residual after CO2+ENSO+AOD | K1: Residual after CO2+ENSO (from ENSO tab) | L1: Decimal year
A2: =Analysis!A2 -> 3/1958 | B2: =Analysis!E2 -> 0.08 | C2: =Analysis!F2 -> 0.17317313 | D2: =ENSO!D2 -> 0 | E2: 0.01006 | F2: =Solar!D2 -> 1361.03 | G2: 0.0064 | H2: 0.1767 | I2: =IF(OR(D2="",E2=""),"",$N$14+$N$15*C2+$N$16*D2+$N$17*E2) -> -0.11010356 | J2: =IF(I2="","",B2-I2) -> 0.19010356 | K2: =ENSO!I2 | L2: =Analysis!B2 -> 1958.2083 | M2: Monthly regressions
A3: =Analysis!A3 -> 4/1958 | B3: =Analysis!E3 -> 0.01 | C3: =Analysis!F3 -> 0.18110255 | D3: =ENSO!D3 -> 0 | E3: 0.00952 | F3: =Solar!D3 -> 1361.85 | G3: 0.00611 | H3: 0.1823 | I3: =IF(OR(D3="",E3=""),"",$N$14+$N$15*C3+$N$16*D3+$N$17*E3) -> -0.087288461 | J3: =IF(I3="","",B3-I3) -> 0.097288461 | K3: =ENSO!I3 | L3: =Analysis!B3 -> 1958.2917 | M3: Lag test: r between CO2+ENSO residual and AOD lagged k months | P3: lag k | Q3: r
A4: =Analysis!A4 -> 5/1958 | B4: =Analysis!E4 -> 0.06 | C4: =Analysis!F4 -> 0.1813752 | D4: =ENSO!D4 -> 0 | E4: 0.00903 | F4: =Solar!D4 -> 1362.07 | G4: 0.00587 | H4: 0.1871 | I4: =IF(OR(D4="",E4=""),"",$N$14+$N$15*C4+$N$16*D4+$N$17*E4) -> -0.085466649 | J4: =IF(I4="","",B4-I4) -> 0.14546665 | K4: =ENSO!I4 | L4: =Analysis!B4 -> 1958.375 | P4: 0 | Q4: =CORREL($K$14:$K$823,OFFSET($G$14:$G$823,-P4,0)) -> -0.19418604
A5: =Analysis!A5 -> 6/1958 | B5: =Analysis!E5 -> -0.09 | C5: =Analysis!F5 -> 0.18028428 | D5: =ENSO!D5 | E5: 0.00843 | F5: =Solar!D5 -> 1362.08 | G5: 0.0057 | H5: 0.1907 | I5: =IF(OR(D5="",E5=""),"",$N$14+$N$15*C5+$N$16*D5+$N$17*E5) | J5: =IF(I5="","",B5-I5) | K5: =ENSO!I5 | L5: =Analysis!B5 -> 1958.4583 | P5: 1 | Q5: =CORREL($K$14:$K$823,OFFSET($G$14:$G$823,-P5,0)) -> -0.21331488
A6: =Analysis!A6 -> 7/1958 | B6: =Analysis!E6 -> 0.05 | C6: =Analysis!F6 -> 0.1739041 | D6: =ENSO!D6 | E6: 0.00785 | F6: =Solar!D6 -> 1361.68 | G6: 0.00556 | H6: 0.1934 | I6: =IF(OR(D6="",E6=""),"",$N$14+$N$15*C6+$N$16*D6+$N$17*E6) | J6: =IF(I6="","",B6-I6) | K6: =ENSO!I6 | L6: =Analysis!B6 -> 1958.5417 | P6: 2 | Q6: =CORREL($K$14:$K$823,OFFSET($G$14:$G$823,-P6,0)) -> -0.23279068
A7: =Analysis!A7 -> 8/1958 | B7: =Analysis!E7 -> -0.05 | C7: =Analysis!F7 -> 0.16960437 | D7: =ENSO!D7 | E7: 0.00733 | F7: =Solar!D7 -> 1361.92 | G7: 0.00547 | H7: 0.1952 | I7: =IF(OR(D7="",E7=""),"",$N$14+$N$15*C7+$N$16*D7+$N$17*E7) | J7: =IF(I7="","",B7-I7) | K7: =ENSO!I7 | L7: =Analysis!B7 -> 1958.625 | P7: 3 | Q7: =CORREL($K$14:$K$823,OFFSET($G$14:$G$823,-P7,0)) -> -0.25141813
A8: =Analysis!A8 -> 9/1958 | B8: =Analysis!E8 -> -0.03 | C8: =Analysis!F8 -> 0.16170345 | D8: =ENSO!D8 | E8: 0.00681 | F8: =Solar!D8 -> 1362.04 | G8: 0.00536 | H8: 0.1973 | I8: =IF(OR(D8="",E8=""),"",$N$14+$N$15*C8+$N$16*D8+$N$17*E8) | J8: =IF(I8="","",B8-I8) | K8: =ENSO!I8 | L8: =Analysis!B8 -> 1958.7083 | P8: 4 | Q8: =CORREL($K$14:$K$823,OFFSET($G$14:$G$823,-P8,0)) -> -0.26718662
A9: =Analysis!A9 -> 10/1958 | B9: =Analysis!E9 -> 0.04 | C9: =Analysis!F9 -> 0.15805999 | D9: =ENSO!D9 -> 0.43 | E9: =IF(G2="","",G2) -> 0.0064 | F9: =Solar!D9 -> 1361.99 | G9: 0.00529 | H9: 0.1988 | I9: =IF(OR(D9="",E9=""),"",$N$14+$N$15*C9+$N$16*D9+$N$17*E9) -> -0.10336839 | J9: =IF(I9="","",B9-I9) -> 0.14336839 | K9: =ENSO!I9 -> 0.16271685 | L9: =Analysis!B9 -> 1958.7917 | P9: 5 | Q9: =CORREL($K$14:$K$823,OFFSET($G$14:$G$823,-P9,0)) -> -0.27951414
A10: =Analysis!A10 -> 11/1958 | B10: =Analysis!E10 -> 0.02 | C10: =Analysis!F10 -> 0.16225608 | D10: =ENSO!D10 -> 0.32 | E10: =IF(G3="","",G3) -> 0.00611 | F10: =Solar!D10 -> 1362.07 | G10: 0.00508 | H10: 0.203 | I10: =IF(OR(D10="",E10=""),"",$N$14+$N$15*C10+$N$16*D10+$N$17*E10) -> -0.1014932 | J10: =IF(I10="","",B10-I10) -> 0.1214932 | K10: =ENSO!I10 -> 0.14076519 | L10: =Analysis!B10 -> 1958.875 | P10: 6 | Q10: =CORREL($K$14:$K$823,OFFSET($G$14:$G$823,-P10,0)) -> -0.29003076
A11: =Analysis!A11 -> 12/1958 | B11: =Analysis!E11 -> 0.01 | C11: =Analysis!F11 -> 0.16841281 | D11: =ENSO!D11 -> 0.28 | E11: =IF(G4="","",G4) -> 0.00587 | F11: =Solar!D11 -> 1361.54 | G11: 0.00485 | H11: 0.2075 | I11: =IF(OR(D11="",E11=""),"",$N$14+$N$15*C11+$N$16*D11+$N$17*E11) -> -0.087884887 | J11: =IF(I11="","",B11-I11) -> 0.097884887 | K11: =ENSO!I11 -> 0.11733541 | L11: =Analysis!B11 -> 1958.9583 | P11: 7 | Q11: =CORREL($K$14:$K$823,OFFSET($G$14:$G$823,-P11,0)) -> -0.29239949
A12: =Analysis!A12 -> 1/1959 | B12: =Analysis!E12 -> 0.08 | C12: =Analysis!F12 -> 0.17257895 | D12: =ENSO!D12 -> 0.3 | E12: =IF(G5="","",G5) -> 0.0057 | F12: =Solar!D12 -> 1361.36 | G12: 0.00466 | H12: 0.2114 | I12: =IF(OR(D12="",E12=""),"",$N$14+$N$15*C12+$N$16*D12+$N$17*E12) -> -0.074292101 | J12: =IF(I12="","",B12-I12) -> 0.1542921 | K12: =ENSO!I12 -> 0.17415113 | L12: =Analysis!B12 -> 1959.0417 | P12: 8 | Q12: =CORREL($K$14:$K$823,OFFSET($G$14:$G$823,-P12,0)) -> -0.28865992
A13: =Analysis!A13 -> 2/1959 | B13: =Analysis!E13 -> 0.07 | C13: =Analysis!F13 -> 0.17673309 | D13: =ENSO!D13 -> 0.36 | E13: =IF(G6="","",G6) -> 0.00556 | F13: =Solar!D13 -> 1361.98 | G13: 0.00444 | H13: 0.2157 | I13: =IF(OR(D13="",E13=""),"",$N$14+$N$15*C13+$N$16*D13+$N$17*E13) -> -0.057086244 | J13: =IF(I13="","",B13-I13) -> 0.12708624 | K13: =ENSO!I13 -> 0.14751829 | L13: =Analysis!B13 -> 1959.125 | M13: Three-factor: anomaly = a + b·log2(CO2) + c·ONI(lag 3) + d·AOD(lag 7) | P13: 9 | Q13: =CORREL($K$14:$K$823,OFFSET($G$14:$G$823,-P13,0)) -> -0.28190371
A14: =Analysis!A14 -> 3/1959 | B14: =Analysis!E14 -> 0.18 | C14: =Analysis!F14 -> 0.17746225 | D14: =ENSO!D14 -> 0.56 | E14: =IF(G7="","",G7) -> 0.00547 | F14: =Solar!D14 -> 1361.39 | G14: 0.0043 | H14: 0.2186 | I14: =IF(OR(D14="",E14=""),"",$N$14+$N$15*C14+$N$16*D14+$N$17*E14) -> -0.036340471 | J14: =IF(I14="","",B14-I14) -> 0.21634047 | K14: =ENSO!I14 -> 0.23810787 | L14: =Analysis!B14 -> 1959.2083 | M14: a | N14: =INDEX(LINEST($B$9:$B$822,$C$9:$C$822:$E$9:$E$822),1,4) -> -0.56028489 | P14: 10 | Q14: =CORREL($K$14:$K$823,OFFSET($G$14:$G$823,-P14,0)) -> -0.27008854
A15: =Analysis!A15 -> 4/1959 | B15: =Analysis!E15 -> 0.16 | C15: =Analysis!F15 -> 0.18232908 | D15: =ENSO!D15 -> 0.6 | E15: =IF(G8="","",G8) -> 0.00536 | F15: =Solar!D15 -> 1361.71 | G15: 0.00426 | H15: 0.2193 | I15: =IF(OR(D15="",E15=""),"",$N$14+$N$15*C15+$N$16*D15+$N$17*E15) -> -0.019112716 | J15: =IF(I15="","",B15-I15) -> 0.17911272 | K15: =ENSO!I15 -> 0.20125817 | L15: =Analysis!B15 -> 1959.2917 | M15: b: °C per CO2 doubling | N15: =INDEX(LINEST($B$9:$B$822,$C$9:$C$822:$E$9:$E$822),1,3) -> 2.7274259 | P15: 11 | Q15: =CORREL($K$14:$K$823,OFFSET($G$14:$G$823,-P15,0)) -> -0.25234455
A16: =Analysis!A16 -> 5/1959 | B16: =Analysis!E16 -> 0.04 | C16: =Analysis!F16 -> 0.184915 | D16: =ENSO!D16 -> 0.64 | E16: =IF(G9="","",G9) -> 0.00529 | F16: =Solar!D16 -> 1361.74 | G16: 0.00425 | H16: 0.2197 | I16: =IF(OR(D16="",E16=""),"",$N$14+$N$15*C16+$N$16*D16+$N$17*E16) -> -0.0081939776 | J16: =IF(I16="","",B16-I16) -> 0.048193978 | K16: =ENSO!I16 -> 0.070673659 | L16: =Analysis!B16 -> 1959.375 | M16: c: °C per unit ONI | N16: =INDEX(LINEST($B$9:$B$822,$C$9:$C$822:$E$9:$E$822),1,2) -> 0.092795016 | P16: 12 | Q16: =CORREL($K$14:$K$823,OFFSET($G$14:$G$823,-P16,0)) -> -0.23280759
A17: =Analysis!A17 -> 6/1959 | B17: =Analysis!E17 -> 0.03 | C17: =Analysis!F17 -> 0.18428029 | D17: =ENSO!D17 -> 0.48 | E17: =IF(G10="","",G10) -> 0.00508 | F17: =Solar!D17 -> 1361.6 | G17: 0.00427 | H17: 0.2193 | I17: =IF(OR(D17="",E17=""),"",$N$14+$N$15*C17+$N$16*D17+$N$17*E17) -> -0.02431023 | J17: =IF(I17="","",B17-I17) -> 0.05431023 | K17: =ENSO!I17 -> 0.07634312 | L17: =Analysis!B17 -> 1959.4583 | M17: d: °C per unit stratospheric AOD | N17: =INDEX(LINEST($B$9:$B$822,$C$9:$C$822:$E$9:$E$822),1,1) -> -2.2003523
A18: =Analysis!A18 -> 7/1959 | B18: =Analysis!E18 -> 0.03 | C18: =Analysis!F18 -> 0.17696099 | D18: =ENSO!D18 -> 0.39 | E18: =IF(G11="","",G11) -> 0.00485 | F18: =Solar!D18 -> 1361.81 | G18: 0.00431 | H18: 0.2185 | I18: =IF(OR(D18="",E18=""),"",$N$14+$N$15*C18+$N$16*D18+$N$17*E18) -> -0.052118555 | J18: =IF(I18="","",B18-I18) -> 0.082118555 | K18: =ENSO!I18 -> 0.10428115 | L18: =Analysis!B18 -> 1959.5417 | M18: R² | N18: =INDEX(LINEST($B$9:$B$822,$C$9:$C$822:$E$9:$E$822,TRUE(),TRUE()),3,1) -> 0.90076359
A19: =Analysis!A19 -> 8/1959 | B19: =Analysis!E19 -> -0.01 | C19: =Analysis!F19 -> 0.16900871 | D19: =ENSO!D19 -> 0.24 | E19: =IF(G12="","",G12) -> 0.00466 | F19: =Solar!D19 -> 1361.19 | G19: 0.00437 | H19: 0.2172 | I19: =IF(OR(D19="",E19=""),"",$N$14+$N$15*C19+$N$16*D19+$N$17*E19) -> -0.08730899 | J19: =IF(I19="","",B19-I19) -> 0.07730899 | K19: =ENSO!I19 -> 0.099180104 | L19: =Analysis!B19 -> 1959.625 | M19: months in fit | N19: =COUNT($E$9:$E$822) -> 814
A20: =Analysis!A20 -> 9/1959 | B20: =Analysis!E20 -> -0.06 | C20: =Analysis!F20 -> 0.16460241 | D20: =ENSO!D20 -> 0.02 | E20: =IF(G13="","",G13) -> 0.00444 | F20: =Solar!D20 -> 1361.64 | G20: 0.00441 | H20: 0.2165 | I20: =IF(OR(D20="",E20=""),"",$N$14+$N$15*C20+$N$16*D20+$N$17*E20) -> -0.11925767 | J20: =IF(I20="","",B20-I20) -> 0.059257673 | K20: =ENSO!I20 -> 0.080431622 | L20: =Analysis!B20 -> 1959.7083 | M20: residual std dev (°C) | N20: =STDEV($J$9:$J$822) -> 0.12208488
A21: =Analysis!A21 -> 10/1959 | B21: =Analysis!E21 -> -0.07 | C21: =Analysis!F21 -> 0.16225608 | D21: =ENSO!D21 -> -0.19 | E21: =IF(G14="","",G14) -> 0.0043 | F21: =Solar!D21 -> 1361.6 | G21: 0.00445 | H21: 0.2155 | I21: =IF(OR(D21="",E21=""),"",$N$14+$N$15*C21+$N$16*D21+$N$17*E21) -> -0.14483603 | J21: =IF(I21="","",B21-I21) -> 0.074836025 | K21: =ENSO!I21 -> 0.095154451 | L21: =Analysis!B21 -> 1959.7917 | M21: lag-1 autocorrelation of residuals | N21: =CORREL($J$9:$J$821,$J$10:$J$822) -> 0.50280224
A22: =Analysis!A22 -> 11/1959 | B22: =Analysis!E22 -> -0.08 | C22: =Analysis!F22 -> 0.16905454 | D22: =ENSO!D22 -> -0.23 | E22: =IF(G15="","",G15) -> 0.00426 | F22: =Solar!D22 -> 1361.37 | G22: 0.00435 | H22: 0.2175 | I22: =IF(OR(D22="",E22=""),"",$N$14+$N$15*C22+$N$16*D22+$N$17*E22) -> -0.12991751 | J22: =IF(I22="","",B22-I22) -> 0.049917513 | K22: =ENSO!I22 -> 0.069961975 | L22: =Analysis!B22 -> 1959.875 | M22: R² of CO2+ENSO on the same months | N22: =INDEX(LINEST($B$9:$B$822,$C$9:$C$822:$D$9:$D$822,TRUE(),TRUE()),3,1) -> 0.89120225
A23: =Analysis!A23 -> 12/1959 | B23: =Analysis!E23 -> 0 | C23: =Analysis!F23 -> 0.17257895 | D23: =ENSO!D23 -> -0.04 | E23: =IF(G16="","",G16) -> 0.00425 | F23: =Solar!D23 -> 1361.39 | G23: 0.00422 | H23: 0.2202 | I23: =IF(OR(D23="",E23=""),"",$N$14+$N$15*C23+$N$16*D23+$N$17*E23) -> -0.1026519 | J23: =IF(I23="","",B23-I23) -> 0.1026519 | K23: =ENSO!I23 -> 0.12374397 | L23: =Analysis!B23 -> 1959.9583
A24: =Analysis!A24 -> 1/1960 | B24: =Analysis!E24 -> 0 | C24: =Analysis!F24 -> 0.17645956 | D24: =ENSO!D24 -> 0.11 | E24: =IF(G17="","",G17) -> 0.00427 | F24: =Solar!D24 -> 1361.48 | G24: 0.00411 | H24: 0.2224 | I24: =IF(OR(D24="",E24=""),"",$N$14+$N$15*C24+$N$16*D24+$N$17*E24) -> -0.07819258 | J24: =IF(I24="","",B24-I24) -> 0.07819258 | K24: =ENSO!I24 -> 0.10002906 | L24: =Analysis!B24 -> 1960.0417 | M24: Four-factor: + e·TSI (months through Dec 2023)
A25: =Analysis!A25 -> 2/1960 | B25: =Analysis!E25 -> 0.13 | C25: =Analysis!F25 -> 0.17896499 | D25: =ENSO!D25 -> 0.23 | E25: =IF(G18="","",G18) -> 0.00431 | F25: =Solar!D25 -> 1361.54 | G25: 0.00397 | H25: 0.2253 | I25: =IF(OR(D25="",E25=""),"",$N$14+$N$15*C25+$N$16*D25+$N$17*E25) -> -0.060311815 | J25: =IF(I25="","",B25-I25) -> 0.19031182 | K25: =ENSO!I25 -> 0.21270262 | L25: =Analysis!B25 -> 1960.125 | M25: b: °C per CO2 doubling | N25: =INDEX(LINEST($B$9:$B$791,$C$9:$C$791:$F$9:$F$791),1,4) -> 2.6436323
A26: =Analysis!A26 -> 3/1960 | B26: =Analysis!E26 -> -0.35 | C26: =Analysis!F26 -> 0.18169323 | D26: =ENSO!D26 -> 0.14 | E26: =IF(G19="","",G19) -> 0.00437 | F26: =Solar!D26 -> 1361.63 | G26: 0.00389 | H26: 0.2269 | I26: =IF(OR(D26="",E26=""),"",$N$14+$N$15*C26+$N$16*D26+$N$17*E26) -> -0.061354304 | J26: =IF(I26="","",B26-I26) -> -0.2886457 | K26: =ENSO!I26 -> -0.26695791 | L26: =Analysis!B26 -> 1960.2083 | M26: c: °C per unit ONI | N26: =INDEX(LINEST($B$9:$B$791,$C$9:$C$791:$F$9:$F$791),1,3) -> 0.090695761
A27: =Analysis!A27 -> 4/1960 | B27: =Analysis!E27 -> -0.15 | C27: =Analysis!F27 -> 0.18826527 | D27: =ENSO!D27 -> 0.02 | E27: =IF(G20="","",G20) -> 0.00441 | F27: =Solar!D27 -> 1361.28 | G27: 0.00391 | H27: 0.2265 | I27: =IF(OR(D27="",E27=""),"",$N$14+$N$15*C27+$N$16*D27+$N$17*E27) -> -0.054652983 | J27: =IF(I27="","",B27-I27) -> -0.095347017 | K27: =ENSO!I27 -> -0.074565413 | L27: =Analysis!B27 -> 1960.2917 | M27: d: °C per unit AOD | N27: =INDEX(LINEST($B$9:$B$791,$C$9:$C$791:$F$9:$F$791),1,2) -> -2.1585874
A28: =Analysis!A28 -> 5/1960 | B28: =Analysis!E28 -> -0.08 | C28: =Analysis!F28 -> 0.19278032 | D28: =ENSO!D28 -> 0.03 | E28: =IF(G21="","",G21) -> 0.00445 | F28: =Solar!D28 -> 1361.33 | G28: 0.00394 | H28: 0.2258 | I28: =IF(OR(D28="",E28=""),"",$N$14+$N$15*C28+$N$16*D28+$N$17*E28) -> -0.041498563 | J28: =IF(I28="","",B28-I28) -> -0.038501437 | K28: =ENSO!I28 -> -0.017837733 | L28: =Analysis!B28 -> 1960.375 | M28: e: °C per W/m² TSI | N28: =INDEX(LINEST($B$9:$B$791,$C$9:$C$791:$F$9:$F$791),1,1) -> 0.052957801
A29: =Analysis!A29 -> 6/1960 | B29: =Analysis!E29 -> -0.04 | C29: =Analysis!F29 -> 0.1907503 | D29: =ENSO!D29 -> 0.06 | E29: =IF(G22="","",G22) -> 0.00435 | F29: =Solar!D29 -> 1361.56 | G29: 0.004 | H29: 0.2246 | I29: =IF(OR(D29="",E29=""),"",$N$14+$N$15*C29+$N$16*D29+$N$17*E29) -> -0.044031427 | J29: =IF(I29="","",B29-I29) -> 0.0040314267 | K29: =ENSO!I29 -> 0.025127206 | L29: =Analysis!B29 -> 1960.4583 | M29: R² | N29: =INDEX(LINEST($B$9:$B$791,$C$9:$C$791:$F$9:$F$791,TRUE(),TRUE()),3,1) -> 0.8932405
A30: =Analysis!A30 -> 7/1960 | B30: =Analysis!E30 -> -0.04 | C30: =Analysis!F30 -> 0.18441633 | D30: =ENSO!D30 -> 0.17 | E30: =IF(G23="","",G23) -> 0.00422 | F30: =Solar!D30 -> 1361.34 | G30: 0.00408 | H30: 0.223 | I30: =IF(OR(D30="",E30=""),"",$N$14+$N$15*C30+$N$16*D30+$N$17*E30) -> -0.050813362 | J30: =IF(I30="","",B30-I30) -> 0.010813362 | K30: =ENSO!I30 -> 0.032951175 | L30: =Analysis!B30 -> 1960.5417 | M30: R² of CO2+ENSO+AOD on the same months | N30: =INDEX(LINEST($B$9:$B$791,$C$9:$C$791:$E$9:$E$791,TRUE(),TRUE()),3,1) -> 0.88957834
A31: =Analysis!A31 -> 8/1960 | B31: =Analysis!E31 -> 0.02 | C31: =Analysis!F31 -> 0.17404111 | D31: =ENSO!D31 -> 0.04 | E31: =IF(G24="","",G24) -> 0.00411 | F31: =Solar!D31 -> 1361.38 | G31: 0.00418 | H31: 0.2211 | I31: =IF(OR(D31="",E31=""),"",$N$14+$N$15*C31+$N$16*D31+$N$17*E31) -> -0.090932312 | J31: =IF(I31="","",B31-I31) -> 0.11093231 | K31: =ENSO!I31 -> 0.13276469 | L31: =Analysis!B31 -> 1960.625 | M31: CO2-only slope on those same months (°C per doubling) | N31: =SLOPE($B$9:$B$791,$C$9:$C$791) -> 2.6398984
A32: =Analysis!A32 -> 9/1960 | B32: =Analysis!E32 -> 0.07 | C32: =Analysis!F32 -> 0.1661186 | D32: =ENSO!D32 -> 0 | E32: =IF(G25="","",G25) -> 0.00397 | F32: =Solar!D32 -> 1361.59 | G32: 0.00424 | H32: 0.2198 | I32: =IF(OR(D32="",E32=""),"",$N$14+$N$15*C32+$N$16*D32+$N$17*E32) -> -0.11594413 | J32: =IF(I32="","",B32-I32) -> 0.18594413 | K32: =ENSO!I32 -> 0.20800773 | L32: =Analysis!B32 -> 1960.7083 | M32: Implied cooling at peak AOD (d × peak monthly AOD)
A33: =Analysis!A33 -> 10/1960 | B33: =Analysis!E33 -> 0.06 | C33: =Analysis!F33 -> 0.16455644 | D33: =ENSO!D33 -> 0.01 | E33: =IF(G26="","",G26) -> 0.00389 | F33: =Solar!D33 -> 1361.44 | G33: 0.00431 | H33: 0.2184 | I33: =IF(OR(D33="",E33=""),"",$N$14+$N$15*C33+$N$16*D33+$N$17*E33) -> -0.11910081 | J33: =IF(I33="","",B33-I33) -> 0.17910081 | K33: =ENSO!I33 -> 0.20142827 | L33: =Analysis!B33 -> 1960.7917 | M33: Agung (peak AOD, 1963-64) | N33: =$N$17*MAX($G$66:$G$83) -> -0.17794249
A34: =Analysis!A34 -> 11/1960 | B34: =Analysis!E34 -> -0.11 | C34: =Analysis!F34 -> 0.169925 | D34: =ENSO!D34 -> 0.15 | E34: =IF(G27="","",G27) -> 0.00391 | F34: =Solar!D34 -> 1361.23 | G34: 0.00423 | H34: 0.22 | I34: =IF(OR(D34="",E34=""),"",$N$14+$N$15*C34+$N$16*D34+$N$17*E34) -> -0.09151117 | J34: =IF(I34="","",B34-I34) -> -0.01848883 | K34: =ENSO!I34 -> 0.0044966477 | L34: =Analysis!B34 -> 1960.875 | M34: El Chichón (peak AOD, 1982-83) | N34: =$N$17*MAX($G$292:$G$311) -> -0.12654226
A35: =Analysis!A35 -> 12/1960 | B35: =Analysis!E35 -> 0.19 | C35: =Analysis!F35 -> 0.17536491 | D35: =ENSO!D35 -> 0.19 | E35: =IF(G28="","",G28) -> 0.00394 | F35: =Solar!D35 -> 1361.34 | G35: 0.00412 | H35: 0.2223 | I35: =IF(OR(D35="",E35=""),"",$N$14+$N$15*C35+$N$16*D35+$N$17*E35) -> -0.073028423 | J35: =IF(I35="","",B35-I35) -> 0.26302842 | K35: =ENSO!I35 -> 0.28607281 | L35: =Analysis!B35 -> 1960.9583 | M35: Pinatubo (peak AOD, 1991-92) | N35: =$N$17*MAX($G$400:$G$419) -> -0.25189633
A36: =Analysis!A36 -> 1/1961 | B36: =Analysis!E36 -> 0.07 | C36: =Analysis!F36 -> 0.17855531 | D36: =ENSO!D36 -> 0.08 | E36: =IF(G29="","",G29) -> 0.004 | F36: =Solar!D36 -> 1361.24 | G36: 0.00402 | H36: 0.2242 | I36: =IF(OR(D36="",E36=""),"",$N$14+$N$15*C36+$N$16*D36+$N$17*E36) -> -0.074666335 | J36: =IF(I36="","",B36-I36) -> 0.14466634 | K36: =ENSO!I36 -> 0.1668836 | L36: =Analysis!B36 -> 1961.0417 | M36: Implied transient response, °C per W/m² (d ÷ ERF per unit AOD) | N36: =$N$17/(MIN($H$400:$H$419)/MAX($G$400:$G$419)) -> 0.12689352
A37: =Analysis!A37 -> 2/1961 | B37: =Analysis!E37 -> 0.19 | C37: =Analysis!F37 -> 0.18223826 | D37: =ENSO!D37 -> -0.07 | E37: =IF(G30="","",G30) -> 0.00408 | F37: =Solar!D37 -> 1361.13 | G37: 0.00389 | H37: 0.2268 | I37: =IF(OR(D37="",E37=""),"",$N$14+$N$15*C37+$N$16*D37+$N$17*E37) -> -0.078716626 | J37: =IF(I37="","",B37-I37) -> 0.26871663 | K37: =ENSO!I37 -> 0.28982294 | L37: =Analysis!B37 -> 1961.125
A38: =Analysis!A38 -> 3/1961 | B38: =Analysis!E38 -> 0.09 | C38: =Analysis!F38 -> 0.18604772 | D38: =ENSO!D38 -> -0.07 | E38: =IF(G31="","",G31) -> 0.00418 | F38: =Solar!D38 -> 1361.04 | G38: 0.00382 | H38: 0.2281 | I38: =IF(OR(D38="",E38=""),"",$N$14+$N$15*C38+$N$16*D38+$N$17*E38) -> -0.068546649 | J38: =IF(I38="","",B38-I38) -> 0.15854665 | K38: =ENSO!I38 -> 0.17935914 | L38: =Analysis!B38 -> 1961.2083 | M38: Recent residual check
A39: =Analysis!A39 -> 4/1961 | B39: =Analysis!E39 -> 0.13 | C39: =Analysis!F39 -> 0.19029879 | D39: =ENSO!D39 -> 0 | E39: =IF(G32="","",G32) -> 0.00424 | F39: =Solar!D39 -> 1360.93 | G39: 0.00385 | H39: 0.2276 | I39: =IF(OR(D39="",E39=""),"",$N$14+$N$15*C39+$N$16*D39+$N$17*E39) -> -0.050588536 | J39: =IF(I39="","",B39-I39) -> 0.18058854 | K39: =ENSO!I39 -> 0.20158966 | L39: =Analysis!B39 -> 1961.2917 | M39: mean residual after 3 factors, 2023-2025 (°C) | N39: =AVERAGEIFS($J$2:$J$823,Analysis!$B$2:$B$823,">=2023",Analysis!$B$2:$B$823,"<2026") -> 0.15129879
A40: =Analysis!A40 -> 5/1961 | B40: =Analysis!E40 -> 0.12 | C40: =Analysis!F40 -> 0.1952576 | D40: =ENSO!D40 -> 0.03 | E40: =IF(G33="","",G33) -> 0.00431 | F40: =Solar!D40 -> 1361.01 | G40: 0.00389 | H40: 0.2267 | I40: =IF(OR(D40="",E40=""),"",$N$14+$N$15*C40+$N$16*D40+$N$17*E40) -> -0.03443394 | J40: =IF(I40="","",B40-I40) -> 0.15443394 | K40: =ENSO!I40 -> 0.17535771 | L40: =Analysis!B40 -> 1961.375 | M40: mean residual, 1959-2022 (°C) | N40: =AVERAGEIFS($J$2:$J$823,Analysis!$B$2:$B$823,">=1959",Analysis!$B$2:$B$823,"<2023") -> -0.008654458
A41: =Analysis!A41 -> 6/1961 | B41: =Analysis!E41 -> 0.11 | C41: =Analysis!F41 -> 0.19160777 | D41: =ENSO!D41 -> 0.01 | E41: =IF(G34="","",G34) -> 0.00423 | F41: =Solar!D41 -> 1360.82 | G41: 0.00396 | H41: 0.2253 | I41: =IF(OR(D41="",E41=""),"",$N$14+$N$15*C41+$N$16*D41+$N$17*E41) -> -0.046068446 | J41: =IF(I41="","",B41-I41) -> 0.15606845 | K41: =ENSO!I41 -> 0.1771238 | L41: =Analysis!B41 -> 1961.4583 | M41: mean residual, Jan-Jul 2026 (°C) | N41: =AVERAGEIFS($J$2:$J$823,Analysis!$B$2:$B$823,">=2026") -> 0.11958867
A42: =Analysis!A42 -> 7/1961 | B42: =Analysis!E42 -> 0.01 | C42: =Analysis!F42 -> 0.1861383 | D42: =ENSO!D42 -> 0.05 | E42: =IF(G35="","",G35) -> 0.00412 | F42: =Solar!D42 -> 1360.94 | G42: 0.00405 | H42: 0.2236 | I42: =IF(OR(D42="",E42=""),"",$N$14+$N$15*C42+$N$16*D42+$N$17*E42) -> -0.057032178 | J42: =IF(I42="","",B42-I42) -> 0.067032178 | K42: =ENSO!I42 -> 0.088665801 | L42: =Analysis!B42 -> 1961.5417
A43: =Analysis!A43 -> 8/1961 | B43: =Analysis!E43 -> 0.01 | C43: =Analysis!F43 -> 0.17809997 | D43: =ENSO!D43 -> 0.22 | E43: =IF(G36="","",G36) -> 0.00402 | F43: =Solar!D43 -> 1361.23 | G43: 0.00415 | H43: 0.2216 | I43: =IF(OR(D43="",E43=""),"",$N$14+$N$15*C43+$N$16*D43+$N$17*E43) -> -0.062960943 | J43: =IF(I43="","",B43-I43) -> 0.072960943 | K43: =ENSO!I43 -> 0.095949037 | L43: =Analysis!B43 -> 1961.625 | M43: How to read this sheet
A44: =Analysis!A44 -> 9/1961 | B44: =Analysis!E44 -> 0.08 | C44: =Analysis!F44 -> 0.1698792 | D44: =ENSO!D44 -> 0.22 | E44: =IF(G37="","",G37) -> 0.00389 | F44: =Solar!D44 -> 1360.78 | G44: 0.00422 | H44: 0.2202 | I44: =IF(OR(D44="",E44=""),"",$N$14+$N$15*C44+$N$16*D44+$N$17*E44) -> -0.08509643 | J44: =IF(I44="","",B44-I44) -> 0.16509643 | K44: =ENSO!I44 -> 0.18852981 | L44: =Analysis!B44 -> 1961.7083 | M44: 1. Volcanic aerosols are the third natural control. Adding lagged stratospheric AOD raises monthly R² from 0.89 to 0.90 and the coefficient (~-2.2 °C per unit AOD) implies peak cooling of ~-0.2 °C for Agung and Pinatubo and ~-0.1 °C for El Chichón, consistent with published estimates (Pinatubo ~-0.3 °C with uncertainty). Most of the 1964 and 1992 residuals on the ENSO tab are now accounted for.
A45: =Analysis!A45 -> 10/1961 | B45: =Analysis!E45 -> 0 | C45: =Analysis!F45 -> 0.1713441 | D45: =ENSO!D45 -> 0.08 | E45: =IF(G38="","",G38) -> 0.00382 | F45: =Solar!D45 -> 1361.02 | G45: 0.0043 | H45: 0.2186 | I45: =IF(OR(D45="",E45=""),"",$N$14+$N$15*C45+$N$16*D45+$N$17*E45) -> -0.093938308 | J45: =IF(I45="","",B45-I45) -> 0.093938308 | K45: =ENSO!I45 -> 0.11669132 | L45: =Analysis!B45 -> 1961.7917 | M45: 2. The lag test peaks at 6-8 months: a short forcing pulse takes about half a year to show in the global mean because the ocean mixed layer has to cool first. Same pattern as the 3-month ENSO lag and the solar cycle: the fitted lags are consistent with known physics.
A46: =Analysis!A46 -> 11/1961 | B46: =Analysis!E46 -> 0.03 | C46: =Analysis!F46 -> 0.17495421 | D46: =ENSO!D46 -> -0.2 | E46: =IF(G39="","",G39) -> 0.00385 | F46: =Solar!D46 -> 1360.89 | G46: 0.00422 | H46: 0.2202 | I46: =IF(OR(D46="",E46=""),"",$N$14+$N$15*C46+$N$16*D46+$N$17*E46) -> -0.11014062 | J46: =IF(I46="","",B46-I46) -> 0.14014062 | K46: =ENSO!I46 -> 0.16114566 | L46: =Analysis!B46 -> 1961.875 | M46: 3. The CO2 coefficient barely moves (2.75 to 2.73). The three large eruptions all sit in the first half of the record, so stratospheric AOD does carry a small sample trend and absorbs a little of the CO2 signal, but the effect is 0.02 °C per doubling.
A47: =Analysis!A47 -> 12/1961 | B47: =Analysis!E47 -> -0.16 | C47: =Analysis!F47 -> 0.17910152 | D47: =ENSO!D47 -> -0.32 | E47: =IF(G40="","",G40) -> 0.00389 | F47: =Solar!D47 -> 1360.91 | G47: 0.00411 | H47: 0.2225 | I47: =IF(OR(D47="",E47=""),"",$N$14+$N$15*C47+$N$16*D47+$N$17*E47) -> -0.11005254 | J47: =IF(I47="","",B47-I47) -> -0.049947463 | K47: =ENSO!I47 -> -0.029801635 | L47: =Analysis!B47 -> 1961.9583 | M47: 4. The implied transient response to volcanic forcing (~0.13 °C per W/m²) is much smaller than the ~0.4 °C per W/m² implied by the solar cycle or the ~0.8 needed for equilibrium sensitivity. That is expected: a 1-2 year pulse never gets close to equilibrium, so regressing on AOD says little about long-run sensitivity.
A48: =Analysis!A48 -> 1/1962 | B48: =Analysis!E48 -> 0.05 | C48: =Analysis!F48 -> 0.18332771 | D48: =ENSO!D48 -> -0.22 | E48: =IF(G41="","",G41) -> 0.00396 | F48: =Solar!D48 -> 1360.76 | G48: 0.00401 | H48: 0.2243 | I48: =IF(OR(D48="",E48=""),"",$N$14+$N$15*C48+$N$16*D48+$N$17*E48) -> -0.08940046 | J48: =IF(I48="","",B48-I48) -> 0.13940046 | K48: =ENSO!I48 -> 0.15988613 | L48: =Analysis!B48 -> 1962.0417 | M48: 5. Still unexplained: 2023-2025 residuals remain positive (~+0.15 °C). Volcanoes do not help; Hunga Tonga (2022) added stratospheric water vapour (a small warming) but little sulfate. The remaining candidates are anthropogenic: the 2020 shipping-fuel sulfur cut, declining Chinese SO2, and cloud feedback. Anthropogenic aerosol forcing is the logical next control.
A49: =Analysis!A49 -> 2/1962 | B49: =Analysis!E49 -> 0.15 | C49: =Analysis!F49 -> 0.18609301 | D49: =ENSO!D49 -> -0.11 | E49: =IF(G42="","",G42) -> 0.00405 | F49: =Solar!D49 -> 1360.67 | G49: 0.00389 | H49: 0.2269 | I49: =IF(OR(D49="",E49=""),"",$N$14+$N$15*C49+$N$16*D49+$N$17*E49) -> -0.071848878 | J49: =IF(I49="","",B49-I49) -> 0.22184888 | K49: =ENSO!I49 -> 0.24271624 | L49: =Analysis!B49 -> 1962.125 | M49: 6. Data note: AOD comes from the ClimateIndicator forcing-timeseries repository, which merges CMIP7 (to 2023), GloSSAC satellite data, and OMPS-LP (2025). 2026 is not yet published, so the lagged column covers through Jul 2026 and the Aug 2026 row is excluded.
A50: =Analysis!A50 -> 3/1962 | B50: =Analysis!E50 -> 0.1 | C50: =Analysis!F50 -> 0.19120166 | D50: =ENSO!D50 -> -0.05 | E50: =IF(G43="","",G43) -> 0.00415 | F50: =Solar!D50 -> 1360.96 | G50: 0.00382 | H50: 0.2282 | I50: =IF(OR(D50="",E50=""),"",$N$14+$N$15*C50+$N$16*D50+$N$17*E50) -> -0.052567746 | J50: =IF(I50="","",B50-I50) -> 0.15256775 | K50: =ENSO!I50 -> 0.17346156 | L50: =Analysis!B50 -> 1962.2083
A51: =Analysis!A51 -> 4/1962 | B51: =Analysis!E51 -> 0.05 | C51: =Analysis!F51 -> 0.19521259 | D51: =ENSO!D51 -> -0.16 | E51: =IF(G44="","",G44) -> 0.00422 | F51: =Solar!D51 -> 1360.85 | G51: 0.00385 | H51: 0.2276 | I51: =IF(OR(D51="",E51=""),"",$N$14+$N$15*C51+$N$16*D51+$N$17*E51) -> -0.051989704 | J51: =IF(I51="","",B51-I51) -> 0.1019897 | K51: =ENSO!I51 -> 0.1220185 | L51: =Analysis!B51 -> 1962.2917
A52: =Analysis!A52 -> 5/1962 | B52: =Analysis!E52 -> -0.06 | C52: =Analysis!F52 -> 0.19723635 | D52: =ENSO!D52 -> -0.17 | E52: =IF(G45="","",G45) -> 0.0043 | F52: =Solar!D52 -> 1360.84 | G52: 0.00389 | H52: 0.2267 | I52: =IF(OR(D52="",E52=""),"",$N$14+$N$15*C52+$N$16*D52+$N$17*E52) -> -0.04757402 | J52: =IF(I52="","",B52-I52) -> -0.01242598 | K52: =ENSO!I52 -> 0.0073300137 | L52: =Analysis!B52 -> 1962.375
A53: =Analysis!A53 -> 6/1962 | B53: =Analysis!E53 -> 0.03 | C53: =Analysis!F53 -> 0.1954376 | D53: =ENSO!D53 -> -0.15 | E53: =IF(G46="","",G46) -> 0.00422 | F53: =Solar!D53 -> 1360.93 | G53: 0.00397 | H53: 0.2253 | I53: =IF(OR(D53="",E53=""),"",$N$14+$N$15*C53+$N$16*D53+$N$17*E53) -> -0.050448076 | J53: =IF(I53="","",B53-I53) -> 0.080448076 | K53: =ENSO!I53 -> 0.10053008 | L53: =Analysis!B53 -> 1962.4583
A54: =Analysis!A54 -> 7/1962 | B54: =Analysis!E54 -> 0.02 | C54: =Analysis!F54 -> 0.19088572 | D54: =ENSO!D54 -> -0.2 | E54: =IF(G47="","",G47) -> 0.00411 | F54: =Solar!D54 -> 1360.8 | G54: 0.00405 | H54: 0.2236 | I54: =IF(OR(D54="",E54=""),"",$N$14+$N$15*C54+$N$16*D54+$N$17*E54) -> -0.067260687 | J54: =IF(I54="","",B54-I54) -> 0.087260687 | K54: =ENSO!I54 -> 0.10738504 | L54: =Analysis!B54 -> 1962.5417
A55: =Analysis!A55 -> 8/1962 | B55: =Analysis!E55 -> -0.01 | C55: =Analysis!F55 -> 0.1808753 | D55: =ENSO!D55 -> -0.19 | E55: =IF(G48="","",G48) -> 0.00401 | F55: =Solar!D55 -> 1360.76 | G55: 0.00416 | H55: 0.2215 | I55: =IF(OR(D55="",E55=""),"",$N$14+$N$15*C55+$N$16*D55+$N$17*E55) -> -0.09341538 | J55: =IF(I55="","",B55-I55) -> 0.08341538 | K55: =ENSO!I55 -> 0.10401125 | L55: =Analysis!B55 -> 1962.625
A56: =Analysis!A56 -> 9/1962 | B56: =Analysis!E56 -> 0 | C56: =Analysis!F56 -> 0.17559303 | D56: =ENSO!D56 -> -0.13 | E56: =IF(G49="","",G49) -> 0.00389 | F56: =Solar!D56 -> 1360.64 | G56: 0.00423 | H56: 0.2201 | I56: =IF(OR(D56="",E56=""),"",$N$14+$N$15*C56+$N$16*D56+$N$17*E56) -> -0.10199063 | J56: =IF(I56="","",B56-I56) -> 0.10199063 | K56: =ENSO!I56 -> 0.1232983 | L56: =Analysis!B56 -> 1962.7083
A57: =Analysis!A57 -> 10/1962 | B57: =Analysis!E57 -> 0.01 | C57: =Analysis!F57 -> 0.17184731 | D57: =ENSO!D57 -> 0 | E57: =IF(G50="","",G50) -> 0.00382 | F57: =Solar!D57 -> 1360.8 | G57: 0.0043 | H57: 0.2185 | I57: =IF(OR(D57="",E57=""),"",$N$14+$N$15*C57+$N$16*D57+$N$17*E57) -> -0.099989427 | J57: =IF(I57="","",B57-I57) -> 0.10998943 | K57: =ENSO!I57 -> 0.13227211 | L57: =Analysis!B57 -> 1962.7917
A58: =Analysis!A58 -> 11/1962 | B58: =Analysis!E58 -> 0.06 | C58: =Analysis!F58 -> 0.17764449 | D58: =ENSO!D58 -> -0.1 | E58: =IF(G51="","",G51) -> 0.00385 | F58: =Solar!D58 -> 1360.76 | G58: 0.00423 | H58: 0.2201 | I58: =IF(OR(D58="",E58=""),"",$N$14+$N$15*C58+$N$16*D58+$N$17*E58) -> -0.093523582 | J58: =IF(I58="","",B58-I58) -> 0.15352358 | K58: =ENSO!I58 -> 0.17505224 | L58: =Analysis!B58 -> 1962.875
A59: =Analysis!A59 -> 12/1962 | B59: =Analysis!E59 -> -0.03 | C59: =Analysis!F59 -> 0.18223826 | D59: =ENSO!D59 -> -0.16 | E59: =IF(G52="","",G52) -> 0.00389 | F59: =Solar!D59 -> 1360.8 | G59: 0.00411 | H59: 0.2223 | I59: =IF(OR(D59="",E59=""),"",$N$14+$N$15*C59+$N$16*D59+$N$17*E59) -> -0.08665011 | J59: =IF(I59="","",B59-I59) -> 0.05665011 | K59: =ENSO!I59 -> 0.077656337 | L59: =Analysis!B59 -> 1962.9583
A60: =Analysis!A60 -> 1/1963 | B60: =Analysis!E60 -> -0.03 | C60: =Analysis!F60 -> 0.18695325 | D60: =ENSO!D60 -> -0.25 | E60: =IF(G53="","",G53) -> 0.00397 | F60: =Solar!D60 -> 1360.71 | G60: 0.00402 | H60: 0.2242 | I60: =IF(OR(D60="",E60=""),"",$N$14+$N$15*C60+$N$16*D60+$N$17*E60) -> -0.082317903 | J60: =IF(I60="","",B60-I60) -> 0.052317903 | K60: =ENSO!I60 -> 0.07253862 | L60: =Analysis!B60 -> 1963.0417
A61: =Analysis!A61 -> 2/1963 | B61: =Analysis!E61 -> 0.18 | C61: =Analysis!F61 -> 0.18844614 | D61: =ENSO!D61 -> -0.25 | E61: =IF(G54="","",G54) -> 0.00405 | F61: =Solar!D61 -> 1360.8 | G61: 0.00389 | H61: 0.2267 | I61: =IF(OR(D61="",E61=""),"",$N$14+$N$15*C61+$N$16*D61+$N$17*E61) -> -0.078422191 | J61: =IF(I61="","",B61-I61) -> 0.25842219 | K61: =ENSO!I61 -> 0.27843796 | L61: =Analysis!B61 -> 1963.125
... A791: =Analysis!A791 -> 12/2023 | B791: =Analysis!E791 -> 1.36 | C791: =Analysis!F791 -> 0.59133747 | D791: =ENSO!D791 -> 1.5 | E791: =IF(G784="","",G784) -> 0.0176 | F791: =Solar!D791 -> 1361.97 | G791: 0.01235 | H791: 0.2432 | I791: =IF(OR(D791="",E791=""),"",$N$14+$N$15*C791+$N$16*D791+$N$17*E791) -> 1.1530106 | J791: =IF(I791="","",B791-I791) -> 0.20698944 | K791: =ENSO!I791 -> 0.19946151 | L791: =Analysis!B791 -> 2023.9583
A792: =Analysis!A792 -> 1/2024 | B792: =Analysis!E792 -> 1.25 | C792: =Analysis!F792 -> 0.59454855 | D792: =ENSO!D792 -> 1.74 | E792: =IF(G785="","",G785) -> 0.01622 | G792: 0.01175 | H792: 0.2535 | I792: =IF(OR(D792="",E792=""),"",$N$14+$N$15*C792+$N$16*D792+$N$17*E792) -> 1.1870758 | J792: =IF(I792="","",B792-I792) -> 0.062924177 | K792: =ENSO!I792 -> 0.059752269 | L792: =Analysis!B792 -> 2024.0417
A793: =Analysis!A793 -> 2/2024 | B793: =Analysis!E793 -> 1.44 | C793: =Analysis!F793 -> 0.60050765 | D793: =ENSO!D793 -> 1.9 | E793: =IF(G786="","",G786) -> 0.0148 | G793: 0.01065 | H793: 0.2679 | I793: =IF(OR(D793="",E793=""),"",$N$14+$N$15*C793+$N$16*D793+$N$17*E793) -> 1.2213005 | J793: =IF(I793="","",B793-I793) -> 0.21869948 | K793: =ENSO!I793 -> 0.2194578 | L793: =Analysis!B793 -> 2024.125
A794: =Analysis!A794 -> 3/2024 | B794: =Analysis!E794 -> 1.4 | C794: =Analysis!F794 -> 0.60332538 | D794: =ENSO!D794 -> 1.99 | E794: =IF(G787="","",G787) -> 0.0136 | G794: 0.00996 | H794: 0.2686 | I794: =IF(OR(D794="",E794=""),"",$N$14+$N$15*C794+$N$16*D794+$N$17*E794) -> 1.2399776 | J794: =IF(I794="","",B794-I794) -> 0.16002235 | K794: =ENSO!I794 -> 0.16388467 | L794: =Analysis!B794 -> 2024.2083
A795: =Analysis!A795 -> 4/2024 | B795: =Analysis!E795 -> 1.32 | C795: =Analysis!F795 -> 0.60715274 | D795: =ENSO!D795 -> 1.84 | E795: =IF(G788="","",G788) -> 0.01351 | G795: 0.00968 | H795: 0.2606 | I795: =IF(OR(D795="",E795=""),"",$N$14+$N$15*C795+$N$16*D795+$N$17*E795) -> 1.2366953 | J795: =IF(I795="","",B795-I795) -> 0.083304725 | K795: =ENSO!I795 -> 0.08642735 | L795: =Analysis!B795 -> 2024.2917
A796: =Analysis!A796 -> 5/2024 | B796: =Analysis!E796 -> 1.16 | C796: =Analysis!F796 -> 0.60847134 | D796: =ENSO!D796 -> 1.53 | E796: =IF(G789="","",G789) -> 0.01377 | G796: 0.01523 | H796: 0.1313 | I796: =IF(OR(D796="",E796=""),"",$N$14+$N$15*C796+$N$16*D796+$N$17*E796) -> 1.2109531 | J796: =IF(I796="","",B796-I796) -> -0.050953099 | K796: =ENSO!I796 -> -0.050212853 | L796: =Analysis!B796 -> 2024.375
A797: =Analysis!A797 -> 6/2024 | B797: =Analysis!E797 -> 1.23 | C797: =Analysis!F797 -> 0.60850513 | D797: =ENSO!D797 -> 1.18 | E797: =IF(G790="","",G790) -> 0.01293 | G797: 0.01854 | H797: 0.0747 | I797: =IF(OR(D797="",E797=""),"",$N$14+$N$15*C797+$N$16*D797+$N$17*E797) -> 1.1804153 | J797: =IF(I797="","",B797-I797) -> 0.049584689 | K797: =ENSO!I797 -> 0.05015754 | L797: =Analysis!B797 -> 2024.4583
A798: =Analysis!A798 -> 7/2024 | B798: =Analysis!E798 -> 1.2 | C798: =Analysis!F798 -> 0.60390182 | D798: =ENSO!D798 -> 0.77 | E798: =IF(G791="","",G791) -> 0.01235 | G798: 0.01687 | H798: 0.1036 | I798: =IF(OR(D798="",E798=""),"",$N$14+$N$15*C798+$N$16*D798+$N$17*E798) -> 1.1310904 | J798: =IF(I798="","",B798-I798) -> 0.068909616 | K798: =ENSO!I798 -> 0.068487368 | L798: =Analysis!B798 -> 2024.5417
A799: =Analysis!A799 -> 8/2024 | B799: =Analysis!E799 -> 1.3 | C799: =Analysis!F799 -> 0.59519673 | D799: =ENSO!D799 -> 0.43 | E799: =IF(G792="","",G792) -> 0.01175 | G799: 0.01663 | H799: 0.1006 | I799: =IF(OR(D799="",E799=""),"",$N$14+$N$15*C799+$N$16*D799+$N$17*E799) -> 1.0771178 | J799: =IF(I799="","",B799-I799) -> 0.22288221 | K799: =ENSO!I799 -> 0.22199133 | L799: =Analysis!B799 -> 2024.625
A800: =Analysis!A800 -> 9/2024 | B800: =Analysis!E800 -> 1.21 | C800: =Analysis!F800 -> 0.59191873 | D800: =ENSO!D800 -> 0.18 | E800: =IF(G793="","",G793) -> 0.01065 | G800: 0.01563 | H800: 0.1194 | I800: =IF(OR(D800="",E800=""),"",$N$14+$N$15*C800+$N$16*D800+$N$17*E800) -> 1.0473989 | J800: =IF(I800="","",B800-I800) -> 0.16260108 | K800: =ENSO!I800 -> 0.16275477 | L800: =Analysis!B800 -> 2024.7083
A801: =Analysis!A801 -> 10/2024 | B801: =Analysis!E801 -> 1.35 | C801: =Analysis!F801 -> 0.5931147 | D801: =ENSO!D801 -> 0.06 | E801: =IF(G794="","",G794) -> 0.00996 | G801: 0.01578 | H801: 0.1193 | I801: =IF(OR(D801="",E801=""),"",$N$14+$N$15*C801+$N$16*D801+$N$17*E801) -> 1.0410437 | J801: =IF(I801="","",B801-I801) -> 0.30895633 | K801: =ENSO!I801 -> 0.30991422 | L801: =Analysis!B801 -> 2024.7917
A802: =Analysis!A802 -> 11/2024 | B802: =Analysis!E802 -> 1.3 | C802: =Analysis!F802 -> 0.59812696 | D802: =ENSO!D802 -> -0.04 | E802: =IF(G795="","",G795) -> 0.00968 | G802: 0.01606 | H802: 0.1196 | I802: =IF(OR(D802="",E802=""),"",$N$14+$N$15*C802+$N$16*D802+$N$17*E802) -> 1.0460508 | J802: =IF(I802="","",B802-I802) -> 0.25394915 | K802: =ENSO!I802 -> 0.25485034 | L802: =Analysis!B802 -> 2024.875
A803: =Analysis!A803 -> 12/2024 | B803: =Analysis!E803 -> 1.27 | C803: =Analysis!F803 -> 0.60339321 | D803: =ENSO!D803 -> -0.12 | E803: =IF(G796="","",G796) -> 0.01523 | G803: 0.01601 | H803: 0.177 | I803: =IF(OR(D803="",E803=""),"",$N$14+$N$15*C803+$N$16*D803+$N$17*E803) -> 1.0407786 | J803: =IF(I803="","",B803-I803) -> 0.22922141 | K803: =ENSO!I803 -> 0.21734805 | L803: =Analysis!B803 -> 2024.9583
... A815: =Analysis!A815 -> 12/2025 | B815: =Analysis!E815 -> 1.06 | C815: =Analysis!F815 -> 0.61046385 | D815: =ENSO!D815 -> -0.43 | E815: =IF(G808="","",G808) -> 0.01328 | G815: 0.01102 | H815: 0.1773 | I815: =IF(OR(D815="",E815=""),"",$N$14+$N$15*C815+$N$16*D815+$N$17*E815) -> 1.0355875 | J815: =IF(I815="","",B815-I815) -> 0.024412536 | K815: =ENSO!I815 -> 0.014908157 | L815: =Analysis!B815 -> 2025.9583
A816: =Analysis!A816 -> 1/2026 | B816: =Analysis!E816 -> 1.09 | C816: =Analysis!F816 -> 0.61427234 | D816: =ENSO!D816 -> -0.57 | E816: =IF(G809="","",G809) -> 0.01459 | I816: =IF(OR(D816="",E816=""),"",$N$14+$N$15*C816+$N$16*D816+$N$17*E816) -> 1.0301011 | J816: =IF(I816="","",B816-I816) -> 0.059898906 | K816: =ENSO!I816 -> 0.046632279 | L816: =Analysis!B816 -> 2026.0417
A817: =Analysis!A817 -> 2/2026 | B817: =Analysis!E817 -> 1.25 | C817: =Analysis!F817 -> 0.61672736 | D817: =ENSO!D817 -> -0.61 | E817: =IF(G810="","",G810) -> 0.01387 | I817: =IF(OR(D817="",E817=""),"",$N$14+$N$15*C817+$N$16*D817+$N$17*E817) -> 1.0346694 | J817: =IF(I817="","",B817-I817) -> 0.21533056 | K817: =ENSO!I817 -> 0.20337034 | L817: =Analysis!B817 -> 2026.125
A818: =Analysis!A818 -> 3/2026 | B818: =Analysis!E818 -> 1.32 | C818: =Analysis!F818 -> 0.61941301 | D818: =ENSO!D818 -> -0.6 | E818: =IF(G811="","",G811) -> 0.01291 | I818: =IF(OR(D818="",E818=""),"",$N$14+$N$15*C818+$N$16*D818+$N$17*E818) -> 1.0450346 | J818: =IF(I818="","",B818-I818) -> 0.27496537 | K818: =ENSO!I818 -> 0.26512305 | L818: =Analysis!B818 -> 2026.2083
A819: =Analysis!A819 -> 4/2026 | B819: =Analysis!E819 -> 1.17 | C819: =Analysis!F819 -> 0.62266266 | D819: =ENSO!D819 -> -0.39 | E819: =IF(G812="","",G812) -> 0.01202 | I819: =IF(OR(D819="",E819=""),"",$N$14+$N$15*C819+$N$16*D819+$N$17*E819) -> 1.0753431 | J819: =IF(I819="","",B819-I819) -> 0.094656916 | K819: =ENSO!I819 -> 0.087918976 | L819: =Analysis!B819 -> 2026.2917
A820: =Analysis!A820 -> 5/2026 | B820: =Analysis!E820 -> 1.13 | C820: =Analysis!F820 -> 0.62673949 | D820: =ENSO!D820 -> -0.21 | E820: =IF(G813="","",G813) -> 0.01164 | I820: =IF(OR(D820="",E820=""),"",$N$14+$N$15*C820+$N$16*D820+$N$17*E820) -> 1.1040016 | J820: =IF(I820="","",B820-I820) -> 0.025998432 | K820: =ENSO!I820 -> 0.021053961 | L820: =Analysis!B820 -> 2026.375
A821: =Analysis!A821 -> 6/2026 | B821: =Analysis!E821 -> 1.18 | C821: =Analysis!F821 -> 0.62369967 | D821: =ENSO!D821 -> 0.11 | E821: =IF(G814="","",G814) -> 0.01159 | I821: =IF(OR(D821="",E821=""),"",$N$14+$N$15*C821+$N$16*D821+$N$17*E821) -> 1.1255151 | J821: =IF(I821="","",B821-I821) -> 0.054484895 | K821: =ENSO!I821 -> 0.051551643 | L821: =Analysis!B821 -> 2026.4583
A822: =Analysis!A822 -> 7/2026 | B822: =Analysis!E822 -> 1.25 | C822: =Analysis!F822 -> 0.61598793 | D822: =ENSO!D822 -> 0.46 | E822: =IF(G815="","",G815) -> 0.01102 | I822: =IF(OR(D822="",E822=""),"",$N$14+$N$15*C822+$N$16*D822+$N$17*E822) -> 1.1382144 | J822: =IF(I822="","",B822-I822) -> 0.11178563 | K822: =ENSO!I822 -> 0.11227099 | L822: =Analysis!B822 -> 2026.5417
A823: =Analysis!A823 -> 8/2026 | B823: =Analysis!E823 -> 1.4 | C823: =Analysis!F823 -> 0.61066632 | D823: =ENSO!D823 -> 0.95 | E823: =IF(G816="","",G816) | I823: =IF(OR(D823="",E823=""),"",$N$14+$N$15*C823+$N$16*D823+$N$17*E823) | J823: =IF(I823="","",B823-I823) | K823: =ENSO!I823 -> 0.23423988 | L823: =Analysis!B823 -> 2026.625

Sheet Forcing
A1: Year | B1: Mean anomaly (°C) | C1: Mean log2(CO2/280) | D1: Mean ONI lag 3 | E1: ERF CO2 | F1: ERF CH4 | G1: ERF N2O | H1: ERF other GHG (all non-CO2 GHGs) | I1: ERF aerosols (ARI + ACI) | J1: ERF other anthro (O3, land use, contrails, BC on snow, strat H2O) | K1: ERF GHG total | L1: ERF anthropogenic total | M1: ERF solar | N1: ERF volcanic | O1: ERF total | P1: Fitted: anthro ERF + ENSO | Q1: Residual | AN1: helper: anthro ERF | AO1: helper: ONI | AQ1: helper: GHG + other anthropogenic ERF (K + J) | AR1: helper: aerosol ERF | AS1: helper: ONI | AU1: helper: anthro ERF | AV1: helper: volcanic ERF | AW1: helper: ONI | AY1: helper: fitted, volcanic-ERF variant | AZ1: helper: residual, volcanic-ERF variant | BA1: Anomaly with non-CO2 human forcing and ENSO removed | BB1: Warming from CO2 since 1959 | BC1: from other GHG | BD1: from ozone, land use, other | BE1: from aerosols | BF1: Observed since 1959 | BG1: Observed, ENSO removed
A2: 1959 | B2: =AVERAGEIFS(Analysis!$E$2:$E$823,Analysis!$B$2:$B$823,">="&A2,Analysis!$B$2:$B$823,"<"&(A2+1)) -> 0.030833333 | C2: =AVERAGEIFS(Analysis!$F$2:$F$823,Analysis!$B$2:$B$823,">="&A2,Analysis!$B$2:$B$823,"<"&(A2+1)) -> 0.1743967 | D2: =AVERAGEIFS(ENSO!$D$2:$D$823,Analysis!$B$2:$B$823,">="&A2,Analysis!$B$2:$B$823,"<"&(A2+1)) -> 0.26083333 | E2: 0.6996 | F2: 0.29 | G2: 0.0776 | H2: 0.392 | I2: -0.9122 | J2: 0.1264 | K2: =E2+H2 -> 1.0916 | L2: =K2+I2+J2 -> 0.3058 | M2: 0.064 | N2: 0.2175 | O2: =L2+M2+N2 -> 0.5873 | P2: =$T$13+$T$14*L2+$T$15*D2 -> -0.016962682 | Q2: =B2-P2 -> 0.047796015 | S2: Assumption | AN2: =L2 -> 0.3058 | AO2: =D2 -> 0.26083333 | AQ2: =K2+J2 -> 1.218 | AR2: =I2 -> -0.9122 | AS2: =D2 -> 0.26083333 | AU2: =L2 -> 0.3058 | AV2: =N2 -> 0.2175 | AW2: =D2 -> 0.26083333 | AY2: =INDEX(LINEST($B$2:$B$68,$AU$2:$AW$68),1,4)+$T$37*L2+$T$38*N2+INDEX(LINEST($B$2:$B$68,$AU$2:$AW$68),1,1)*D2 -> 0.013218622 | AZ2: =B2-AY2 -> 0.017614712 | BA2: =B2-$T$14*(L2-E2)-$T$15*D2 -> 0.16542642 | BB2: =$T$14*(E2-$E$2) -> 0 | BC2: =$T$14*(H2-$H$2) -> 0 | BD2: =$T$14*(J2-$J$2) -> 0 | BE2: =$T$14*(I2-$I$2) -> 0 | BF2: =B2-$B$2 -> 0 | BG2: =B2-$B$2-$T$15*(D2-$D$2) -> 0
A3: 1960 | B3: =AVERAGEIFS(Analysis!$E$2:$E$823,Analysis!$B$2:$B$823,">="&A3,Analysis!$B$2:$B$823,"<"&(A3+1)) -> -0.025 | C3: =AVERAGEIFS(Analysis!$F$2:$F$823,Analysis!$B$2:$B$823,">="&A3,Analysis!$B$2:$B$823,"<"&(A3+1)) -> 0.17861134 | D3: =AVERAGEIFS(ENSO!$D$2:$D$823,Analysis!$B$2:$B$823,">="&A3,Analysis!$B$2:$B$823,"<"&(A3+1)) -> 0.095833333 | E3: 0.7137 | F3: 0.2932 | G3: 0.0786 | H3: 0.3988 | I3: -0.9486 | J3: 0.1327 | K3: =E3+H3 -> 1.1125 | L3: =K3+I3+J3 -> 0.2966 | M3: 0.0444 | N3: 0.223 | O3: =L3+M3+N3 -> 0.564 | P3: =$T$13+$T$14*L3+$T$15*D3 -> -0.037425998 | Q3: =B3-P3 -> 0.012425998 | S3: Forcing for a CO2 doubling, F2x (W/m²) | 5-95% half-width | T3: 3.93 | U3: 0.47 | AN3: =L3 -> 0.2966 | AO3: =D3 -> 0.095833333 | AQ3: =K3+J3 -> 1.2452 | AR3: =I3 -> -0.9486 | AS3: =D3 -> 0.095833333 | AU3: =L3 -> 0.2966 | AV3: =N3 -> 0.223 | AW3: =D3 -> 0.095833333 | AY3: =INDEX(LINEST($B$2:$B$68,$AU$2:$AW$68),1,4)+$T$37*L3+$T$38*N3+INDEX(LINEST($B$2:$B$68,$AU$2:$AW$68),1,1)*D3 -> -0.0097246448 | AZ3: =B3-AY3 -> -0.015275355 | BA3: =B3-$T$14*(L3-E3)-$T$15*D3 -> 0.13582086 | BB3: =$T$14*(E3-$E$2) -> 0.0057644551 | BC3: =$T$14*(H3-$H$2) -> 0.0027800209 | BD3: =$T$14*(J3-$J$2) -> 0.0025756076 | BE3: =$T$14*(I3-$I$2) -> -0.014881288 | BF3: =B3-$B$2 -> -0.055833333 | BG3: =B3-$B$2-$T$15*(D3-$D$2) -> -0.039131222
A4: 1961 | B4: =AVERAGEIFS(Analysis!$E$2:$E$823,Analysis!$B$2:$B$823,">="&A4,Analysis!$B$2:$B$823,"<"&(A4+1)) -> 0.056666667 | C4: =AVERAGEIFS(Analysis!$F$2:$F$823,Analysis!$B$2:$B$823,">="&A4,Analysis!$B$2:$B$823,"<"&(A4+1)) -> 0.18196023 | D4: =AVERAGEIFS(ENSO!$D$2:$D$823,Analysis!$B$2:$B$823,">="&A4,Analysis!$B$2:$B$823,"<"&(A4+1)) -> 0.0025 | E4: 0.7253 | F4: 0.2957 | G4: 0.0797 | H4: 0.4054 | I4: -0.9846 | J4: 0.1401 | K4: =E4+H4 -> 1.1307 | L4: =K4+I4+J4 -> 0.2862 | M4: -0.0049 | N4: 0.2238 | O4: =L4+M4+N4 -> 0.5051 | P4: =$T$13+$T$14*L4+$T$15*D4 -> -0.051125453 | Q4: =B4-P4 -> 0.10779212 | S4: Implied F2x from this file: slope of CO2 ERF on log2(CO2/280) | T4: =SLOPE(E2:E68,C2:C68) -> 3.8372772 | AN4: =L4 -> 0.2862 | AO4: =D4 -> 0.0025 | AQ4: =K4+J4 -> 1.2708 | AR4: =I4 -> -0.9846 | AS4: =D4 -> 0.0025 | AU4: =L4 -> 0.2862 | AV4: =N4 -> 0.2238 | AW4: =D4 -> 0.0025 | AY4: =INDEX(LINEST($B$2:$B$68,$AU$2:$AW$68),1,4)+$T$37*L4+$T$38*N4+INDEX(LINEST($B$2:$B$68,$AU$2:$AW$68),1,1)*D4 -> -0.02510005 | AZ4: =B4-AY4 -> 0.081766717 | BA4: =B4-$T$14*(L4-E4)-$T$15*D4 -> 0.23592937 | BB4: =$T$14*(E4-$E$2) -> 0.010506844 | BC4: =$T$14*(H4-$H$2) -> 0.0054782765 | BD4: =$T$14*(J4-$J$2) -> 0.0056009245 | BE4: =$T$14*(I4-$I$2) -> -0.029599046 | BF4: =B4-$B$2 -> 0.025833333 | BG4: =B4-$B$2-$T$15*(D4-$D$2) -> 0.051983104
A5: 1962 | B5: =AVERAGEIFS(Analysis!$E$2:$E$823,Analysis!$B$2:$B$823,">="&A5,Analysis!$B$2:$B$823,"<"&(A5+1)) -> 0.030833333 | C5: =AVERAGEIFS(Analysis!$F$2:$F$823,Analysis!$B$2:$B$823,">="&A5,Analysis!$B$2:$B$823,"<"&(A5+1)) -> 0.18563275 | D5: =AVERAGEIFS(ENSO!$D$2:$D$823,Analysis!$B$2:$B$823,">="&A5,Analysis!$B$2:$B$823,"<"&(A5+1)) -> -0.13666667 | E5: 0.7382 | F5: 0.3019 | G5: 0.0809 | H5: 0.4161 | I5: -0.9916 | J5: 0.1434 | K5: =E5+H5 -> 1.1543 | L5: =K5+I5+J5 -> 0.3061 | M5: -0.0281 | N5: 0.2237 | O5: =L5+M5+N5 -> 0.5017 | P5: =$T$13+$T$14*L5+$T$15*D5 -> -0.057076938 | Q5: =B5-P5 -> 0.087910272 | S5: Annual fits, 1959-2025 (67 years) | AN5: =L5 -> 0.3061 | AO5: =D5 -> -0.13666667 | AQ5: =K5+J5 -> 1.2977 | AR5: =I5 -> -0.9916 | AS5: =D5 -> -0.13666667 | AU5: =L5 -> 0.3061 | AV5: =N5 -> 0.2237 | AW5: =D5 -> -0.13666667 | AY5: =INDEX(LINEST($B$2:$B$68,$AU$2:$AW$68),1,4)+$T$37*L5+$T$38*N5+INDEX(LINEST($B$2:$B$68,$AU$2:$AW$68),1,1)*D5 -> -0.033897162 | AZ5: =B5-AY5 -> 0.064730495 | BA5: =B5-$T$14*(L5-E5)-$T$15*D5 -> 0.22132138 | BB5: =$T$14*(E5-$E$2) -> 0.015780707 | BC5: =$T$14*(H5-$H$2) -> 0.0098527211 | BD5: =$T$14*(J5-$J$2) -> 0.0069500523 | BE5: =$T$14*(I5-$I$2) -> -0.032460832 | BF5: =B5-$B$2 -> 1.1830814e-15 | BG5: =B5-$B$2-$T$15*(D5-$D$2) -> 0.040236905
A6: 1963 | B6: =AVERAGEIFS(Analysis!$E$2:$E$823,Analysis!$B$2:$B$823,">="&A6,Analysis!$B$2:$B$823,"<"&(A6+1)) -> 0.054166667 | C6: =AVERAGEIFS(Analysis!$F$2:$F$823,Analysis!$B$2:$B$823,">="&A6,Analysis!$B$2:$B$823,"<"&(A6+1)) -> 0.18806838 | D6: =AVERAGEIFS(ENSO!$D$2:$D$823,Analysis!$B$2:$B$823,">="&A6,Analysis!$B$2:$B$823,"<"&(A6+1)) -> 0.19416667 | E6: 0.7486 | F6: 0.3104 | G6: 0.0822 | H6: 0.4299 | I6: -1.0605 | J6: 0.1613 | K6: =E6+H6 -> 1.1785 | L6: =K6+I6+J6 -> 0.2793 | M6: -0.0356 | N6: -0.6649 | O6: =L6+M6+N6 -> -0.4212 | P6: =$T$13+$T$14*L6+$T$15*D6 -> -0.034544914 | Q6: =B6-P6 -> 0.088711581 | S6: Single-regressor fits | U6: R² | AN6: =L6 -> 0.2793 | AO6: =D6 -> 0.19416667 | AQ6: =K6+J6 -> 1.3398 | AR6: =I6 -> -1.0605 | AS6: =D6 -> 0.19416667 | AU6: =L6 -> 0.2793 | AV6: =N6 -> -0.6649 | AW6: =D6 -> 0.19416667 | AY6: =INDEX(LINEST($B$2:$B$68,$AU$2:$AW$68),1,4)+$T$37*L6+$T$38*N6+INDEX(LINEST($B$2:$B$68,$AU$2:$AW$68),1,1)*D6 -> -0.119867 | AZ6: =B6-AY6 -> 0.17403367 | BA6: =B6-$T$14*(L6-E6)-$T$15*D6 -> 0.22637449 | BB6: =$T$14*(E6-$E$2) -> 0.020032504 | BC6: =$T$14*(H6-$H$2) -> 0.015494528 | BD6: =$T$14*(J6-$J$2) -> 0.014268048 | BE6: =$T$14*(I6-$I$2) -> -0.060628985 | BF6: =B6-$B$2 -> 0.023333333 | BG6: =B6-$B$2-$T$15*(D6-$D$2) -> 0.030081661
A7: 1964 | B7: =AVERAGEIFS(Analysis!$E$2:$E$823,Analysis!$B$2:$B$823,">="&A7,Analysis!$B$2:$B$823,"<"&(A7+1)) -> -0.19916667 | C7: =AVERAGEIFS(Analysis!$F$2:$F$823,Analysis!$B$2:$B$823,">="&A7,Analysis!$B$2:$B$823,"<"&(A7+1)) -> 0.19090695 | D7: =AVERAGEIFS(ENSO!$D$2:$D$823,Analysis!$B$2:$B$823,">="&A7,Analysis!$B$2:$B$823,"<"&(A7+1)) -> 0.10666667 | E7: 0.7603 | F7: 0.3181 | G7: 0.0835 | H7: 0.4434 | I7: -1.0545 | J7: 0.1603 | K7: =E7+H7 -> 1.2037 | L7: =K7+I7+J7 -> 0.3095 | M7: -0.0382 | N7: -0.5477 | O7: =L7+M7+N7 -> -0.2764 | P7: =$T$13+$T$14*L7+$T$15*D7 -> -0.031055531 | Q7: =B7-P7 -> -0.16811114 | S7: log2(CO2): °C per doubling | T7: =SLOPE($B$2:$B$68,$C$2:$C$68) -> 2.7423885 | U7: =RSQ($B$2:$B$68,$C$2:$C$68) -> 0.93091854 | AN7: =L7 -> 0.3095 | AO7: =D7 -> 0.10666667 | AQ7: =K7+J7 -> 1.364 | AR7: =I7 -> -1.0545 | AS7: =D7 -> 0.10666667 | AU7: =L7 -> 0.3095 | AV7: =N7 -> -0.5477 | AW7: =D7 -> 0.10666667 | AY7: =INDEX(LINEST($B$2:$B$68,$AU$2:$AW$68),1,4)+$T$37*L7+$T$38*N7+INDEX(LINEST($B$2:$B$68,$AU$2:$AW$68),1,1)*D7 -> -0.10306304 | AZ7: =B7-AY7 -> -0.096103627 | BA7: =B7-$T$14*(L7-E7)-$T$15*D7 -> -0.025664958 | BB7: =$T$14*(E7-$E$2) -> 0.024815775 | BC7: =$T$14*(H7-$H$2) -> 0.021013687 | BD7: =$T$14*(J7-$J$2) -> 0.013859222 | BE7: =$T$14*(I7-$I$2) -> -0.058176026 | BF7: =B7-$B$2 -> -0.23 | BG7: =B7-$B$2-$T$15*(D7-$D$2) -> -0.21439449
A8: 1965 | B8: =AVERAGEIFS(Analysis!$E$2:$E$823,Analysis!$B$2:$B$823,">="&A8,Analysis!$B$2:$B$823,"<"&(A8+1)) -> -0.10666667 | C8: =AVERAGEIFS(Analysis!$F$2:$F$823,Analysis!$B$2:$B$823,">="&A8,Analysis!$B$2:$B$823,"<"&(A8+1)) -> 0.19279249 | D8: =AVERAGEIFS(ENSO!$D$2:$D$823,Analysis!$B$2:$B$823,">="&A8,Analysis!$B$2:$B$823,"<"&(A8+1)) -> 0.18333333 | E8: 0.7685 | F8: 0.3244 | G8: 0.0847 | H8: 0.4561 | I8: -1.0792 | J8: 0.1687 | K8: =E8+H8 -> 1.2246 | L8: =K8+I8+J8 -> 0.3141 | M8: -0.0337 | N8: 0.056 | O8: =L8+M8+N8 -> 0.3364 | P8: =$T$13+$T$14*L8+$T$15*D8 -> -0.021414352 | Q8: =B8-P8 -> -0.085252315 | S8: anthropogenic ERF: °C per W/m² | T8: =SLOPE($B$2:$B$68,$L$2:$L$68) -> 0.40864436 | U8: =RSQ($B$2:$B$68,$L$2:$L$68) -> 0.92747072 | AN8: =L8 -> 0.3141 | AO8: =D8 -> 0.18333333 | AQ8: =K8+J8 -> 1.3933 | AR8: =I8 -> -1.0792 | AS8: =D8 -> 0.18333333 | AU8: =L8 -> 0.3141 | AV8: =N8 -> 0.056 | AW8: =D8 -> 0.18333333 | AY8: =INDEX(LINEST($B$2:$B$68,$AU$2:$AW$68),1,4)+$T$37*L8+$T$38*N8+INDEX(LINEST($B$2:$B$68,$AU$2:$AW$68),1,1)*D8 -> -0.013721302 | AZ8: =B8-AY8 -> -0.092945365 | BA8: =B8-$T$14*(L8-E8)-$T$15*D8 -> 0.06054624 | BB8: =$T$14*(E8-$E$2) -> 0.028168153 | BC8: =$T$14*(H8-$H$2) -> 0.026205785 | BD8: =$T$14*(J8-$J$2) -> 0.017293365 | BE8: =$T$14*(I8-$I$2) -> -0.068274043 | BF8: =B8-$B$2 -> -0.1375 | BG8: =B8-$B$2-$T$15*(D8-$D$2) -> -0.12965507
A9: 1966 | B9: =AVERAGEIFS(Analysis!$E$2:$E$823,Analysis!$B$2:$B$823,">="&A9,Analysis!$B$2:$B$823,"<"&(A9+1)) -> -0.0575 | C9: =AVERAGEIFS(Analysis!$F$2:$F$823,Analysis!$B$2:$B$823,">="&A9,Analysis!$B$2:$B$823,"<"&(A9+1)) -> 0.19877222 | D9: =AVERAGEIFS(ENSO!$D$2:$D$823,Analysis!$B$2:$B$823,">="&A9,Analysis!$B$2:$B$823,"<"&(A9+1)) -> 0.7675 | E9: 0.7867 | F9: 0.3295 | G9: 0.0861 | H9: 0.4684 | I9: -1.0942 | J9: 0.1739 | K9: =E9+H9 -> 1.2551 | L9: =K9+I9+J9 -> 0.3348 | M9: -0.0088 | N9: 0.1706 | O9: =L9+M9+N9 -> 0.4966 | P9: =$T$13+$T$14*L9+$T$15*D9 -> 0.046180582 | Q9: =B9-P9 -> -0.10368058 | S9: total ERF (anthro + solar + volcanic): °C per W/m² | T9: =SLOPE($B$2:$B$68,$O$2:$O$68) -> 0.35681815 | U9: =RSQ($B$2:$B$68,$O$2:$O$68) -> 0.86772401 | AN9: =L9 -> 0.3348 | AO9: =D9 -> 0.7675 | AQ9: =K9+J9 -> 1.429 | AR9: =I9 -> -1.0942 | AS9: =D9 -> 0.7675 | AU9: =L9 -> 0.3348 | AV9: =N9 -> 0.1706 | AW9: =D9 -> 0.7675 | AY9: =INDEX(LINEST($B$2:$B$68,$AU$2:$AW$68),1,4)+$T$37*L9+$T$38*N9+INDEX(LINEST($B$2:$B$68,$AU$2:$AW$68),1,1)*D9 -> 0.080084884 | AZ9: =B9-AY9 -> -0.13758488 | BA9: =B9-$T$14*(L9-E9)-$T$15*D9 -> 0.049558618 | BB9: =$T$14*(E9-$E$2) -> 0.035608797 | BC9: =$T$14*(H9-$H$2) -> 0.031234353 | BD9: =$T$14*(J9-$J$2) -> 0.019419264 | BE9: =$T$14*(I9-$I$2) -> -0.074406442 | BF9: =B9-$B$2 -> -0.088333333 | BG9: =B9-$B$2-$T$15*(D9-$D$2) -> -0.13962063
A10: 1967 | B10: =AVERAGEIFS(Analysis!$E$2:$E$823,Analysis!$B$2:$B$823,">="&A10,Analysis!$B$2:$B$823,"<"&(A10+1)) -> -0.024166667 | C10: =AVERAGEIFS(Analysis!$F$2:$F$823,Analysis!$B$2:$B$823,">="&A10,Analysis!$B$2:$B$823,"<"&(A10+1)) -> 0.20241456 | D10: =AVERAGEIFS(ENSO!$D$2:$D$823,Analysis!$B$2:$B$823,">="&A10,Analysis!$B$2:$B$823,"<"&(A10+1)) -> -0.27416667 | E10: 0.7969 | F10: 0.335 | G10: 0.0875 | H10: 0.4817 | I10: -1.1205 | J10: 0.186 | K10: =E10+H10 -> 1.2786 | L10: =K10+I10+J10 -> 0.3441 | M10: 0.0179 | N10: 0.2007 | O10: =L10+M10+N10 -> 0.5627 | P10: =$T$13+$T$14*L10+$T$15*D10 -> -0.055459954 | Q10: =B10-P10 -> 0.031293287 | S10: GHG ERF only: °C per W/m² | T10: =SLOPE($B$2:$B$68,$K$2:$K$68) -> 0.46858948 | U10: =RSQ($B$2:$B$68,$K$2:$K$68) -> 0.90550432 | AN10: =L10 -> 0.3441 | AO10: =D10 -> -0.27416667 | AQ10: =K10+J10 -> 1.4646 | AR10: =I10 -> -1.1205 | AS10: =D10 -> -0.27416667 | AU10: =L10 -> 0.3441 | AV10: =N10 -> 0.2007 | AW10: =D10 -> -0.27416667 | AY10: =INDEX(LINEST($B$2:$B$68,$AU$2:$AW$68),1,4)+$T$37*L10+$T$38*N10+INDEX(LINEST($B$2:$B$68,$AU$2:$AW$68),1,1)*D10 -> -0.038151723 | AZ10: =B10-AY10 -> 0.013985056 | BA10: =B10-$T$14*(L10-E10)-$T$15*D10 -> 0.18870252 | BB10: =$T$14*(E10-$E$2) -> 0.039778829 | BC10: =$T$14*(H10-$H$2) -> 0.036671746 | BD10: =$T$14*(J10-$J$2) -> 0.024366066 | BE10: =$T$14*(I10-$I$2) -> -0.085158582 | BF10: =B10-$B$2 -> -0.055 | BG10: =B10-$B$2-$T$15*(D10-$D$2) -> -0.00084466888
A11: 1968 | B11: =AVERAGEIFS(Analysis!$E$2:$E$823,Analysis!$B$2:$B$823,">="&A11,Analysis!$B$2:$B$823,"<"&(A11+1)) -> -0.0825 | C11: =AVERAGEIFS(Analysis!$F$2:$F$823,Analysis!$B$2:$B$823,">="&A11,Analysis!$B$2:$B$823,"<"&(A11+1)) -> 0.20630941 | D11: =AVERAGEIFS(ENSO!$D$2:$D$823,Analysis!$B$2:$B$823,">="&A11,Analysis!$B$2:$B$823,"<"&(A11+1)) -> -0.20083333 | E11: 0.8124 | F11: 0.3428 | G11: 0.0889 | H11: 0.4982 | I11: -1.1406 | J11: 0.1907 | K11: =E11+H11 -> 1.3106 | L11: =K11+I11+J11 -> 0.3607 | M11: 0.0249 | N11: 0.1035 | O11: =L11+M11+N11 -> 0.4891 | P11: =$T$13+$T$14*L11+$T$15*D11 -> -0.041250271 | Q11: =B11-P11 -> -0.041249729 | AN11: =L11 -> 0.3607 | AO11: =D11 -> -0.20083333 | AQ11: =K11+J11 -> 1.5013 | AR11: =I11 -> -1.1406 | AS11: =D11 -> -0.20083333 | AU11: =L11 -> 0.3607 | AV11: =N11 -> 0.1035 | AW11: =D11 -> -0.20083333 | AY11: =INDEX(LINEST($B$2:$B$68,$AU$2:$AW$68),1,4)+$T$37*L11+$T$38*N11+INDEX(LINEST($B$2:$B$68,$AU$2:$AW$68),1,1)*D11 -> -0.035180212 | AZ11: =B11-AY11 -> -0.047319788 | BA11: =B11-$T$14*(L11-E11)-$T$15*D11 -> 0.12249631 | BB11: =$T$14*(E11-$E$2) -> 0.046115641 | BC11: =$T$14*(H11-$H$2) -> 0.043417385 | BD11: =$T$14*(J11-$J$2) -> 0.026287551 | BE11: =$T$14*(I11-$I$2) -> -0.093375996 | BF11: =B11-$B$2 -> -0.11333333 | BG11: =B11-$B$2-$T$15*(D11-$D$2) -> -0.066601163
A12: 1969 | B12: =AVERAGEIFS(Analysis!$E$2:$E$823,Analysis!$B$2:$B$823,">="&A12,Analysis!$B$2:$B$823,"<"&(A12+1)) -> 0.0525 | C12: =AVERAGEIFS(Analysis!$F$2:$F$823,Analysis!$B$2:$B$823,">="&A12,Analysis!$B$2:$B$823,"<"&(A12+1)) -> 0.2133079 | D12: =AVERAGEIFS(ENSO!$D$2:$D$823,Analysis!$B$2:$B$823,">="&A12,Analysis!$B$2:$B$823,"<"&(A12+1)) -> 0.66666667 | E12: 0.8271 | F12: 0.3507 | G12: 0.0903 | H12: 0.5157 | I12: -1.1591 | J12: 0.1957 | K12: =E12+H12 -> 1.3428 | L12: =K12+I12+J12 -> 0.3794 | M12: 0.0336 | N12: 0.0235 | O12: =L12+M12+N12 -> 0.4365 | P12: =$T$13+$T$14*L12+$T$15*D12 -> 0.054207402 | Q12: =B12-P12 -> -0.0017074024 | S12: Two-factor: anomaly = a + b·anthro ERF + c·ONI | AN12: =L12 -> 0.3794 | AO12: =D12 -> 0.66666667 | AQ12: =K12+J12 -> 1.5385 | AR12: =I12 -> -1.1591 | AS12: =D12 -> 0.66666667 | AU12: =L12 -> 0.3794 | AV12: =N12 -> 0.0235 | AW12: =D12 -> 0.66666667 | AY12: =INDEX(LINEST($B$2:$B$68,$AU$2:$AW$68),1,4)+$T$37*L12+$T$38*N12+INDEX(LINEST($B$2:$B$68,$AU$2:$AW$68),1,1)*D12 -> 0.066847467 | AZ12: =B12-AY12 -> -0.014347467 | BA12: =B12-$T$14*(L12-E12)-$T$15*D12 -> 0.16804839 | BB12: =$T$14*(E12-$E$2) -> 0.052125392 | BC12: =$T$14*(H12-$H$2) -> 0.050571851 | BD12: =$T$14*(J12-$J$2) -> 0.028331684 | BE12: =$T$14*(I12-$I$2) -> -0.10093929 | BF12: =B12-$B$2 -> 0.021666667 | BG12: =B12-$B$2-$T$15*(D12-$D$2) -> -0.019413779
A13: 1970 | B13: =AVERAGEIFS(Analysis!$E$2:$E$823,Analysis!$B$2:$B$823,">="&A13,Analysis!$B$2:$B$823,"<"&(A13+1)) -> 0.0275 | C13: =AVERAGEIFS(Analysis!$F$2:$F$823,Analysis!$B$2:$B$823,">="&A13,Analysis!$B$2:$B$823,"<"&(A13+1)) -> 0.21801538 | D13: =AVERAGEIFS(ENSO!$D$2:$D$823,Analysis!$B$2:$B$823,">="&A13,Analysis!$B$2:$B$823,"<"&(A13+1)) -> 0.11 | E13: 0.8531 | F13: 0.3604 | G13: 0.0917 | H13: 0.5357 | I13: -1.2258 | J13: 0.2112 | K13: =E13+H13 -> 1.3888 | L13: =K13+I13+J13 -> 0.3742 | M13: 0.0326 | N13: 0.1638 | O13: =L13+M13+N13 -> 0.5706 | P13: =$T$13+$T$14*L13+$T$15*D13 -> -0.0042670336 | Q13: =B13-P13 -> 0.031767034 | S13: a | T13: =INDEX(LINEST($B$2:$B$68,$AN$2:$AN$68:$AO$2:$AO$68),1,3) -> -0.16838469 | AN13: =L13 -> 0.3742 | AO13: =D13 -> 0.11 | AQ13: =K13+J13 -> 1.6 | AR13: =I13 -> -1.2258 | AS13: =D13 -> 0.11 | AU13: =L13 -> 0.3742 | AV13: =N13 -> 0.1638 | AW13: =D13 -> 0.11 | AY13: =INDEX(LINEST($B$2:$B$68,$AU$2:$AW$68),1,4)+$T$37*L13+$T$38*N13+INDEX(LINEST($B$2:$B$68,$AU$2:$AW$68),1,1)*D13 -> 0.015649491 | AZ13: =B13-AY13 -> 0.011850509 | BA13: =B13-$T$14*(L13-E13)-$T$15*D13 -> 0.21215232 | BB13: =$T$14*(E13-$E$2) -> 0.062754884 | BC13: =$T$14*(H13-$H$2) -> 0.058748383 | BD13: =$T$14*(J13-$J$2) -> 0.034668496 | BE13: =$T$14*(I13-$I$2) -> -0.12820802 | BF13: =B13-$B$2 -> -0.0033333333 | BG13: =B13-$B$2-$T$15*(D13-$D$2) -> 0.011934758
A14: 1971 | B14: =AVERAGEIFS(Analysis!$E$2:$E$823,Analysis!$B$2:$B$823,">="&A14,Analysis!$B$2:$B$823,"<"&(A14+1)) -> -0.079166667 | C14: =AVERAGEIFS(Analysis!$F$2:$F$823,Analysis!$B$2:$B$823,">="&A14,Analysis!$B$2:$B$823,"<"&(A14+1)) -> 0.22084049 | D14: =AVERAGEIFS(ENSO!$D$2:$D$823,Analysis!$B$2:$B$823,">="&A14,Analysis!$B$2:$B$823,"<"&(A14+1)) -> -0.87583333 | E14: 0.8635 | F14: 0.3693 | G14: 0.0932 | H14: 0.5556 | I14: -1.2357 | J14: 0.222 | K14: =E14+H14 -> 1.4191 | L14: =K14+I14+J14 -> 0.4054 | M14: -0.0047 | N14: 0.2105 | O14: =L14+M14+N14 -> 0.6112 | P14: =$T$13+$T$14*L14+$T$15*D14 -> -0.091302542 | Q14: =B14-P14 -> 0.012135875 | S14: b: °C per W/m² | T14: =INDEX(LINEST($B$2:$B$68,$AN$2:$AN$68:$AO$2:$AO$68),1,2) -> 0.4088266 | AN14: =L14 -> 0.4054 | AO14: =D14 -> -0.87583333 | AQ14: =K14+J14 -> 1.6411 | AR14: =I14 -> -1.2357 | AS14: =D14 -> -0.87583333 | AU14: =L14 -> 0.4054 | AV14: =N14 -> 0.2105 | AW14: =D14 -> -0.87583333 | AY14: =INDEX(LINEST($B$2:$B$68,$AU$2:$AW$68),1,4)+$T$37*L14+$T$38*N14+INDEX(LINEST($B$2:$B$68,$AU$2:$AW$68),1,1)*D14 -> -0.084846046 | AZ14: =B14-AY14 -> 0.0056793798 | BA14: =B14-$T$14*(L14-E14)-$T$15*D14 -> 0.19677296 | BB14: =$T$14*(E14-$E$2) -> 0.06700668 | BC14: =$T$14*(H14-$H$2) -> 0.066884032 | BD14: =$T$14*(J14-$J$2) -> 0.039083823 | BE14: =$T$14*(I14-$I$2) -> -0.13225541 | BF14: =B14-$B$2 -> -0.11 | BG14: =B14-$B$2-$T$15*(D14-$D$2) -> 0.0050589901
A15: 1972 | B15: =AVERAGEIFS(Analysis!$E$2:$E$823,Analysis!$B$2:$B$823,">="&A15,Analysis!$B$2:$B$823,"<"&(A15+1)) -> 0.0091666667 | C15: =AVERAGEIFS(Analysis!$F$2:$F$823,Analysis!$B$2:$B$823,">="&A15,Analysis!$B$2:$B$823,"<"&(A15+1)) -> 0.22586053 | D15: =AVERAGEIFS(ENSO!$D$2:$D$823,Analysis!$B$2:$B$823,">="&A15,Analysis!$B$2:$B$823,"<"&(A15+1)) -> 0.16333333 | E15: 0.8965 | F15: 0.3772 | G15: 0.0946 | H15: 0.5756 | I15: -1.3046 | J15: 0.2435 | K15: =E15+H15 -> 1.4721 | L15: =K15+I15+J15 -> 0.411 | M15: 0.0059 | N15: 0.2199 | O15: =L15+M15+N15 -> 0.6368 | P15: =$T$13+$T$14*L15+$T$15*D15 -> 0.016176448 | Q15: =B15-P15 -> -0.007009781 | S15: c: °C per unit ONI | T15: =INDEX(LINEST($B$2:$B$68,$AN$2:$AN$68:$AO$2:$AO$68),1,1) -> 0.10122492 | AN15: =L15 -> 0.411 | AO15: =D15 -> 0.16333333 | AQ15: =K15+J15 -> 1.7156 | AR15: =I15 -> -1.3046 | AS15: =D15 -> 0.16333333 | AU15: =L15 -> 0.411 | AV15: =N15 -> 0.2199 | AW15: =D15 -> 0.16333333 | AY15: =INDEX(LINEST($B$2:$B$68,$AU$2:$AW$68),1,4)+$T$37*L15+$T$38*N15+INDEX(LINEST($B$2:$B$68,$AU$2:$AW$68),1,1)*D15 -> 0.044222388 | AZ15: =B15-AY15 -> -0.035055722 | BA15: =B15-$T$14*(L15-E15)-$T$15*D15 -> 0.19111858 | BB15: =$T$14*(E15-$E$2) -> 0.080497958 | BC15: =$T$14*(H15-$H$2) -> 0.075060564 | BD15: =$T$14*(J15-$J$2) -> 0.047873595 | BE15: =$T$14*(I15-$I$2) -> -0.16042356 | BF15: =B15-$B$2 -> -0.021666667 | BG15: =B15-$B$2-$T$15*(D15-$D$2) -> -0.011797237
A16: 1973 | B16: =AVERAGEIFS(Analysis!$E$2:$E$823,Analysis!$B$2:$B$823,">="&A16,Analysis!$B$2:$B$823,"<"&(A16+1)) -> 0.16083333 | C16: =AVERAGEIFS(Analysis!$F$2:$F$823,Analysis!$B$2:$B$823,">="&A16,Analysis!$B$2:$B$823,"<"&(A16+1)) -> 0.23562788 | D16: =AVERAGEIFS(ENSO!$D$2:$D$823,Analysis!$B$2:$B$823,">="&A16,Analysis!$B$2:$B$823,"<"&(A16+1)) -> 0.32 | E16: 0.9397 | F16: 0.3831 | G16: 0.0961 | H16: 0.5947 | I16: -1.3083 | J16: 0.2427 | K16: =E16+H16 -> 1.5344 | L16: =K16+I16+J16 -> 0.4688 | M16: -0.023 | N16: 0.2153 | O16: =L16+M16+N16 -> 0.6611 | P16: =$T$13+$T$14*L16+$T$15*D16 -> 0.055665196 | Q16: =B16-P16 -> 0.10516814 | S16: R² | T16: =INDEX(LINEST($B$2:$B$68,$AN$2:$AN$68:$AO$2:$AO$68,TRUE(),TRUE()),3,1) -> 0.95321835 | AN16: =L16 -> 0.4688 | AO16: =D16 -> 0.32 | AQ16: =K16+J16 -> 1.7771 | AR16: =I16 -> -1.3083 | AS16: =D16 -> 0.32 | AU16: =L16 -> 0.4688 | AV16: =N16 -> 0.2153 | AW16: =D16 -> 0.32 | AY16: =INDEX(LINEST($B$2:$B$68,$AU$2:$AW$68),1,4)+$T$37*L16+$T$38*N16+INDEX(LINEST($B$2:$B$68,$AU$2:$AW$68),1,1)*D16 -> 0.085898194 | AZ16: =B16-AY16 -> 0.074935139 | BA16: =B16-$T$14*(L16-E16)-$T$15*D16 -> 0.32095781 | BB16: =$T$14*(E16-$E$2) -> 0.098159268 | BC16: =$T$14*(H16-$H$2) -> 0.082869153 | BD16: =$T$14*(J16-$J$2) -> 0.047546534 | BE16: =$T$14*(I16-$I$2) -> -0.16193622 | BF16: =B16-$B$2 -> 0.13 | BG16: =B16-$B$2-$T$15*(D16-$D$2) -> 0.12401086
A17: 1974 | B17: =AVERAGEIFS(Analysis!$E$2:$E$823,Analysis!$B$2:$B$823,">="&A17,Analysis!$B$2:$B$823,"<"&(A17+1)) -> -0.071666667 | C17: =AVERAGEIFS(Analysis!$F$2:$F$823,Analysis!$B$2:$B$823,">="&A17,Analysis!$B$2:$B$823,"<"&(A17+1)) -> 0.23785982 | D17: =AVERAGEIFS(ENSO!$D$2:$D$823,Analysis!$B$2:$B$823,">="&A17,Analysis!$B$2:$B$823,"<"&(A17+1)) -> -1.1566667 | E17: 0.9538 | F17: 0.3888 | G17: 0.0977 | H17: 0.615 | I17: -1.3004 | J17: 0.2438 | K17: =E17+H17 -> 1.5688 | L17: =K17+I17+J17 -> 0.5122 | M17: -0.0327 | N17: 0.2139 | O17: =L17+M17+N17 -> 0.6934 | P17: =$T$13+$T$14*L17+$T$15*D17 -> -0.076067192 | Q17: =B17-P17 -> 0.0044005251 | S17: b × F2x, °C per doubling (historical regression, not TCR) | T17: =T14*T3 -> 1.6066886 | AN17: =L17 -> 0.5122 | AO17: =D17 -> -1.1566667 | AQ17: =K17+J17 -> 1.8126 | AR17: =I17 -> -1.3004 | AS17: =D17 -> -1.1566667 | AU17: =L17 -> 0.5122 | AV17: =N17 -> 0.2139 | AW17: =D17 -> -1.1566667 | AY17: =INDEX(LINEST($B$2:$B$68,$AU$2:$AW$68),1,4)+$T$37*L17+$T$38*N17+INDEX(LINEST($B$2:$B$68,$AU$2:$AW$68),1,1)*D17 -> -0.075223602 | AZ17: =B17-AY17 -> 0.0035569358 | BA17: =B17-$T$14*(L17-E17)-$T$15*D17 -> 0.22595465 | BB17: =$T$14*(E17-$E$2) -> 0.10392372 | BC17: =$T$14*(H17-$H$2) -> 0.091168333 | BD17: =$T$14*(J17-$J$2) -> 0.047996243 | BE17: =$T$14*(I17-$I$2) -> -0.15870649 | BF17: =B17-$B$2 -> -0.1025 | BG17: =B17-$B$2-$T$15*(D17-$D$2) -> 0.040986321
A18: 1975 | B18: =AVERAGEIFS(Analysis!$E$2:$E$823,Analysis!$B$2:$B$823,">="&A18,Analysis!$B$2:$B$823,"<"&(A18+1)) -> -0.013333333 | C18: =AVERAGEIFS(Analysis!$F$2:$F$823,Analysis!$B$2:$B$823,">="&A18,Analysis!$B$2:$B$823,"<"&(A18+1)) -> 0.24193918 | D18: =AVERAGEIFS(ENSO!$D$2:$D$823,Analysis!$B$2:$B$823,">="&A18,Analysis!$B$2:$B$823,"<"&(A18+1)) -> -0.8225 | E18: 0.9548 | F18: 0.3955 | G18: 0.0993 | H18: 0.6366 | I18: -1.2811 | J18: 0.2429 | K18: =E18+H18 -> 1.5914 | L18: =K18+I18+J18 -> 0.5532 | M18: -0.0405 | N18: 0.2035 | O18: =L18+M18+N18 -> 0.7162 | P18: =$T$13+$T$14*L18+$T$15*D18 -> -0.025479308 | Q18: =B18-P18 -> 0.012145974 | S18: lag-1 autocorrelation of residuals | T18: =CORREL($Q$2:$Q$67,$Q$3:$Q$68) -> 0.35745078 | AN18: =L18 -> 0.5532 | AO18: =D18 -> -0.8225 | AQ18: =K18+J18 -> 1.8343 | AR18: =I18 -> -1.2811 | AS18: =D18 -> -0.8225 | AU18: =L18 -> 0.5532 | AV18: =N18 -> 0.2035 | AW18: =D18 -> -0.8225 | AY18: =INDEX(LINEST($B$2:$B$68,$AU$2:$AW$68),1,4)+$T$37*L18+$T$38*N18+INDEX(LINEST($B$2:$B$68,$AU$2:$AW$68),1,1)*D18 -> -0.019630636 | AZ18: =B18-AY18 -> 0.0062973026 | BA18: =B18-$T$14*(L18-E18)-$T$15*D18 -> 0.23410893 | BB18: =$T$14*(E18-$E$2) -> 0.10433255 | BC18: =$T$14*(H18-$H$2) -> 0.099998987 | BD18: =$T$14*(J18-$J$2) -> 0.047628299 | BE18: =$T$14*(I18-$I$2) -> -0.15081613 | BF18: =B18-$B$2 -> -0.044166667 | BG18: =B18-$B$2-$T$15*(D18-$D$2) -> 0.065493661
A19: 1976 | B19: =AVERAGEIFS(Analysis!$E$2:$E$823,Analysis!$B$2:$B$823,">="&A19,Analysis!$B$2:$B$823,"<"&(A19+1)) -> -0.0975 | C19: =AVERAGEIFS(Analysis!$F$2:$F$823,Analysis!$B$2:$B$823,">="&A19,Analysis!$B$2:$B$823,"<"&(A19+1)) -> 0.24584257 | D19: =AVERAGEIFS(ENSO!$D$2:$D$823,Analysis!$B$2:$B$823,">="&A19,Analysis!$B$2:$B$823,"<"&(A19+1)) -> -0.58916667 | E19: 0.9667 | F19: 0.403 | G19: 0.1009 | H19: 0.6586 | I19: -1.3487 | J19: 0.2592 | K19: =E19+H19 -> 1.6253 | L19: =K19+I19+J19 -> 0.5358 | M19: -0.0434 | N19: 0.2041 | O19: =L19+M19+N19 -> 0.6965 | P19: =$T$13+$T$14*L19+$T$15*D19 -> -0.008973743 | Q19: =B19-P19 -> -0.088526257 | S19: naive SE of b → AR(1)-adjusted SE | T19: =INDEX(LINEST($B$2:$B$68,$AN$2:$AN$68:$AO$2:$AO$68,TRUE(),TRUE()),2,2) -> 0.011472148 | U19: =T19*SQRT((1+T18)/(1-T18)) -> 0.016674529 | AN19: =L19 -> 0.5358 | AO19: =D19 -> -0.58916667 | AQ19: =K19+J19 -> 1.8845 | AR19: =I19 -> -1.3487 | AS19: =D19 -> -0.58916667 | AU19: =L19 -> 0.5358 | AV19: =N19 -> 0.2041 | AW19: =D19 -> -0.58916667 | AY19: =INDEX(LINEST($B$2:$B$68,$AU$2:$AW$68),1,4)+$T$37*L19+$T$38*N19+INDEX(LINEST($B$2:$B$68,$AU$2:$AW$68),1,1)*D19 -> 0.0016212727 | AZ19: =B19-AY19 -> -0.099121273 | BA19: =B19-$T$14*(L19-E19)-$T$15*D19 -> 0.13830173 | BB19: =$T$14*(E19-$E$2) -> 0.10919759 | BC19: =$T$14*(H19-$H$2) -> 0.10899317 | BD19: =$T$14*(J19-$J$2) -> 0.054292173 | BE19: =$T$14*(I19-$I$2) -> -0.17845281 | BF19: =B19-$B$2 -> -0.12833333 | BG19: =B19-$B$2-$T$15*(D19-$D$2) -> -0.042292153
A20: 1977 | B20: =AVERAGEIFS(Analysis!$E$2:$E$823,Analysis!$B$2:$B$823,">="&A20,Analysis!$B$2:$B$823,"<"&(A20+1)) -> 0.17833333 | C20: =AVERAGEIFS(Analysis!$F$2:$F$823,Analysis!$B$2:$B$823,">="&A20,Analysis!$B$2:$B$823,"<"&(A20+1)) -> 0.25372587 | D20: =AVERAGEIFS(ENSO!$D$2:$D$823,Analysis!$B$2:$B$823,">="&A20,Analysis!$B$2:$B$823,"<"&(A20+1)) -> 0.52583333 | E20: 0.9968 | F20: 0.4108 | G20: 0.1026 | H20: 0.681 | I20: -1.3575 | J20: 0.2677 | K20: =E20+H20 -> 1.6778 | L20: =K20+I20+J20 -> 0.588 | M20: -0.0213 | N20: 0.2177 | O20: =L20+M20+N20 -> 0.7844 | P20: =$T$13+$T$14*L20+$T$15*D20 -> 0.12523279 | Q20: =B20-P20 -> 0.053100544 | S20: Do greenhouse gases and the other anthropogenic terms get the same response as aerosols? anomaly = a + g·(GHG + other anthro ERF) + h·aerosol ERF + c·ONI | T20: =(T14-1.96*U19)*T3 -> 1.478248 | U20: =(T14+1.96*U19)*T3 -> 1.7351291 | AN20: =L20 -> 0.588 | AO20: =D20 -> 0.52583333 | AQ20: =K20+J20 -> 1.9455 | AR20: =I20 -> -1.3575 | AS20: =D20 -> 0.52583333 | AU20: =L20 -> 0.588 | AV20: =N20 -> 0.2177 | AW20: =D20 -> 0.52583333 | AY20: =INDEX(LINEST($B$2:$B$68,$AU$2:$AW$68),1,4)+$T$37*L20+$T$38*N20+INDEX(LINEST($B$2:$B$68,$AU$2:$AW$68),1,1)*D20 -> 0.15921432 | AZ20: =B20-AY20 -> 0.019119015 | BA20: =B20-$T$14*(L20-E20)-$T$15*D20 -> 0.29223421 | BB20: =$T$14*(E20-$E$2) -> 0.12150327 | BC20: =$T$14*(H20-$H$2) -> 0.11815089 | BD20: =$T$14*(J20-$J$2) -> 0.057767199 | BE20: =$T$14*(I20-$I$2) -> -0.18205049 | BF20: =B20-$B$2 -> 0.1475 | BG20: =B20-$B$2-$T$15*(D20-$D$2) -> 0.1206754
A21: 1978 | B21: =AVERAGEIFS(Analysis!$E$2:$E$823,Analysis!$B$2:$B$823,">="&A21,Analysis!$B$2:$B$823,"<"&(A21+1)) -> 0.066666667 | C21: =AVERAGEIFS(Analysis!$F$2:$F$823,Analysis!$B$2:$B$823,">="&A21,Analysis!$B$2:$B$823,"<"&(A21+1)) -> 0.26049698 | D21: =AVERAGEIFS(ENSO!$D$2:$D$823,Analysis!$B$2:$B$823,">="&A21,Analysis!$B$2:$B$823,"<"&(A21+1)) -> 0.165 | E21: 1.0242 | F21: 0.4189 | G21: 0.1044 | H21: 0.7036 | I21: -1.3764 | J21: 0.2782 | K21: =E21+H21 -> 1.7278 | L21: =K21+I21+J21 -> 0.6296 | M21: 0.0276 | N21: 0.2203 | O21: =L21+M21+N21 -> 0.8775 | P21: =$T$13+$T$14*L21+$T$15*D21 -> 0.10571465 | Q21: =B21-P21 -> -0.039047985 | S21: g: °C per W/m² of GHG + other anthropogenic forcing | T21: =INDEX(LINEST($B$2:$B$68,$AQ$2:$AQ$68:$AS$2:$AS$68),1,3) -> 0.408678 | AN21: =L21 -> 0.6296 | AO21: =D21 -> 0.165 | AQ21: =K21+J21 -> 2.006 | AR21: =I21 -> -1.3764 | AS21: =D21 -> 0.165 | AU21: =L21 -> 0.6296 | AV21: =N21 -> 0.2203 | AW21: =D21 -> 0.165 | AY21: =INDEX(LINEST($B$2:$B$68,$AU$2:$AW$68),1,4)+$T$37*L21+$T$38*N21+INDEX(LINEST($B$2:$B$68,$AU$2:$AW$68),1,1)*D21 -> 0.13273905 | AZ21: =B21-AY21 -> -0.066072381 | BA21: =B21-$T$14*(L21-E21)-$T$15*D21 -> 0.21128753 | BB21: =$T$14*(E21-$E$2) -> 0.13270512 | BC21: =$T$14*(H21-$H$2) -> 0.12739037 | BD21: =$T$14*(J21-$J$2) -> 0.062059878 | BE21: =$T$14*(I21-$I$2) -> -0.18977731 | BF21: =B21-$B$2 -> 0.035833333 | BG21: =B21-$B$2-$T$15*(D21-$D$2) -> 0.045534055
A22: 1979 | B22: =AVERAGEIFS(Analysis!$E$2:$E$823,Analysis!$B$2:$B$823,">="&A22,Analysis!$B$2:$B$823,"<"&(A22+1)) -> 0.16416667 | C22: =AVERAGEIFS(Analysis!$F$2:$F$823,Analysis!$B$2:$B$823,">="&A22,Analysis!$B$2:$B$823,"<"&(A22+1)) -> 0.26659554 | D22: =AVERAGEIFS(ENSO!$D$2:$D$823,Analysis!$B$2:$B$823,">="&A22,Analysis!$B$2:$B$823,"<"&(A22+1)) -> 0.155 | E22: 1.0524 | F22: 0.4269 | G22: 0.1062 | H22: 0.7253 | I22: -1.3988 | J22: 0.2848 | K22: =E22+H22 -> 1.7777 | L22: =K22+I22+J22 -> 0.6637 | M22: 0.0741 | N22: 0.1957 | O22: =L22+M22+N22 -> 0.9335 | P22: =$T$13+$T$14*L22+$T$15*D22 -> 0.11864339 | Q22: =B22-P22 -> 0.045523277 | S22: h: °C per W/m² of aerosol forcing | T22: =INDEX(LINEST($B$2:$B$68,$AQ$2:$AQ$68:$AS$2:$AS$68),1,2) -> 0.41376443 | AN22: =L22 -> 0.6637 | AO22: =D22 -> 0.155 | AQ22: =K22+J22 -> 2.0625 | AR22: =I22 -> -1.3988 | AS22: =D22 -> 0.155 | AU22: =L22 -> 0.6637 | AV22: =N22 -> 0.1957 | AW22: =D22 -> 0.155 | AY22: =INDEX(LINEST($B$2:$B$68,$AU$2:$AW$68),1,4)+$T$37*L22+$T$38*N22+INDEX(LINEST($B$2:$B$68,$AU$2:$AW$68),1,1)*D22 -> 0.14211162 | AZ22: =B22-AY22 -> 0.022055048 | BA22: =B22-$T$14*(L22-E22)-$T$15*D22 -> 0.30738771 | BB22: =$T$14*(E22-$E$2) -> 0.14423403 | BC22: =$T$14*(H22-$H$2) -> 0.13626191 | BD22: =$T$14*(J22-$J$2) -> 0.064758134 | BE22: =$T$14*(I22-$I$2) -> -0.19893503 | BF22: =B22-$B$2 -> 0.13333333 | BG22: =B22-$B$2-$T$15*(D22-$D$2) -> 0.1440463
A23: 1980 | B23: =AVERAGEIFS(Analysis!$E$2:$E$823,Analysis!$B$2:$B$823,">="&A23,Analysis!$B$2:$B$823,"<"&(A23+1)) -> 0.25583333 | C23: =AVERAGEIFS(Analysis!$F$2:$F$823,Analysis!$B$2:$B$823,">="&A23,Analysis!$B$2:$B$823,"<"&(A23+1)) -> 0.27482719 | D23: =AVERAGEIFS(ENSO!$D$2:$D$823,Analysis!$B$2:$B$823,">="&A23,Analysis!$B$2:$B$823,"<"&(A23+1)) -> 0.34916667 | E23: 1.0864 | F23: 0.4347 | G23: 0.1084 | H23: 0.7471 | I23: -1.3939 | J23: 0.2836 | K23: =E23+H23 -> 1.8335 | L23: =K23+I23+J23 -> 0.7232 | M23: 0.0774 | N23: 0.1516 | O23: =L23+M23+N23 -> 0.9522 | P23: =$T$13+$T$14*L23+$T$15*D23 -> 0.16262308 | Q23: =B23-P23 -> 0.093210256 | S23: R² | T23: =INDEX(LINEST($B$2:$B$68,$AQ$2:$AQ$68:$AS$2:$AS$68,TRUE(),TRUE()),3,1) -> 0.95322247 | AN23: =L23 -> 0.7232 | AO23: =D23 -> 0.34916667 | AQ23: =K23+J23 -> 2.1171 | AR23: =I23 -> -1.3939 | AS23: =D23 -> 0.34916667 | AU23: =L23 -> 0.7232 | AV23: =N23 -> 0.1516 | AW23: =D23 -> 0.34916667 | AY23: =INDEX(LINEST($B$2:$B$68,$AU$2:$AW$68),1,4)+$T$37*L23+$T$38*N23+INDEX(LINEST($B$2:$B$68,$AU$2:$AW$68),1,1)*D23 -> 0.18388808 | AZ23: =B23-AY23 -> 0.071945253 | BA23: =B23-$T$14*(L23-E23)-$T$15*D23 -> 0.36897479 | BB23: =$T$14*(E23-$E$2) -> 0.15813413 | BC23: =$T$14*(H23-$H$2) -> 0.14517433 | BD23: =$T$14*(J23-$J$2) -> 0.064267542 | BE23: =$T$14*(I23-$I$2) -> -0.19693177 | BF23: =B23-$B$2 -> 0.225 | BG23: =B23-$B$2-$T$15*(D23-$D$2) -> 0.21605847
A24: 1981 | B24: =AVERAGEIFS(Analysis!$E$2:$E$823,Analysis!$B$2:$B$823,">="&A24,Analysis!$B$2:$B$823,"<"&(A24+1)) -> 0.32333333 | C24: =AVERAGEIFS(Analysis!$F$2:$F$823,Analysis!$B$2:$B$823,">="&A24,Analysis!$B$2:$B$823,"<"&(A24+1)) -> 0.28059167 | D24: =AVERAGEIFS(ENSO!$D$2:$D$823,Analysis!$B$2:$B$823,">="&A24,Analysis!$B$2:$B$823,"<"&(A24+1)) -> -0.2125 | E24: 1.106 | F24: 0.442 | G24: 0.1112 | H24: 0.7687 | I24: -1.3544 | J24: 0.279 | K24: =E24+H24 -> 1.8747 | L24: =K24+I24+J24 -> 0.7993 | M24: 0.0835 | N24: 0.1187 | O24: =L24+M24+N24 -> 1.0015 | P24: =$T$13+$T$14*L24+$T$15*D24 -> 0.13688012 | Q24: =B24-P24 -> 0.18645321 | S24: correlation between GHG and aerosol ERF series | T24: =CORREL($K$2:$K$68,$I$2:$I$68) -> 0.018611199 | AN24: =L24 -> 0.7993 | AO24: =D24 -> -0.2125 | AQ24: =K24+J24 -> 2.1537 | AR24: =I24 -> -1.3544 | AS24: =D24 -> -0.2125 | AU24: =L24 -> 0.7993 | AV24: =N24 -> 0.1187 | AW24: =D24 -> -0.2125 | AY24: =INDEX(LINEST($B$2:$B$68,$AU$2:$AW$68),1,4)+$T$37*L24+$T$38*N24+INDEX(LINEST($B$2:$B$68,$AU$2:$AW$68),1,1)*D24 -> 0.14247129 | AZ24: =B24-AY24 -> 0.18086205 | BA24: =B24-$T$14*(L24-E24)-$T$15*D24 -> 0.47023075 | BB24: =$T$14*(E24-$E$2) -> 0.16614713 | BC24: =$T$14*(H24-$H$2) -> 0.15400498 | BD24: =$T$14*(J24-$J$2) -> 0.06238694 | BE24: =$T$14*(I24-$I$2) -> -0.18078312 | BF24: =B24-$B$2 -> 0.2925 | BG24: =B24-$B$2-$T$15*(D24-$D$2) -> 0.34041313
A25: 1982 | B25: =AVERAGEIFS(Analysis!$E$2:$E$823,Analysis!$B$2:$B$823,">="&A25,Analysis!$B$2:$B$823,"<"&(A25+1)) -> 0.13916667 | C25: =AVERAGEIFS(Analysis!$F$2:$F$823,Analysis!$B$2:$B$823,">="&A25,Analysis!$B$2:$B$823,"<"&(A25+1)) -> 0.28634093 | D25: =AVERAGEIFS(ENSO!$D$2:$D$823,Analysis!$B$2:$B$823,">="&A25,Analysis!$B$2:$B$823,"<"&(A25+1)) -> 0.37416667 | E25: 1.1181 | F25: 0.4485 | G25: 0.1152 | H25: 0.7905 | I25: -1.393 | J25: 0.2961 | K25: =E25+H25 -> 1.9086 | L25: =K25+I25+J25 -> 0.8117 | M25: 0.027 | N25: -0.1985 | O25: =L25+M25+N25 -> 0.6402 | P25: =$T$13+$T$14*L25+$T$15*D25 -> 0.20133485 | Q25: =B25-P25 -> -0.062168188 | AN25: =L25 -> 0.8117 | AO25: =D25 -> 0.37416667 | AQ25: =K25+J25 -> 2.2047 | AR25: =I25 -> -1.393 | AS25: =D25 -> 0.37416667 | AU25: =L25 -> 0.8117 | AV25: =N25 -> -0.1985 | AW25: =D25 -> 0.37416667 | AY25: =INDEX(LINEST($B$2:$B$68,$AU$2:$AW$68),1,4)+$T$37*L25+$T$38*N25+INDEX(LINEST($B$2:$B$68,$AU$2:$AW$68),1,1)*D25 -> 0.17728189 | AZ25: =B25-AY25 -> -0.038115227 | BA25: =B25-$T$14*(L25-E25)-$T$15*D25 -> 0.22655615 | BB25: =$T$14*(E25-$E$2) -> 0.17109393 | BC25: =$T$14*(H25-$H$2) -> 0.1629174 | BD25: =$T$14*(J25-$J$2) -> 0.069377875 | BE25: =$T$14*(I25-$I$2) -> -0.19656383 | BF25: =B25-$B$2 -> 0.10833333 | BG25: =B25-$B$2-$T$15*(D25-$D$2) -> 0.096861176
A26: 1983 | B26: =AVERAGEIFS(Analysis!$E$2:$E$823,Analysis!$B$2:$B$823,">="&A26,Analysis!$B$2:$B$823,"<"&(A26+1)) -> 0.315 | C26: =AVERAGEIFS(Analysis!$F$2:$F$823,Analysis!$B$2:$B$823,">="&A26,Analysis!$B$2:$B$823,"<"&(A26+1)) -> 0.293402 | D26: =AVERAGEIFS(ENSO!$D$2:$D$823,Analysis!$B$2:$B$823,">="&A26,Analysis!$B$2:$B$823,"<"&(A26+1)) -> 1.175 | E26: 1.1456 | F26: 0.4542 | G26: 0.1171 | H26: 0.8094 | I26: -1.3101 | J26: 0.2774 | K26: =E26+H26 -> 1.955 | L26: =K26+I26+J26 -> 0.9223 | M26: 0.0275 | N26: -0.645 | O26: =L26+M26+N26 -> 0.3048 | P26: =$T$13+$T$14*L26+$T$15*D26 -> 0.32761537 | Q26: =B26-P26 -> -0.012615365 | S26: End-to-end check | AN26: =L26 -> 0.9223 | AO26: =D26 -> 1.175 | AQ26: =K26+J26 -> 2.2324 | AR26: =I26 -> -1.3101 | AS26: =D26 -> 1.175 | AU26: =L26 -> 0.9223 | AV26: =N26 -> -0.645 | AW26: =D26 -> 1.175 | AY26: =INDEX(LINEST($B$2:$B$68,$AU$2:$AW$68),1,4)+$T$37*L26+$T$38*N26+INDEX(LINEST($B$2:$B$68,$AU$2:$AW$68),1,1)*D26 -> 0.26087286 | AZ26: =B26-AY26 -> 0.054127142 | BA26: =B26-$T$14*(L26-E26)-$T$15*D26 -> 0.2873517 | BB26: =$T$14*(E26-$E$2) -> 0.18233667 | BC26: =$T$14*(H26-$H$2) -> 0.17064422 | BD26: =$T$14*(J26-$J$2) -> 0.061732817 | BE26: =$T$14*(I26-$I$2) -> -0.16267211 | BF26: =B26-$B$2 -> 0.28416667 | BG26: =B26-$B$2-$T$15*(D26-$D$2) -> 0.19163022
A27: 1984 | B27: =AVERAGEIFS(Analysis!$E$2:$E$823,Analysis!$B$2:$B$823,">="&A27,Analysis!$B$2:$B$823,"<"&(A27+1)) -> 0.155 | C27: =AVERAGEIFS(Analysis!$F$2:$F$823,Analysis!$B$2:$B$823,">="&A27,Analysis!$B$2:$B$823,"<"&(A27+1)) -> 0.30058891 | D27: =AVERAGEIFS(ENSO!$D$2:$D$823,Analysis!$B$2:$B$823,">="&A27,Analysis!$B$2:$B$823,"<"&(A27+1)) -> -0.55 | E27: 1.1706 | F27: 0.459 | G27: 0.1194 | H27: 0.828 | I27: -1.3375 | J27: 0.2883 | K27: =E27+H27 -> 1.9986 | L27: =K27+I27+J27 -> 0.9494 | M27: -0.0247 | N27: -0.2423 | O27: =L27+M27+N27 -> 0.6824 | P27: =$T$13+$T$14*L27+$T$15*D27 -> 0.16408158 | Q27: =B27-P27 -> -0.0090815829 | S27: anthro ERF change, 1959 to 2025 (W/m²) | T27: =L68-L2 -> 2.7977 | AN27: =L27 -> 0.9494 | AO27: =D27 -> -0.55 | AQ27: =K27+J27 -> 2.2869 | AR27: =I27 -> -1.3375 | AS27: =D27 -> -0.55 | AU27: =L27 -> 0.9494 | AV27: =N27 -> -0.2423 | AW27: =D27 -> -0.55 | AY27: =INDEX(LINEST($B$2:$B$68,$AU$2:$AW$68),1,4)+$T$37*L27+$T$38*N27+INDEX(LINEST($B$2:$B$68,$AU$2:$AW$68),1,1)*D27 -> 0.1155146 | AZ27: =B27-AY27 -> 0.0394854 | BA27: =B27-$T$14*(L27-E27)-$T$15*D27 -> 0.30110615 | BB27: =$T$14*(E27-$E$2) -> 0.19255733 | BC27: =$T$14*(H27-$H$2) -> 0.1782484 | BD27: =$T$14*(J27-$J$2) -> 0.066189027 | BE27: =$T$14*(I27-$I$2) -> -0.17387395 | BF27: =B27-$B$2 -> 0.12416667 | BG27: =B27-$B$2-$T$15*(D27-$D$2) -> 0.2062432
A28: 1985 | B28: =AVERAGEIFS(Analysis!$E$2:$E$823,Analysis!$B$2:$B$823,">="&A28,Analysis!$B$2:$B$823,"<"&(A28+1)) -> 0.11833333 | C28: =AVERAGEIFS(Analysis!$F$2:$F$823,Analysis!$B$2:$B$823,">="&A28,Analysis!$B$2:$B$823,"<"&(A28+1)) -> 0.3067888 | D28: =AVERAGEIFS(ENSO!$D$2:$D$823,Analysis!$B$2:$B$823,">="&A28,Analysis!$B$2:$B$823,"<"&(A28+1)) -> -0.71833333 | E28: 1.1944 | F28: 0.4641 | G28: 0.1212 | H28: 0.8478 | I28: -1.3503 | J28: 0.2938 | K28: =E28+H28 -> 2.0422 | L28: =K28+I28+J28 -> 0.9857 | M28: -0.0434 | N28: 0.0276 | O28: =L28+M28+N28 -> 0.9699 | P28: =$T$13+$T$14*L28+$T$15*D28 -> 0.16188246 | Q28: =B28-P28 -> -0.043549127 | S28: fitted warming over the same span (°C) | T28: =T14*T27 -> 1.1437742 | AN28: =L28 -> 0.9857 | AO28: =D28 -> -0.71833333 | AQ28: =K28+J28 -> 2.336 | AR28: =I28 -> -1.3503 | AS28: =D28 -> -0.71833333 | AU28: =L28 -> 0.9857 | AV28: =N28 -> 0.0276 | AW28: =D28 -> -0.71833333 | AY28: =INDEX(LINEST($B$2:$B$68,$AU$2:$AW$68),1,4)+$T$37*L28+$T$38*N28+INDEX(LINEST($B$2:$B$68,$AU$2:$AW$68),1,1)*D28 -> 0.14479703 | AZ28: =B28-AY28 -> -0.026463696 | BA28: =B28-$T$14*(L28-E28)-$T$15*D28 -> 0.27636868 | BB28: =$T$14*(E28-$E$2) -> 0.2022874 | BC28: =$T$14*(H28-$H$2) -> 0.18634317 | BD28: =$T$14*(J28-$J$2) -> 0.068437573 | BE28: =$T$14*(I28-$I$2) -> -0.17910694 | BF28: =B28-$B$2 -> 0.0875 | BG28: =B28-$B$2-$T$15*(D28-$D$2) -> 0.18661607
A29: 1986 | B29: =AVERAGEIFS(Analysis!$E$2:$E$823,Analysis!$B$2:$B$823,">="&A29,Analysis!$B$2:$B$823,"<"&(A29+1)) -> 0.18 | C29: =AVERAGEIFS(Analysis!$F$2:$F$823,Analysis!$B$2:$B$823,">="&A29,Analysis!$B$2:$B$823,"<"&(A29+1)) -> 0.31201398 | D29: =AVERAGEIFS(ENSO!$D$2:$D$823,Analysis!$B$2:$B$823,">="&A29,Analysis!$B$2:$B$823,"<"&(A29+1)) -> -0.0725 | E29: 1.2174 | F29: 0.4692 | G29: 0.1242 | H29: 0.8699 | I29: -1.352 | J29: 0.3027 | K29: =E29+H29 -> 2.0873 | L29: =K29+I29+J29 -> 1.038 | M29: -0.0426 | N29: 0.0226 | O29: =L29+M29+N29 -> 1.018 | P29: =$T$13+$T$14*L29+$T$15*D29 -> 0.24863852 | Q29: =B29-P29 -> -0.068638518 | AN29: =L29 -> 1.038 | AO29: =D29 -> -0.0725 | AQ29: =K29+J29 -> 2.39 | AR29: =I29 -> -1.352 | AS29: =D29 -> -0.0725 | AU29: =L29 -> 1.038 | AV29: =N29 -> 0.0226 | AW29: =D29 -> -0.0725 | AY29: =INDEX(LINEST($B$2:$B$68,$AU$2:$AW$68),1,4)+$T$37*L29+$T$38*N29+INDEX(LINEST($B$2:$B$68,$AU$2:$AW$68),1,1)*D29 -> 0.24331897 | AZ29: =B29-AY29 -> -0.06331897 | BA29: =B29-$T$14*(L29-E29)-$T$15*D29 -> 0.2606823 | BB29: =$T$14*(E29-$E$2) -> 0.21169042 | BC29: =$T$14*(H29-$H$2) -> 0.19537823 | BD29: =$T$14*(J29-$J$2) -> 0.07207613 | BE29: =$T$14*(I29-$I$2) -> -0.17980194 | BF29: =B29-$B$2 -> 0.14916667 | BG29: =B29-$B$2-$T$15*(D29-$D$2) -> 0.18290831
A30: 1987 | B30: =AVERAGEIFS(Analysis!$E$2:$E$823,Analysis!$B$2:$B$823,">="&A30,Analysis!$B$2:$B$823,"<"&(A30+1)) -> 0.32166667 | C30: =AVERAGEIFS(Analysis!$F$2:$F$823,Analysis!$B$2:$B$823,">="&A30,Analysis!$B$2:$B$823,"<"&(A30+1)) -> 0.31907046 | D30: =AVERAGEIFS(ENSO!$D$2:$D$823,Analysis!$B$2:$B$823,">="&A30,Analysis!$B$2:$B$823,"<"&(A30+1)) -> 1.1425 | E30: 1.2449 | F30: 0.4732 | G30: 0.1248 | H30: 0.8892 | I30: -1.3934 | J30: 0.3135 | K30: =E30+H30 -> 2.1341 | L30: =K30+I30+J30 -> 1.0542 | M30: -0.0254 | N30: 0.0983 | O30: =L30+M30+N30 -> 1.1271 | P30: =$T$13+$T$14*L30+$T$15*D30 -> 0.37824978 | Q30: =B30-P30 -> -0.056583118 | S30: Recent residual check (anthro ERF + ENSO model) | AN30: =L30 -> 1.0542 | AO30: =D30 -> 1.1425 | AQ30: =K30+J30 -> 2.4476 | AR30: =I30 -> -1.3934 | AS30: =D30 -> 1.1425 | AU30: =L30 -> 1.0542 | AV30: =N30 -> 0.0983 | AW30: =D30 -> 1.1425 | AY30: =INDEX(LINEST($B$2:$B$68,$AU$2:$AW$68),1,4)+$T$37*L30+$T$38*N30+INDEX(LINEST($B$2:$B$68,$AU$2:$AW$68),1,1)*D30 -> 0.40650803 | AZ30: =B30-AY30 -> -0.084841365 | BA30: =B30-$T$14*(L30-E30)-$T$15*D30 -> 0.28398043 | BB30: =$T$14*(E30-$E$2) -> 0.22293315 | BC30: =$T$14*(H30-$H$2) -> 0.20326859 | BD30: =$T$14*(J30-$J$2) -> 0.076491458 | BE30: =$T$14*(I30-$I$2) -> -0.19672736 | BF30: =B30-$B$2 -> 0.29083333 | BG30: =B30-$B$2-$T$15*(D30-$D$2) -> 0.2015867
A31: 1988 | B31: =AVERAGEIFS(Analysis!$E$2:$E$823,Analysis!$B$2:$B$823,">="&A31,Analysis!$B$2:$B$823,"<"&(A31+1)) -> 0.39 | C31: =AVERAGEIFS(Analysis!$F$2:$F$823,Analysis!$B$2:$B$823,">="&A31,Analysis!$B$2:$B$823,"<"&(A31+1)) -> 0.32886052 | D31: =AVERAGEIFS(ENSO!$D$2:$D$823,Analysis!$B$2:$B$823,">="&A31,Analysis!$B$2:$B$823,"<"&(A31+1)) -> -0.15583333 | E31: 1.2845 | F31: 0.4783 | G31: 0.1272 | H31: 0.9124 | I31: -1.4008 | J31: 0.3233 | K31: =E31+H31 -> 2.1969 | L31: =K31+I31+J31 -> 1.1194 | M31: 0.0137 | N31: 0.1513 | O31: =L31+M31+N31 -> 1.2844 | P31: =$T$13+$T$14*L31+$T$15*D31 -> 0.27348159 | Q31: =B31-P31 -> 0.11651841 | S31: mean residual 2023-2025 (°C) | T31: =AVERAGE(Q66:Q68) -> 0.13648318 | AN31: =L31 -> 1.1194 | AO31: =D31 -> -0.15583333 | AQ31: =K31+J31 -> 2.5202 | AR31: =I31 -> -1.4008 | AS31: =D31 -> -0.15583333 | AU31: =L31 -> 1.1194 | AV31: =N31 -> 0.1513 | AW31: =D31 -> -0.15583333 | AY31: =INDEX(LINEST($B$2:$B$68,$AU$2:$AW$68),1,4)+$T$37*L31+$T$38*N31+INDEX(LINEST($B$2:$B$68,$AU$2:$AW$68),1,1)*D31 -> 0.28278936 | AZ31: =B31-AY31 -> 0.10721064 | BA31: =B31-$T$14*(L31-E31)-$T$15*D31 -> 0.47327149 | BB31: =$T$14*(E31-$E$2) -> 0.23912268 | BC31: =$T$14*(H31-$H$2) -> 0.21275336 | BD31: =$T$14*(J31-$J$2) -> 0.080497958 | BE31: =$T$14*(I31-$I$2) -> -0.19975268 | BF31: =B31-$B$2 -> 0.35916667 | BG31: =B31-$B$2-$T$15*(D31-$D$2) -> 0.40134372
A32: 1989 | B32: =AVERAGEIFS(Analysis!$E$2:$E$823,Analysis!$B$2:$B$823,">="&A32,Analysis!$B$2:$B$823,"<"&(A32+1)) -> 0.27416667 | C32: =AVERAGEIFS(Analysis!$F$2:$F$823,Analysis!$B$2:$B$823,">="&A32,Analysis!$B$2:$B$823,"<"&(A32+1)) -> 0.33505818 | D32: =AVERAGEIFS(ENSO!$D$2:$D$823,Analysis!$B$2:$B$823,">="&A32,Analysis!$B$2:$B$823,"<"&(A32+1)) -> -1.0191667 | E32: 1.3104 | F32: 0.4837 | G32: 0.1307 | H32: 0.9352 | I32: -1.3841 | J32: 0.326 | K32: =E32+H32 -> 2.2456 | L32: =K32+I32+J32 -> 1.1875 | M32: 0.0774 | N32: 0.188 | O32: =L32+M32+N32 -> 1.4529 | P32: =$T$13+$T$14*L32+$T$15*D32 -> 0.21393184 | Q32: =B32-P32 -> 0.060234827 | S32: mean residual 1959-2022 (°C) | T32: =AVERAGE(Q2:Q65) -> -0.0063976489 | AN32: =L32 -> 1.1875 | AO32: =D32 -> -1.0191667 | AQ32: =K32+J32 -> 2.5716 | AR32: =I32 -> -1.3841 | AS32: =D32 -> -1.0191667 | AU32: =L32 -> 1.1875 | AV32: =N32 -> 0.188 | AW32: =D32 -> -1.0191667 | AY32: =INDEX(LINEST($B$2:$B$68,$AU$2:$AW$68),1,4)+$T$37*L32+$T$38*N32+INDEX(LINEST($B$2:$B$68,$AU$2:$AW$68),1,1)*D32 -> 0.210702 | AZ32: =B32-AY32 -> 0.063464663 | BA32: =B32-$T$14*(L32-E32)-$T$15*D32 -> 0.42757652 | BB32: =$T$14*(E32-$E$2) -> 0.24971129 | BC32: =$T$14*(H32-$H$2) -> 0.22207461 | BD32: =$T$14*(J32-$J$2) -> 0.08160179 | BE32: =$T$14*(I32-$I$2) -> -0.19292527 | BF32: =B32-$B$2 -> 0.24333333 | BG32: =B32-$B$2-$T$15*(D32-$D$2) -> 0.37290123
A33: 1990 | B33: =AVERAGEIFS(Analysis!$E$2:$E$823,Analysis!$B$2:$B$823,">="&A33,Analysis!$B$2:$B$823,"<"&(A33+1)) -> 0.44916667 | C33: =AVERAGEIFS(Analysis!$F$2:$F$823,Analysis!$B$2:$B$823,">="&A33,Analysis!$B$2:$B$823,"<"&(A33+1)) -> 0.34014661 | D33: =AVERAGEIFS(ENSO!$D$2:$D$823,Analysis!$B$2:$B$823,">="&A33,Analysis!$B$2:$B$823,"<"&(A33+1)) -> 0.16 | E33: 1.3305 | F33: 0.4867 | G33: 0.1337 | H33: 0.9531 | I33: -1.3994 | J33: 0.3317 | K33: =E33+H33 -> 2.2836 | L33: =K33+I33+J33 -> 1.2159 | M33: 0.0671 | N33: 0.1837 | O33: =L33+M33+N33 -> 1.4667 | P33: =$T$13+$T$14*L33+$T$15*D33 -> 0.34490356 | Q33: =B33-P33 -> 0.1042631 | S33: aerosol ERF change 2019 to 2025 (W/m²) | T33: =I68-I62 -> 0.1511 | AN33: =L33 -> 1.2159 | AO33: =D33 -> 0.16 | AQ33: =K33+J33 -> 2.6153 | AR33: =I33 -> -1.3994 | AS33: =D33 -> 0.16 | AU33: =L33 -> 1.2159 | AV33: =N33 -> 0.1837 | AW33: =D33 -> 0.16 | AY33: =INDEX(LINEST($B$2:$B$68,$AU$2:$AW$68),1,4)+$T$37*L33+$T$38*N33+INDEX(LINEST($B$2:$B$68,$AU$2:$AW$68),1,1)*D33 -> 0.3641211 | AZ33: =B33-AY33 -> 0.08504557 | BA33: =B33-$T$14*(L33-E33)-$T$15*D33 -> 0.47982221 | BB33: =$T$14*(E33-$E$2) -> 0.2579287 | BC33: =$T$14*(H33-$H$2) -> 0.22939261 | BD33: =$T$14*(J33-$J$2) -> 0.083932102 | BE33: =$T$14*(I33-$I$2) -> -0.19918032 | BF33: =B33-$B$2 -> 0.41833333 | BG33: =B33-$B$2-$T$15*(D33-$D$2) -> 0.42854018
A34: 1991 | B34: =AVERAGEIFS(Analysis!$E$2:$E$823,Analysis!$B$2:$B$823,">="&A34,Analysis!$B$2:$B$823,"<"&(A34+1)) -> 0.4075 | C34: =AVERAGEIFS(Analysis!$F$2:$F$823,Analysis!$B$2:$B$823,">="&A34,Analysis!$B$2:$B$823,"<"&(A34+1)) -> 0.34522236 | D34: =AVERAGEIFS(ENSO!$D$2:$D$823,Analysis!$B$2:$B$823,">="&A34,Analysis!$B$2:$B$823,"<"&(A34+1)) -> 0.44416667 | E34: 1.3514 | F34: 0.492 | G34: 0.136 | H34: 0.9702 | I34: -1.4889 | J34: 0.3673 | K34: =E34+H34 -> 2.3216 | L34: =K34+I34+J34 -> 1.2 | M34: 0.0533 | N34: -0.5286 | O34: =L34+M34+N34 -> 0.7247 | P34: =$T$13+$T$14*L34+$T$15*D34 -> 0.36716797 | Q34: =B34-P34 -> 0.040332031 | S34: implied temperature effect at b (°C) | T34: =T33*T14 -> 0.0617737 | AN34: =L34 -> 1.2 | AO34: =D34 -> 0.44416667 | AQ34: =K34+J34 -> 2.6889 | AR34: =I34 -> -1.4889 | AS34: =D34 -> 0.44416667 | AU34: =L34 -> 1.2 | AV34: =N34 -> -0.5286 | AW34: =D34 -> 0.44416667 | AY34: =INDEX(LINEST($B$2:$B$68,$AU$2:$AW$68),1,4)+$T$37*L34+$T$38*N34+INDEX(LINEST($B$2:$B$68,$AU$2:$AW$68),1,1)*D34 -> 0.2997548 | AZ34: =B34-AY34 -> 0.1077452 | BA34: =B34-$T$14*(L34-E34)-$T$15*D34 -> 0.42443561 | BB34: =$T$14*(E34-$E$2) -> 0.26647318 | BC34: =$T$14*(H34-$H$2) -> 0.23638354 | BD34: =$T$14*(J34-$J$2) -> 0.098486329 | BE34: =$T$14*(I34-$I$2) -> -0.2357703 | BF34: =B34-$B$2 -> 0.37666667 | BG34: =B34-$B$2-$T$15*(D34-$D$2) -> 0.35810877
